Workbook
Name a_cr: Design!$C$83
Name A_cust: Design!$C$41
Name A_emp: Design!$C$170
Name A_hold: Design!$C$520
Name A_tyre: Design!$C$310
Name ac_type: Design!$C$40
Name ACN: Design!$C$313
Name aisle_w: Design!$C$52
Name aisle1: Design!$C$245
Name aisle1_b: Design!$C$251
Name aisle2: Design!$C$246
Name aisle2_b: Design!$C$252
Name alpha_cr: Design!$E$649
Name AR_: Design!$E$641
Name AR_HT: Design!$C$61
Name AR_VT: Design!$C$62
Name arm_frac: Design!$C$60
Name B_box: Plot_Data!$AT$1
Name b_HT: Design!$C$275
Name b_VT: Design!$C$280
Name b_w: Design!$C$223
Name beta_cr: Design!$C$88
Name beta_xw: Design!$C$478
Name BFL: Design!$C$387
Name BPR: Design!$C$65
Name brake_g: Design!$C$352
Name bus_frac: Design!$C$26
Name bus_pitch: Design!$C$27
Name c_cabin: Design!$C$528
Name c_cap: Design!$C$530
Name C_cust: Design!$C$42
Name C_emp: Design!$C$171
Name c_fuel: Design!$C$526
Name c_HT: Design!$C$58
Name c_pilot: Design!$C$527
Name c_price: Design!$C$529
Name c_root: Design!$C$227
Name c_tip: Design!$C$228
Name c_VT: Design!$C$59
Name CD_0: Design!$E$643
Name CD_cr: Design!$C$140
Name CD0_est: Design!$C$492
Name cg_aft: Design!$C$448
Name cg_fwd: Design!$C$447
Name cg_MTOM: Design!$D$443
Name chk_ACN: Design!$C$314
Name chk_alt: Design!$C$408
Name chk_BFL: Design!$C$388
Name chk_CD0: Design!$C$494
Name chk_ceil: Design!$C$366
Name chk_clear: Design!$C$341
Name chk_climb: Design!$C$397
Name chk_fin: Design!$C$476
Name chk_fuel: Design!$C$233
Name chk_gear: Design!$C$460
Name chk_hold: Design!$C$523
Name chk_LD: Design!$C$351
Name chk_rot: Design!$C$473
Name chk_SM: Design!$C$456
Name chk_tailfit: Design!$C$463

Sheet Design
A1: AIRCRAFT PRELIMINARY SIZING - change the yellow cells; every value and drawing recalculates
A2: All variables are in columns A-E, colour coded by discipline (key below the results panel). Key results are in G-I. Drawings are to the right (column K onward).
A3: 1. REQUIRED PARAMETERS | B3: Name | C3: Value | D3: Unit | E3: Method / note | G3: KEY RESULTS | H3: Value | I3: Unit
A4: Aspect ratio | B4: AR_ | C4: 9.5 | D4: - | E4: AR [used by: wing sizing, constraints] | G4: Max take-off mass (MTOM) | H4: =(MTOW)*IF(unit_sys="Imperial",2.20462,1) -> 71061.951 | I4: =IF(unit_sys="Imperial","lb","kg") -> kg
A5: Oswald efficiency factor | B5: e_os | C5: 0.8 | D5: - | E5: e [used by: constraints, weight] | G5: Operating empty mass | H5: =(OEW)*IF(unit_sys="Imperial",2.20462,1) -> 35727.3 | I5: =IF(unit_sys="Imperial","lb","kg") -> kg
A6: Zero-lift drag coefficient (clean) | B6: CD_0 | C6: 0.018 | D6: - | E6: CDo [used by: constraints, weight] | G6: Mission fuel (design mission) | H6: =(W_fuel)*IF(unit_sys="Imperial",2.20462,1) -> 21084.651 | I6: =IF(unit_sys="Imperial","lb","kg") -> kg
A7: Maximum payload | B7: PyldMax | C7: 17500 | D7: kg | E7: PyldMax - sets MZFW and the max-payload range point [used by: weight, payload-range] | G7: Design payload | H7: =(W_pl)*IF(unit_sys="Imperial",2.20462,1) -> 14250 | I7: =IF(unit_sys="Imperial","lb","kg") -> kg
A8: Take-off distance available | B8: TODA | C8: 2200 | D8: m | E8: TODA - balanced take-off field length [used by: take-off constraint] | G8: Design wing loading W/S | H8: =(WS_des)*IF(unit_sys="Imperial",0.0208854,1) -> 5281.0085 | I8: =IF(unit_sys="Imperial","lb/ft2","N/m2") -> N/m2
A9: Landing distance available | B9: LDA | C9: 1670 | D9: m | E9: LDA - landing field length [used by: landing constraint] | G9: Design wing loading m/S | H9: =(WS_des/grav)*IF(unit_sys="Imperial",0.204816,1) -> 538.513 | I9: =IF(unit_sys="Imperial","lb/ft2","kg/m2") -> kg/m2
A10: CLmax, take-off configuration | B10: CLmaxTO | C10: 2.1 | D10: - | E10: 'Takeoff' - ASSUMED to mean CLmax in take-off configuration [used by: take-off and climb constraints] | G10: Design thrust-to-weight T/W (SL static) | H10: =TW_des -> 0.27275334 | I10: -
A11: CLmax, landing configuration | B11: CLmaxL | C11: 2.7 | D11: - | E11: 'Landing' - ASSUMED to mean CLmax in landing configuration [used by: landing and climb constraints] | G11: Critical constraint | H11: =crit_con -> Take-off + cruise
A12: Cruise thrust lapse T_cruise / T_SL,static | B12: alpha_cr | C12: 0.22 | D12: - | E12: acr - ASSUMED to be the thrust lapse ratio used in the cruise constraint [used by: cruise constraint, engine sizing] | G12: Wing area S | H12: =(S_ref)*IF(unit_sys="Imperial",10.7639,1) -> 131.95958 | I12: =IF(unit_sys="Imperial","ft2","m2") -> m2
A13: Cruise Mach number | B13: MCR | C13: 0.78 | D13: - | E13: MCR [used by: cruise constraint, wing sweep, weight] | G13: Wing span b | H13: =(b_w)*IF(unit_sys="Imperial",3.28084,1) -> 35.406441 | I13: =IF(unit_sys="Imperial","ft","m") -> m
A14: Thrust-specific fuel consumption in cruise | B14: TSFC_in | C14: 0.6 | D14: 1/h | E14: TSFCcr - pick the unit in column D (1/h = lb/lbf/h = kg/kgf/h) [used by: weight (fuel), payload-range] | G14: Mean aerodynamic chord | H14: =(MAC)*IF(unit_sys="Imperial",3.28084,1) -> 4.174233 | I14: =IF(unit_sys="Imperial","ft","m") -> m
A15: Typical passenger count | B15: PaxTyp | C15: 150 | D15: pax | E15: PaxTyp [used by: fuselage and cabin, weight] | G15: Quarter-chord sweep | H15: =sweep25 -> 26.176952 | I15: deg
A16: Design range with typical payload | B16: RangeTyp | C16: 5000 | D16: km | E16: RangeTyp - pick km or nm in column D [used by: weight (fuel)] | G16: Total SL static thrust | H16: =(T_SL/1000)*IF(unit_sys="Imperial",224.809,1) -> 190.07626 | I16: =IF(unit_sys="Imperial","lbf","kN") -> kN
A17: Typical passenger payload (total) | B17: PayPax | C17: 14250 | D17: kg | E17: Payload_typPax - TOTAL payload of the typical passenger load, in kg (not per passenger) [used by: weight (payload)] | G17: Thrust per engine | H17: =(T_eng/1000)*IF(unit_sys="Imperial",224.809,1) -> 95.038128 | I17: =IF(unit_sys="Imperial","lbf","kN") -> kN
G18: Cruise L/D | H18: =LD_cr -> 17.459659 | I18: -
A19: 2. SECONDARY ASSUMPTIONS (defaults - edit if your brief specifies them) | B19: Name | C19: Value | D19: Unit | E19: Method / note | G19: Fuselage length | H19: =(L_fus)*IF(unit_sys="Imperial",3.28084,1) -> 35.62096 | I19: =IF(unit_sys="Imperial","ft","m") -> m
A20: Cruise altitude | B20: h_cr | C20: 10668 | D20: m | E20: 35 000 ft. ISA atmosphere | G20: Fuselage outer diameter | H20: =(d_fus)*IF(unit_sys="Imperial",3.28084,1) -> 3.98185 | I20: =IF(unit_sys="Imperial","ft","m") -> m
A21: Airport altitude | B21: h_apt | C21: 0 | D21: m | E21: ISA; must be below 11 000 m | G21: Seats abreast x rows | H21: =n_SA&" x "&n_rows -> 6 x 25
A22: Units shown in the key results panel | B22: unit_sys | C22: SI | E22: SI or Imperial (lb, ft, nm, lbf) | G22: Horizontal tail area | H22: =(S_HT)*IF(unit_sys="Imperial",10.7639,1) -> 34.363666 | I22: =IF(unit_sys="Imperial","ft2","m2") -> m2
A23: Empty weight method | B23: ew_mode | C23: Fraction | E23: Fraction = guessed We/W0 (section 4). Build-up = component weights (section 12) fed back into the take-off mass | G23: Vertical tail area | H23: =(S_VT)*IF(unit_sys="Imperial",10.7639,1) -> 26.232977 | I23: =IF(unit_sys="Imperial","ft2","m2") -> m2
A24: Automatic wing placement | B24: wing_auto | C24: Yes | E24: Yes = the wing is positioned to give the target static margin. No = use the manual position below | G24: Main gear: struts x wheels per strut | H24: =n_struts&" x "&n_wps -> 2 x 2
A25: Target static margin at the most aft CG | B25: SM_target | C25: 0.1 | D25: MAC | E25: Used by the automatic wing placement | G25: Main tyre diameter x width | H25: =TEXT(D_tyre,"0.00")&" x "&TEXT(w_tyre,"0.00") -> 1.15 x 0.42 | I25: m
A26: Business-class share of passengers | B26: bus_frac | C26: 0 | D26: - | E26: 0 = single class. Business seats are fewer abreast, at the pitch below | G26: Range with maximum payload | H26: =(R_maxpl)*IF(unit_sys="Imperial",0.539957,1) -> 3590.0086 | I26: =IF(unit_sys="Imperial","nm","km") -> km
A27: Business seat pitch | B27: bus_pitch | C27: 0.97 | D27: m | E27: 38 in | G27: Take-off field length achieved | H27: =(TOFL)*IF(unit_sys="Imperial",3.28084,1) -> 2200 | I27: =IF(unit_sys="Imperial","ft","m") -> m
A28: Number of engines | B28: N_eng | C28: 2 | D28: - | E28: 2, 3 or 4 - drives the one-engine-inoperative climb constraints | G28: Landing field length achieved | H28: =(LFL)*IF(unit_sys="Imperial",3.28084,1) -> 1584.41 | I28: =IF(unit_sys="Imperial","ft","m") -> m
A29: Max landing mass / max take-off mass | B29: ML_ratio | C29: 0.85 | D29: - | E29: Typical 0.75 (long range) to 0.95 (short range) | G29: Service ceiling | H29: =(h_serv)*IF(unit_sys="Imperial",3.28084,1) -> 11258.711 | I29: =IF(unit_sys="Imperial","ft","m") -> m
A30: Residual climb rate at top of climb | B30: ROC_cr | C30: 1.5 | D30: m/s | E30: 300 ft/min; set 0 for a pure level-cruise constraint | G30: Time to climb to cruise altitude | H30: =t_climb -> 18.762342 | I30: min
A31: Landing field coefficient k_L | B31: k_L | C31: 0.107 | D31: kg/m3 | E31: Loftin/Scholz: m_ML/S = k_L * sigma * CLmaxL * LDA (V_app = 1.70*sqrt(LDA)) | G31: Design limit load factor | H31: =n_lim -> 2.5 | I31: -
A32: Take-off field coefficient k_TO | B32: k_TO | C32: 2.34 | D32: m3/kg | E32: Loftin/Scholz: (T/W)/(m/S) = k_TO / (TODA * sigma * CLmaxTO) | G32: Static margin at MTOM | H32: =SM_MTOM -> 0.11294174 | I32: MAC
A33: Landing gear drag increment (landing climb) | B33: dCD0_gear | C33: 0.015 | D33: - | E33: FAR 25 missed approach is flown gear-down | G33: CDo from drag build-up | H33: =CD0_est -> 0.019308435 | I33: -
A34: Fuel fraction: engine start & taxi | B34: ff_taxi | C34: 0.97 | D34: - | E34: Historical regression constant | G34: Empty mass from component build-up | H34: =(W_e_build)*IF(unit_sys="Imperial",2.20462,1) -> 35844.589 | I34: =IF(unit_sys="Imperial","lb","kg") -> kg
A35: Fuel fraction: take-off | B35: ff_TO | C35: 0.985 | D35: - | E35: Historical regression constant | G35: Cost per seat-kilometre | H35: =cost_skm -> 4.5953793 | I35: US cents
A36: Fuel fraction: climb | B36: ff_climb | C36: 0.985 | D36: - | E36: Historical regression constant | G36: Closest real aircraft | H36: =cmp_name -> Airbus A320-200
A37: Fuel fraction: descent | B37: ff_desc | C37: 0.99 | D37: - | E37: Historical regression constant | G37: Balanced field length (Raymer) | H37: =(BFL)*IF(unit_sys="Imperial",3.28084,1) -> 2247.103 | I37: =IF(unit_sys="Imperial","ft","m") -> m
A38: Fuel fraction: reserves / hold | B38: ff_res | C38: 0.95 | D38: - | E38: Historical regression constant | G38: Best initial cruise altitude | H38: =(h_best)*IF(unit_sys="Imperial",3.28084,1) -> 11258.711 | I38: =IF(unit_sys="Imperial","ft","m") -> m
A39: Reserve and trapped fuel factor | B39: k_res | C39: 1.06 | D39: - | E39: Raymer: Wf/W0 = 1.06 * (1 - Mff) | G39: CO2 per seat-kilometre | H39: =co2_skm -> 72.46083 | I39: g
A40: Aircraft type for the empty weight guess | B40: ac_type | C40: Auto | E40: Auto = chosen from PaxTyp and MCR. Or pick a type from the list (table in section 4) | G40: Main tyre pressure | H40: =p_tyre -> 1.0849083 | I40: MPa
A41: Custom empty weight coefficient A | B41: A_cust | C41: 0.97 | D41: - | E41: Only used when the aircraft type is Custom (W0 in kg) | G41: Requirements met | H41: =n_met&" of 14" -> 14 of 14
A42: Custom empty weight exponent C | B42: C_cust | C42: -0.06 | D42: - | E42: Only used when the aircraft type is Custom
A43: Flight crew | B43: N_flight | C43: 2 | D43: - | G43: CHECKS
A44: Passengers per cabin crew member | B44: pax_per_cc | C44: 50 | D44: pax | E44: Regulatory minimum is 1 per 50 seats | G44: Weight iteration | H44: =chk_weight -> OK - converged
A45: Mass per crew member incl. baggage | B45: m_crew | C45: 93 | D45: kg | G45: Max payload >= design payload | H45: =IF(PyldMax>=W_pl,"OK","FAIL - PyldMax is below Payload_typPax") -> OK
A46: Wing taper ratio | B46: taper | C46: 0.25 | D46: - | G46: Payload per passenger plausible | H46: =IF(OR(PaxTyp<=0,AND(W_pl/MAX(1,PaxTyp)>=60,W_pl/MAX(1,PaxTyp)<=200)),"OK","CHECK - Payload_typPax must be the total payload in kg: "&TEXT(W_pl/MAX(1,PaxTyp),"#,##0")&" kg per passenger") -> OK
A47: Wing dihedral | B47: dihedral | C47: 5 | D47: deg | E47: Low-wing transport | G47: Range with maximum payload | H47: =IF(R_maxpl>0,"OK","ZERO - at PyldMax the fuel left is below the fixed allowances; raise RangeTyp (check km / nm) or lower PyldMax") -> OK
A48: Wing aerodynamic centre / fuselage length (manual) | B48: xw_in | C48: 0.46 | D48: - | E48: Used only when automatic wing placement is set to No | G48: Wing fuel volume | H48: =chk_fuel -> OK
A49: Korn technology factor | B49: kappa | C49: 0.95 | D49: - | E49: 0.95 supercritical, 0.87 conventional aerofoil | G49: Gear tip-back angle >= 15 deg | H49: =chk_tipback -> OK
A50: Fuel density | B50: rho_fuel | C50: 800 | D50: kg/m3 | E50: Jet A-1 | G50: Engine ground clearance | H50: =chk_clear -> OK
A51: Seat width incl. armrest share | B51: seat_w | C51: 0.53 | D51: m | E51: Economy | G51: Thrust lapse / TSFC unit plausibility | H51: =IF(AND(TSFC_s>0.00005,TSFC_s<0.0005,alpha_cr>0.05,alpha_cr<=1),"OK","CHECK - TSFC unit or thrust lapse looks out of range") -> OK
A52: Aisle width | B52: aisle_w | C52: 0.5 | D52: m | G52: Take-off distance | H52: =chk_TO -> OK - 0 m margin on TODA
A53: Seat pitch | B53: seat_pitch | C53: 0.81 | D53: m | E53: 32 in economy | G53: Landing distance | H53: =chk_LD -> OK - 86 m margin on LDA
A54: Door / galley zone length (each end) | B54: door_len | C54: 1.5 | D54: m | E54: Entry door, galley and crew seats at the front and rear of the cabin | G54: Service ceiling | H54: =chk_ceil -> OK - 591 m above cruise altitude
A55: Lavatory size (square) | B55: lav_len | C55: 1 | D55: m | G55: Static stability | H55: =chk_SM -> OK
A56: Passengers per lavatory | B56: pax_per_lav | C56: 50 | D56: pax | E56: Typical 40-60 | G56: Gear position vs calculated CG | H56: =chk_gear -> OK
A57: Nose / cockpit length | B57: nose_len | C57: 4 | D57: m | E57: Scholz: fuselage length = cabin + 1.6 d + 4 m | G57: CDo input vs build-up | H57: =chk_CD0 -> OK - within 20 % of the build-up
A58: Horizontal tail volume coefficient | B58: c_HT | C58: 1 | D58: - | E58: Raymer Table 6.4 jet transport | G58: Cargo hold volume | H58: =chk_hold -> OK
A59: Vertical tail volume coefficient | B59: c_VT | C59: 0.09 | D59: - | E59: Raymer Table 6.4 jet transport | G59: Climb gradients (engine out) | H59: =chk_climb -> OK - every climb requirement is met
A60: Tail arm / fuselage length | B60: arm_frac | C60: 0.45 | D60: - | E60: Raymer: 0.50-0.55 wing-mounted engines, 0.45-0.50 aft engines | G60: Balanced field length cross-check | H60: =chk_BFL -> NOTE - Raymer BFL is 47 m over TODA (the sizing used the Loftin correlation)
A61: Horizontal tail aspect ratio | B61: AR_HT | C61: 4.5 | D61: - | G61: Trim on approach | H61: =chk_trim -> OK
A62: Vertical tail aspect ratio | B62: AR_VT | C62: 1.7 | D62: - | G62: Take-off rotation | H62: =chk_rot -> OK
A63: Horizontal tail taper ratio | B63: taper_HT | C63: 0.4 | D63: - | G63: Engine-failure control | H63: =chk_fin -> OK
A64: Vertical tail taper ratio | B64: taper_VT | C64: 0.35 | D64: - | G64: Crosswind control | H64: =chk_xw -> OK
A65: Engine bypass ratio | B65: BPR | C65: 5 | D65: - | E65: Used only for engine mass and size | G65: Seats drawn | H65: =IF(AND(n_rows<=60,n_rows_b<=20),"OK","Drawings show the first 60 economy and 20 business rows only") -> OK
A66: Inboard engine spanwise position / semi-span | B66: eta_in | C66: 0.34 | D66: - | E66: Wing-mounted engines | G66: Tailplane position | H66: =chk_tailfit -> OK
A67: Outboard engine spanwise position / semi-span | B67: eta_out | C67: 0.62 | D67: - | E67: Used with 4 engines. With 3 engines the third is on the tail centreline | G67: Tyre pressure and pavement loading | H67: =chk_ACN -> OK for major airports (PCN 60-80)
A68: Static load share on main gear | B68: main_frac | C68: 0.92 | D68: - | E68: Raymer: 0.85-0.92 (nose gear 8-15 %)
A69: Tyre load growth margin | B69: tyre_margin | C69: 1.07 | D69: - | E69: FAR 25 adds 7 % | G69: COLOUR KEY
A70: Nose tyre size / main tyre size | B70: nose_scale | C70: 0.65 | D70: - | E70: Raymer: 60-100 % | G70: Requirements (your parameters) | H70: data rows
A71: Wheelbase / fuselage length | B71: wb_frac | C71: 0.38 | D71: - | E71: Typical 0.33-0.42 | G71: Assumptions | H71: data rows
A72: CG height above ground / fuselage diameter | B72: hcg_fac | C72: 0.92 | D72: - | E72: Low-wing transport with underwing engines | G72: Constraint analysis: W/S and T/W | H72: data rows
A73: Vertical touchdown speed | B73: V_vert | C73: 3.05 | D73: m/s | E73: FAR 25: 10 ft/s | G73: Weight estimation and payload-range | H73: data rows
A74: Gear load factor | B74: N_gear | C74: 3 | D74: - | E74: Raymer: transports 2.7-3 | G74: Wing sizing | H74: data rows
A75: 3D view: rotation about vertical axis | B75: view_az | C75: 40 | D75: deg | E75: Change to rotate the 3D drawing (0 = side view) | G75: Fuselage and cabin | H75: data rows
A76: 3D view: elevation | B76: view_el | C76: 25 | D76: deg | E76: Change to tilt the 3D drawing (90 = top view) | G76: Tail sizing | H76: data rows
A77: Gravitational acceleration | B77: grav | C77: 9.80665 | D77: m/s2 | G77: Engine requirements | H77: data rows
A78: Sea-level air density | B78: rho_SL | C78: 1.225 | D78: kg/m3 | E78: ISA | G78: Landing gear | H78: data rows
G79: Layout geometry and drawings | H79: data rows
A80: 3. CONSTRAINT ANALYSIS - atmosphere and cruise condition | B80: Name | C80: Value | D80: Unit | E80: Method / note | G80: Performance | H80: data rows
A81: Cruise temperature | B81: T_cr | C81: =IF(h_cr<=11000,288.15-0.0065*h_cr,216.65) -> 218.808 | D81: K | E81: ISA | G81: Weight breakdown, balance and stability | H81: data rows
A82: Cruise density | B82: rho_cr | C82: =IF(h_cr<=11000,rho_SL*(T_cr/288.15)^4.25588,0.36392*EXP(-(h_cr-11000)/6341.62)) -> 0.37959679 | D82: kg/m3 | E82: ISA | G82: Aerodynamics and controls | H82: data rows
A83: Cruise speed of sound | B83: a_cr | C83: =SQRT(1.4*287.053*T_cr) -> 296.53548 | D83: m/s | G83: Operating cost | H83: data rows
A84: Cruise true airspeed | B84: V_cr | C84: =MCR*a_cr -> 231.29767 | D84: m/s | G84: Comparison with real aircraft | H84: data rows
A85: Cruise dynamic pressure | B85: q_cr | C85: =0.5*rho_cr*V_cr^2 -> 10153.951 | D85: Pa
A86: Airport density ratio sigma | B86: sigma | C86: =(1-0.0065*h_apt/288.15)^4.25588 -> 1 | D86: - | E86: ISA | G86: Yellow cell = a value you enter
A87: Induced drag factor K | B87: K_ind | C87: =1/(PI()*AR_*e_os) -> 0.04188288 | D87: - | E87: CD = CD0 + K*CL^2 | G87: Blue text = an editable input or constant
A88: Weight fraction at start of cruise | B88: beta_cr | C88: =ff_taxi*ff_TO*ff_climb -> 0.94111825 | D88: - | E88: W_cruise / W_take-off | G88: Black text = calculated
A89: Cruise curve coefficient a | B89: cr_a | C89: =q_cr*CD_0/alpha_cr -> 830.77782 | D89: N/m2 | E89: Cruise T/W = a/(W/S) + b*(W/S) + c (zero-lift drag term)
A90: Cruise curve coefficient b | B90: cr_b | C90: =K_ind*beta_cr^2/(alpha_cr*q_cr) -> 1.6606082e-05 | D90: m2/N | E90: Induced drag term
A91: Cruise curve coefficient c | B91: cr_c | C91: =beta_cr*ROC_cr/(alpha_cr*V_cr) -> 0.027742239 | D91: - | E91: Residual climb term
A93: Landing field length (vertical line - maximum wing loading) | B93: Name | C93: Value | D93: Unit | E93: Method / note
A94: Max landing wing loading m_ML/S | B94: mS_L | C94: =k_L*sigma*CLmaxL*LDA -> 482.463 | D94: kg/m2 | E94: Loftin: approach speed limited by LDA
A95: Max take-off wing loading W/S | B95: WS_max | C95: =mS_L*grav/ML_ratio -> 5566.2892 | D95: N/m2 | E95: Referred to take-off weight
A97: Take-off field length (T/W = slope x W/S) | B97: Name | C97: Value | D97: Unit | E97: Method / note
A98: Slope (T/W) per (N/m2) | B98: TO_slope | C98: =k_TO/(TODA*sigma*CLmaxTO*grav) -> 5.1647964e-05 | D98: m2/N | E98: T/W >= k_TO*(m/S)/(TODA*sigma*CLmaxTO)
A100: Second-segment climb, one engine inoperative (horizontal line) | B100: Name | C100: Value | D100: Unit | E100: Method / note
A101: Required climb gradient | B101: grad_2 | C101: =0.024+0.003*(N_eng-2) -> 0.024 | D101: - | E101: FAR/CS 25.121: 2.4 / 2.7 / 3.0 % for 2 / 3 / 4 engines
A102: Lift coefficient at V2 = 1.2 Vs | B102: CL_2 | C102: =CLmaxTO/1.44 -> 1.4583333 | D102: -
A103: Flap drag increment | B103: dCD0_f2 | C103: =MAX(0,0.05*CL_2-0.055) -> 0.017916667 | D103: - | E103: Scholz
...

Sheet Summary
A1: AIRCRAFT DESIGN SUMMARY
A3: =IF(Design!G4="","",Design!G4) -> Max take-off mass (MTOM) | B3: =IF(Design!H4="","",Design!H4) -> 71061.951 | C3: =IF(Design!I4="","",Design!I4) -> kg
A4: =IF(Design!G5="","",Design!G5) -> Operating empty mass | B4: =IF(Design!H5="","",Design!H5) -> 35727.3 | C4: =IF(Design!I5="","",Design!I5) -> kg
A5: =IF(Design!G6="","",Design!G6) -> Mission fuel (design mission) | B5: =IF(Design!H6="","",Design!H6) -> 21084.651 | C5: =IF(Design!I6="","",Design!I6) -> kg
A6: =IF(Design!G7="","",Design!G7) -> Design payload | B6: =IF(Design!H7="","",Design!H7) -> 14250 | C6: =IF(Design!I7="","",Design!I7) -> kg
A7: =IF(Design!G8="","",Design!G8) -> Design wing loading W/S | B7: =IF(Design!H8="","",Design!H8) -> 5281.0085 | C7: =IF(Design!I8="","",Design!I8) -> N/m2
A8: =IF(Design!G9="","",Design!G9) -> Design wing loading m/S | B8: =IF(Design!H9="","",Design!H9) -> 538.513 | C8: =IF(Design!I9="","",Design!I9) -> kg/m2
A9: =IF(Design!G10="","",Design!G10) -> Design thrust-to-weight T/W (SL static) | B9: =IF(Design!H10="","",Design!H10) -> 0.27275334 | C9: =IF(Design!I10="","",Design!I10) -> -
A10: =IF(Design!G11="","",Design!G11) -> Critical constraint | B10: =IF(Design!H11="","",Design!H11) -> Take-off + cruise | C10: =IF(Design!I11="","",Design!I11)
A11: =IF(Design!G12="","",Design!G12) -> Wing area S | B11: =IF(Design!H12="","",Design!H12) -> 131.95958 | C11: =IF(Design!I12="","",Design!I12) -> m2
A12: =IF(Design!G13="","",Design!G13) -> Wing span b | B12: =IF(Design!H13="","",Design!H13) -> 35.406441 | C12: =IF(Design!I13="","",Design!I13) -> m
A13: =IF(Design!G14="","",Design!G14) -> Mean aerodynamic chord | B13: =IF(Design!H14="","",Design!H14) -> 4.174233 | C13: =IF(Design!I14="","",Design!I14) -> m
A14: =IF(Design!G15="","",Design!G15) -> Quarter-chord sweep | B14: =IF(Design!H15="","",Design!H15) -> 26.176952 | C14: =IF(Design!I15="","",Design!I15) -> deg
... A66: =IF(Design!G67="","",Design!G67) -> Tyre pressure and pavement loading | B66: =IF(Design!H67="","",Design!H67) -> OK for major airports (PCN 60-80) | C66: =IF(Design!I67="","",Design!I67)
A68: REQUIREMENT | B68: Required / Achieved | C68: Status
A69: =Design!A621 -> Aspect ratio | B69: =IF(ISNUMBER(Design!B621),IF(Design!B621=INT(Design!B621),TEXT(Design!B621,"#,##0"),TEXT(Design!B621,"0.000")),Design!B621)&" / "&IF(ISNUMBER(Design!C621),IF(Design!C621=INT(Design!C621),TEXT(Design!C621,"#,##0"),TEXT(Design!C621,"0.000")),Design!C621) -> 9.500 / 9.500 | C69: =Design!D621 -> OK
A70: =Design!A622 -> Oswald efficiency factor | B70: =IF(ISNUMBER(Design!B622),IF(Design!B622=INT(Design!B622),TEXT(Design!B622,"#,##0"),TEXT(Design!B622,"0.000")),Design!B622)&" / "&IF(ISNUMBER(Design!C622),IF(Design!C622=INT(Design!C622),TEXT(Design!C622,"#,##0"),TEXT(Design!C622,"0.000")),Design!C622) -> 0.800 / 0.800 | C70: =Design!D622 -> Used as given
A71: =Design!A623 -> Zero-lift drag coefficient | B71: =IF(ISNUMBER(Design!B623),IF(Design!B623=INT(Design!B623),TEXT(Design!B623,"#,##0"),TEXT(Design!B623,"0.000")),Design!B623)&" / "&IF(ISNUMBER(Design!C623),IF(Design!C623=INT(Design!C623),TEXT(Design!C623,"#,##0"),TEXT(Design!C623,"0.000")),Design!C623) -> 0.018 / 0.019 | C71: =Design!D623 -> OK
A72: =Design!A624 -> Maximum payload (kg) | B72: =IF(ISNUMBER(Design!B624),IF(Design!B624=INT(Design!B624),TEXT(Design!B624,"#,##0"),TEXT(Design!B624,"0.000")),Design!B624)&" / "&IF(ISNUMBER(Design!C624),IF(Design!C624=INT(Design!C624),TEXT(Design!C624,"#,##0"),TEXT(Design!C624,"0.000")),Design!C624) -> 17,500 / 17,500 | C72: =Design!D624 -> OK
A73: =Design!A625 -> Take-off distance available (m) | B73: =IF(ISNUMBER(Design!B625),IF(Design!B625=INT(Design!B625),TEXT(Design!B625,"#,##0"),TEXT(Design!B625,"0.000")),Design!B625)&" / "&IF(ISNUMBER(Design!C625),IF(Design!C625=INT(Design!C625),TEXT(Design!C625,"#,##0"),TEXT(Design!C625,"0.000")),Design!C625) -> 2,200 / 2,200 | C73: =Design!D625 -> OK
A74: =Design!A626 -> Landing distance available (m) | B74: =IF(ISNUMBER(Design!B626),IF(Design!B626=INT(Design!B626),TEXT(Design!B626,"#,##0"),TEXT(Design!B626,"0.000")),Design!B626)&" / "&IF(ISNUMBER(Design!C626),IF(Design!C626=INT(Design!C626),TEXT(Design!C626,"#,##0"),TEXT(Design!C626,"0.000")),Design!C626) -> 1,670 / 1584.410 | C74: =Design!D626 -> OK
A75: =Design!A627 -> CLmax, take-off | B75: =IF(ISNUMBER(Design!B627),IF(Design!B627=INT(Design!B627),TEXT(Design!B627,"#,##0"),TEXT(Design!B627,"0.000")),Design!B627)&" / "&IF(ISNUMBER(Design!C627),IF(Design!C627=INT(Design!C627),TEXT(Design!C627,"#,##0"),TEXT(Design!C627,"0.000")),Design!C627) -> 2.100 / 2.100 | C75: =Design!D627 -> OK
A76: =Design!A628 -> CLmax, landing | B76: =IF(ISNUMBER(Design!B628),IF(Design!B628=INT(Design!B628),TEXT(Design!B628,"#,##0"),TEXT(Design!B628,"0.000")),Design!B628)&" / "&IF(ISNUMBER(Design!C628),IF(Design!C628=INT(Design!C628),TEXT(Design!C628,"#,##0"),TEXT(Design!C628,"0.000")),Design!C628) -> 2.700 / 2.700 | C76: =Design!D628 -> OK
A77: =Design!A629 -> Cruise thrust lapse | B77: =IF(ISNUMBER(Design!B629),IF(Design!B629=INT(Design!B629),TEXT(Design!B629,"#,##0"),TEXT(Design!B629,"0.000")),Design!B629)&" / "&IF(ISNUMBER(Design!C629),IF(Design!C629=INT(Design!C629),TEXT(Design!C629,"#,##0"),TEXT(Design!C629,"0.000")),Design!C629) -> 0.220 / 0.198 | C77: =Design!D629 -> OK
A78: =Design!A630 -> Cruise Mach number | B78: =IF(ISNUMBER(Design!B630),IF(Design!B630=INT(Design!B630),TEXT(Design!B630,"#,##0"),TEXT(Design!B630,"0.000")),Design!B630)&" / "&IF(ISNUMBER(Design!C630),IF(Design!C630=INT(Design!C630),TEXT(Design!C630,"#,##0"),TEXT(Design!C630,"0.000")),Design!C630) -> 0.780 / 0.820 | C78: =Design!D630 -> OK
A79: =Design!A631 -> Cruise TSFC | B79: =IF(ISNUMBER(Design!B631),IF(Design!B631=INT(Design!B631),TEXT(Design!B631,"#,##0"),TEXT(Design!B631,"0.000")),Design!B631)&" / "&IF(ISNUMBER(Design!C631),IF(Design!C631=INT(Design!C631),TEXT(Design!C631,"#,##0"),TEXT(Design!C631,"0.000")),Design!C631) -> 0.600 / 0.600 | C79: =Design!D631 -> Used as given
A80: =Design!A632 -> Typical passengers | B80: =IF(ISNUMBER(Design!B632),IF(Design!B632=INT(Design!B632),TEXT(Design!B632,"#,##0"),TEXT(Design!B632,"0.000")),Design!B632)&" / "&IF(ISNUMBER(Design!C632),IF(Design!C632=INT(Design!C632),TEXT(Design!C632,"#,##0"),TEXT(Design!C632,"0.000")),Design!C632) -> 150 / 150 | C80: =Design!D632 -> OK
... A82: =Design!A634 -> Typical passenger payload (kg) | B82: =IF(ISNUMBER(Design!B634),IF(Design!B634=INT(Design!B634),TEXT(Design!B634,"#,##0"),TEXT(Design!B634,"0.000")),Design!B634)&" / "&IF(ISNUMBER(Design!C634),IF(Design!C634=INT(Design!C634),TEXT(Design!C634,"#,##0"),TEXT(Design!C634,"0.000")),Design!C634) -> 14,250 / 14,250 | C82: =Design!D634 -> OK

Sheet Plot_Data
A1: CHART DATA - calculated automatically from the Design sheet. Nothing to edit here. | AS1: Drawing box size (m) | AT1: =1.1*MAX(L_fus,b_w) -> 39.183056
A4: W/S / landing limit | B4: W/S (N/m2) | C4: m/S (kg/m2) | D4: Take-off | E4: 2nd segment OEI | F4: Missed approach OEI | G4: Cruise | H4: Required T/W | K4: Landing W/S | L4: T/W | S4: Station | T4: x (m) | U4: radius (m) | V4: z centre (m) | X4: x centred | Y4: side view z | Z4: top view y | AA4: x from nose | AC4: x centred | AD4: y | AE4: z | AG4: span fraction | AH4: y | AI4: x front | AJ4: z centre | AL4: x centred | AM4: y | AN4: z | AP4: x centred | AQ4: z | AS4: box x | AT4: box y | AV4: seat column | AW4: column used | AX4: lane edge y | AY4: row used | AZ4: row start x | BA4: cabin x | BB4: cabin y | BD4: X | BE4: Y | BF4: Z | BG4: screen u | BH4: screen v | BK4: Legend text | BM4: seat line x | BN4: seat line y | BO4: seat line x centred | BQ4: pilot seat x | BR4: pilot seat y | BT4: lavatory | BU4: used | BV4: front? | BW4: index in zone | BX4: x start | BY4: y low | CA4: outline x | CB4: outline y | CE4: CL clean | CF4: CD clean | CG4: L/D clean | CH4: CL take-off | CI4: CD take-off | CJ4: L/D take-off | CK4: CL landing | CL4: CD landing | CM4: L/D landing | CN4: cruise CD | CO4: cruise CL | CP4: cruise L/D | CR4: altitude m | CS4: T (K) | CT4: density | CU4: speed of sound | CV4: T/W available | CW4: best-climb speed | CX4: rate of climb m/s | CY4: climb time s | CZ4: discriminant | DA4: min speed | DB4: max speed | DC4: min Mach | DD4: max Mach | DE4: cruise alt line x | DF4: cruise alt line y | DG4: cruise Mach | DH4: cruise altitude | DJ4: V (m/s EAS) | DK4: n manoeuvre | DL4: V gust + | DM4: n gust + | DN4: V gust - | DO4: n gust - | DQ4: CG % MAC | DR4: mass kg | DS4: neutral point | DT4: mass | DU4: aft limit | DV4: mass | DX4: fuselage y | DY4: fuselage z | DZ4: surface y | EA4: surface z | EB4: engine y | EC4: engine z | ED4: gear y | EE4: gear z | EG4: skin y | EH4: skin z | EI4: lining y | EJ4: lining z | EK4: floor y | EL4: floor z | EM4: seat y | EN4: seat z | EO4: box | EP4: box | ER4: exit x | ES4: exit y | ET4: galley x | EU4: galley y | EW4: case | EX4: payload kg | EY4: fuel fraction | EZ4: A | GA4: aircraft | GB4: passengers | GC4: MTOM kg | GD4: OEW kg | GE4: wing area m2 | GF4: span m | GG4: length m | GH4: thrust per engine kN | GI4: engines | GJ4: range km | GK4: distance score | GZ4: wing placement solver | HA4: trial 1 | HB4: trial 2 | HC4: wing position needed | HF4: W0 guess | HG4: wing area | HH4: span | HI4: root chord | HJ4: MAC | HK4: wing | HL4: tails | HM4: fuselage | HN4: gear | HO4: engines | HP4: systems | HQ4: empty mass | HR4: W0 new | HT4: seat column | HU4: column used | HV4: lane edge y | HW4: row used | HX4: row start x | HY4: seat line x | HZ4: seat line y | IA4: seat line x centred | IC4: tank x centred | ID4: tank y
A5: =10/50 -> 0.2 | B5: =A5*WS_max -> 1113.2578 | C5: =B5/grav -> 113.52071 | D5: =TO_slope*B5 -> 0.0574975 | E5: =TW_2 -> 0.21941554 | F5: =TW_MA -> 0.21104328 | G5: =beta_cr/alpha_cr*(q_cr*CD_0/(beta_cr*B5)+K_ind*beta_cr*B5/q_cr+ROC_cr/V_cr) -> 0.79248732 | H5: =MAX(D5:G5) -> 0.79248732 | K5: =WS_max -> 5566.2892 | L5: 0 | S5: nose 0.00 | T5: =0*nose_len -> 0 | U5: =d_fus/2*SQRT(1-(1-0)^2) -> 0 | V5: =-0.3*(d_fus/2-U5) -> -0.5972775 | X5: =T5-L_fus/2 -> -17.81048 | Y5: =V5+1*U5 -> -0.5972775 | Z5: =1*U5 -> 0 | AA5: =T5 -> 0 | AC5: =x_wLE0-L_fus/2 -> -7.3048467 | AD5: 0 | AE5: =z_w0 -> -1.194555 | AG5: =eta_in -> 0.34 | AH5: =AG5*b_w/2 -> 6.0190949 | AI5: =IF(AG5=0,L_fus-tail_len-0.2*L_nac,x_wLE0+ABS(AH5)*TAN(RADIANS(sweepLE))-0.8*L_nac) -> 10.385503 | AJ5: =IF(AG5=0,z_VT0+0.55*D_nac,z_w0+ABS(AH5)*TAN(RADIANS(dihedral))-0.6*D_nac) -> -2.0075068 | AL5: =AI5+0*L_nac-L_fus/2 -> -7.4249768 | AM5: =AH5+-1*D_nac/2 -> 4.9027996 | AN5: =AJ5+-1*D_nac/2 -> -3.1238022 | AP5: =x_main-L_fus/2+0*D_tyre/2 -> -0.30456748 | AQ5: =-h_cg+D_tyre/2+1*D_tyre/2 -> -2.5108116 | AS5: =-1*B_box/2 -> -19.591528 | AT5: =-1*B_box/2 -> -19.591528 | AV5: 0 | AW5: =MIN(AV5,n_SA-1) -> 0 | AX5: =-w_cabin/2+0.025+(1)*(AW5*seat_w+aisle_w*((AW5>=aisle1)+(AW5>=aisle2))) -> -1.84 | AY5: =MAX(0,MIN(0,n_rows-1)) -> 0 | AZ5: =x_eco0+AY5*(seat_pitch) -> 6.5 | BA5: =nose_len+0*L_cabin -> 4 | BB5: =-1*w_cabin/2 -> -1.865 | BC5: =BA5-L_fus/2 -> -13.81048 | BD5: =T5-L_fus/2 -> -17.81048 | BE5: =U5*1 -> 0 | BF5: =V5+U5*0 -> -0.5972775 | BG5: =BD5*COS(RADIANS(view_az))+BE5*SIN(RADIANS(view_az)) -> -13.643619 | BH5: =BF5*COS(RADIANS(view_el))+(BE5*COS(RADIANS(view_az))-BD5*SIN(RADIANS(view_az)))*SIN(RADIANS(view_el)) -> 4.296967 | BK5: ="Fuselage: L = "&TEXT(L_fus,"0.0")&" m, d = "&TEXT(d_fus,"0.00")&" m" -> Fuselage: L = 35.6 m, d = 3.98 m | BM5: =$AZ$5+0.2*(seat_pitch)*($AY$5*n_SA+$AW$5<pax_e) -> 6.662 | BN5: =$AX$5 -> -1.84 | BO5: =BM5-L_fus/2 -> -11.14848 | BQ5: =0.5*nose_len+0*MIN(0.6,0.2*nose_len) -> 2 | BR5: =-1*MIN(0.55,0.2*d_fus)+-1*MIN(0.5,0.25*d_fus)/2 -> -0.8 | BT5: 0 | BU5: =MIN(BT5,n_lav-1) -> 0 | BV5: =IF(BU5<n_lav_front,1,0) -> 1 | BW5: =IF(BV5=1,BU5,BU5-n_lav_front) -> 0 | BX5: =IF(BV5=1,nose_len,x_seat_end+door_len)+INT(BW5/lav_slots)*lav_len -> 4 | BY5: =CHOOSE(MOD(BW5,lav_slots)+1,-w_cabin/2,w_cabin/2-lav_w,-lav_w/2) -> -1.865 | CA5: =$BX$5+0*lav_len -> 4 | CB5: =$BY$5+0*lav_w -> -1.865 | CE5: =0/24*CLmax_c -> 0 | CF5: =CD_0+K_ind*CE5^2 -> 0.018 | CG5: =CE5/CF5 -> 0 | CH5: =0/24*CLmaxTO -> 0 | CI5: =CD_0+dCD0_f2+K_ind*CH5^2 -> 0.035916667 | CJ5: =CH5/CI5 -> 0 | CK5: =0/24*CLmaxL -> 0 | CL5: =CD_0+dCD0_fMA+dCD0_gear+K_ind*CK5^2 -> 0.057881657 | CM5: =CK5/CL5 -> 0 | CN5: =CD_cr -> 0.028034333 | CO5: =CL_cr -> 0.4894699 | CP5: =LD_cr -> 17.459659 | CR5: =0/28*h_abs -> 0 | CS5: =IF(CR5<=11000,288.15-0.0065*CR5,216.65) -> 288.15 | CT5: =IF(CR5<=11000,rho_SL*(CS5/288.15)^4.25588,0.36392*EXP(-(CR5-11000)/6341.62)) -> 1.225 | CU5: =SQRT(1.4*287.053*CS5) -> 340.29407 | CV5: =TW_p*(CT5/rho_SL)^lapse_n -> 0.28981835 | CW5: =MIN(M_MO*CU5,SQRT(CV5*WS_p*(1+SQRT(1+3/(LD_max^2*CV5^2)))/(3*CT5*CD_0))) -> 211.40613 | CX5: =MAX(0,CW5*(CV5-0.5*CT5*CW5^2*CD_0/WS_p-K_ind*WS_p/(0.5*CT5*CW5^2))) -> 38.702804 | CY5: =IF(CR5>=h_cr,0,(MIN(CR6,h_cr)-CR5)/MAX(0.05,(CX5+CX6)/2)) -> 10.904192 | CZ5: =MAX(0,CV5^2-4*CD_0*K_ind) -> 0.080979107 | DA5: =MAX(SQRT(2*WS_p/(CT5*CLmax_c)),SQRT(2*WS_p*(CV5-SQRT(CZ5))/(2*CD_0)/CT5)) -> 73.549861 | DB5: =MAX(DA5,MIN(M_MO*CU5,SQRT(2*WS_p*(CV5+SQRT(CZ5))/(2*CD_0)/CT5))) -> 279.04113 | DC5: =DA5/CU5 -> 0.21613618 | DD5: =DB5/CU5 -> 0.82 | DE5: 0 | DF5: =h_cr -> 10668 | DG5: =MCR -> 0.78 | DH5: =h_cr -> 10668 | DJ5: =0/10*V_A -> 0 | DK5: =(0/10*V_A/V_S1)^2 -> 0 | DL5: 0 | DM5: 1 | DN5: 0 | DO5: 1 | DQ5: =Design!$D$441 -> 0.43553093 | DR5: =Design!$B$441 -> 35727.3 | DS5: =x_np -> 0.57069573 | DT5: =0.95*OEW -> 33940.935 | DU5: =x_np-0.05 -> 0.52069573 | DV5: =0.95*OEW -> 33940.935 | DX5: =d_fus/2*1 -> 1.990925 | DY5: =d_fus/2*0 -> 0 | DZ5: =-b_w/2 -> -17.70322 | EA5: =z_w0+b_w/2*TAN(RADIANS(dihedral)) -> 0.35427609 | EB5: =$AH$5+D_nac/2*1 -> 7.1353903 | EC5: =$AJ$5+D_nac/2*0 -> -2.0075068 | ED5: =-track/2+0*2.2*w_tyre/2 -> -3.5406441 | EE5: =z_w0+track/2*TAN(RADIANS(dihedral)) -> -0.88478878 | EG5: =d_fus/2*1 -> 1.990925 | EH5: =d_fus/2*0 -> 0 | EI5: =w_cabin/2*1 -> 1.865 | EJ5: =w_cabin/2*0 -> 0 | EK5: =-1*SQRT(MAX(0,(w_cabin/2)^2-(z_floor)^2)) -> -1.7658497 | EL5: =z_floor -> -0.6 | EM5: =$AX$5+0.05*seat_w -> -1.8135 | EN5: =z_floor+0 -> -0.6 | EO5: =-1*0.6*d_fus -> -2.38911 | EP5: =-1*0.6*d_fus -> -2.38911 | ER5: =IF(0<n_door,x_door_f+IF(n_door>1,0/(n_door-1),0)*(x_door_r-x_door_f),IF(0<n_door+n_overwing,x_ac_w+(0-n_door-(n_overwing-1)/2)*seat_pitch,x_door_f)) -> 5.75 | ES5: =-1*w_cabin/2 -> -1.865 | ET5: =x_seat0-door_len+0*0.6 -> 5 | EU5: =w_cabin/2-gal_w+0*gal_w -> 0.265 | EW5: Range x 0.9 | EX5: =W_pl -> 14250 | EY5: =k_res*(1-ff_fixed*EXP(-Range_km*0.9*1000*TSFC_s*1/(V_cr*LD_cr))) -> 0.2807936 | EZ5: =A_emp -> 0.97 | FA5: =MTOW_frac -> 71061.951 | FB5: =IF(1-$EY5-$EZ5*FA5^C_emp>0.02,(W_crew+$EX5)/(1-$EY5-$EZ5*FA5^C_emp),FA5) -> 65990.314 | FC5: =IF(1-$EY5-$EZ5*FB5^C_emp>0.02,(W_crew+$EX5)/(1-$EY5-$EZ5*FB5^C_emp),FB5) -> 66650.711 | FD5: =IF(1-$EY5-$EZ5*FC5^C_emp>0.02,(W_crew+$EX5)/(1-$EY5-$EZ5*FC5^C_emp),FC5) -> 66560.958 | FE5: =IF(1-$EY5-$EZ5*FD5^C_emp>0.02,(W_crew+$EX5)/(1-$EY5-$EZ5*FD5^C_emp),FD5) -> 66573.086 | FF5: =IF(1-$EY5-$EZ5*FE5^C_emp>0.02,(W_crew+$EX5)/(1-$EY5-$EZ5*FE5^C_emp),FE5) -> 66571.446 | FG5: =IF(1-$EY5-$EZ5*FF5^C_emp>0.02,(W_crew+$EX5)/(1-$EY5-$EZ5*FF5^C_emp),FF5) -> 66571.668 | FH5: =IF(1-$EY5-$EZ5*FG5^C_emp>0.02,(W_crew+$EX5)/(1-$EY5-$EZ5*FG5^C_emp),FG5) -> 66571.638 | FI5: =IF(1-$EY5-$EZ5*FH5^C_emp>0.02,(W_crew+$EX5)/(1-$EY5-$EZ5*FH5^C_emp),FH5) -> 66571.642 | ... FY5: =IF(1-$EY5-$EZ5*FX5^C_emp>0.02,(W_crew+$EX5)/(1-$EY5-$EZ5*FX5^C_emp),FX5) -> 66571.641 | GA5: Cessna Citation CJ3 | GB5: 7 | GC5: 6291 | GD5: 3850 | GE5: 27.3 | GF5: 16.26 | GG5: 15.59 | GH5: 12.5 | GI5: 2 | GJ5: 3480 | GK5: =ABS(LN(GC5/MTOW))+ABS(LN(MAX(1,GB5)/MAX(1,PaxTyp))) -> 5.4891571 | GZ5: wing position / length | HA5: 0.38 | HB5: 0.54 | HF5: =MTOW_frac -> 71061.951 | HG5: =HF5*grav/WS_des -> 131.95958 | HH5: =SQRT(AR_*HG5) -> 35.406441 | HI5: =2*HG5/(HH5*(1+taper)) -> 5.96319 | HJ5: =2/3*HI5*(1+taper+taper^2)/(1+taper) -> 4.174233 | HK5: =49*MAX(0.5*HG5,HG5-d_fus*HI5*(1-(1-taper)*d_fus/(2*HH5))) -> 5351.6052 | HL5: =27*(c_HT*HJ5*HG5/L_tail+c_VT*HH5*HG5/L_tail) -> 1636.1094 | HM5: =24*S_wet_fus -> 9147.0379 | HN5: =0.043*HF5 -> 3055.6639 | HO5: =1.3*N_eng*14.7*(TW_des*HF5*grav/N_eng/1000)^1.1*EXP(-0.045*BPR) -> 4573.6411 | HP5: =0.17*HF5 -> 12080.532 | HQ5: =SUM(HK5:HP5) -> 35844.589 | HR5: =IF(fuel_frac<0.95,MIN(100*MTOW_frac,(W_crew+W_pl+HQ5)/(1-fuel_frac)),HF5) -> 71889.899 | HT5: 0 | HU5: =MIN(HT5,n_SA_b-1) -> 0 | HV5: =-w_cabin/2+0.025+(n_rows_b>0)*(HU5*seat_w_b+aisle_w*((HU5>=aisle1_b)+(HU5>=aisle2_b))) -> -1.84 | HW5: =MAX(0,MIN(0,n_rows_b-1)) -> 0 | HX5: =x_seat0+HW5*(bus_pitch*(n_rows_b>0)) -> 6.5 | HY5: =$HX$5+0.2*(bus_pitch*(n_rows_b>0))*($HW$5*n_SA_b+$HU$5<pax_b) -> 6.5 | HZ5: =$HV$5 -> -1.84 | IA5: =HY5-L_fus/2 -> -11.31048 | IC5: =x_wLE0+(d_fus/2)*TAN(RADIANS(sweepLE))-L_fus/2+0.15*c_root*(1-(1-taper)*2*(d_fus/2)/b_w) -> -5.3814091 | ID5: =1*d_fus/2 -> 1.990925
A6: =11/50 -> 0.22 | B6: =A6*WS_max -> 1224.5836 | C6: =B6/grav -> 124.87278 | D6: =TO_slope*B6 -> 0.06324725 | E6: =TW_2 -> 0.21941554 | F6: =TW_MA -> 0.21104328 | G6: =beta_cr/alpha_cr*(q_cr*CD_0/(beta_cr*B6)+K_ind*beta_cr*B6/q_cr+ROC_cr/V_cr) -> 0.72649435 | H6: =MAX(D6:G6) -> 0.72649435 | K6: =WS_max -> 5566.2892 | L6: 0.8 | S6: nose 0.02 | T6: =0.02*nose_len -> 0.08 | U6: =d_fus/2*SQRT(1-(1-0.02)^2) -> 0.39618907 | V6: =-0.3*(d_fus/2-U6) -> -0.47842078 | X6: =T6-L_fus/2 -> -17.73048 | Y6: =V6+1*U6 -> -0.082231706 | Z6: =1*U6 -> 0.39618907 | AA6: =T6 -> 0.08 | AC6: =x_wLE0+b_w/2*TAN(RADIANS(sweepLE))-L_fus/2 -> 2.515472 | AD6: =b_w/2 -> 17.70322 | AE6: =z_w0+b_w/2*TAN(RADIANS(dihedral)) -> 0.35427609 | AG6: =-eta_in -> -0.34 | AH6: =AG6*b_w/2 -> -6.0190949 | AI6: =IF(AG6=0,L_fus-tail_len-0.2*L_nac,x_wLE0+ABS(AH6)*TAN(RADIANS(sweepLE))-0.8*L_nac) -> 10.385503 | AJ6: =IF(AG6=0,z_VT0+0.55*D_nac,z_w0+ABS(AH6)*TAN(RADIANS(dihedral))-0.6*D_nac) -> -2.0075068 | AL6: =AI5+1*L_nac-L_fus/2 -> -3.1011787 | AM6: =AH5+-1*D_nac/2 -> 4.9027996 | AN6: =AJ5+-1*D_nac/2 -> -3.1238022 | AP6: =x_main-L_fus/2+-0.5*D_tyre/2 -> -0.59269007 | AQ6: =-h_cg+D_tyre/2+0.86603*D_tyre/2 -> -2.5880112 | AS6: =1*B_box/2 -> 19.591528 | AT6: =1*B_box/2 -> 19.591528 | AV6: 1 | AW6: =MIN(AV6,n_SA-1) -> 1 | AX6: =-w_cabin/2+0.025+(1)*(AW6*seat_w+aisle_w*((AW6>=aisle1)+(AW6>=aisle2))) -> -1.31 | AY6: =MAX(0,MIN(1,n_rows-1)) -> 1 | AZ6: =x_eco0+AY6*(seat_pitch) -> 7.31 | BA6: =nose_len+1*L_cabin -> 29.25 | BB6: =-1*w_cabin/2 -> -1.865 | BC6: =BA6-L_fus/2 -> 11.43952 | BD6: =T6-L_fus/2 -> -17.73048 | BE6: =U6*1 -> 0.39618907 | BF6: =V6+U6*0 -> -0.47842078 | BG6: =BD6*COS(RADIANS(view_az))+BE6*SIN(RADIANS(view_az)) -> -13.32767 | BH6: =BF6*COS(RADIANS(view_el))+(BE6*COS(RADIANS(view_az))-BD6*SIN(RADIANS(view_az)))*SIN(RADIANS(view_el)) -> 4.5112195 | BK6: ="Wing: S = "&TEXT(S_ref,"0.0")&" m2, b = "&TEXT(b_w,"0.0")&" m, c/4 sweep "&TEXT(sweep25,"0")&" deg" -> Wing: S = 132.0 m2, b = 35.4 m, c/4 sweep 26 deg | BM6: =$AZ$5+0.2*(seat_pitch)*($AY$5*n_SA+$AW$5<pax_e) -> 6.662 | BN6: =$AX$5+seat_w*($AY$5*n_SA+$AW$5<pax_e) -> -1.31 | BO6: =BM6-L_fus/2 -> -11.14848 | BQ6: =0.5*nose_len+1*MIN(0.6,0.2*nose_len) -> 2.6 | BR6: =-1*MIN(0.55,0.2*d_fus)+-1*MIN(0.5,0.25*d_fus)/2 -> -0.8 | BT6: 1 | BU6: =MIN(BT6,n_lav-1) -> 1 | BV6: =IF(BU6<n_lav_front,1,0) -> 0 | BW6: =IF(BV6=1,BU6,BU6-n_lav_front) -> 0 | BX6: =IF(BV6=1,nose_len,x_seat_end+door_len)+INT(BW6/lav_slots)*lav_len -> 28.25 | BY6: =CHOOSE(MOD(BW6,lav_slots)+1,-w_cabin/2,w_cabin/2-lav_w,-lav_w/2) -> -1.865 | CA6: =$BX$5+1*lav_len -> 5 | CB6: =$BY$5+0*lav_w -> -1.865 | CE6: =1/24*CLmax_c -> 0.0625 | CF6: =CD_0+K_ind*CE6^2 -> 0.018163605 | CG6: =CE6/CF6 -> 3.4409469 | CH6: =1/24*CLmaxTO -> 0.0875 | CI6: =CD_0+dCD0_f2+K_ind*CH6^2 -> 0.036237332 | CJ6: =CH6/CI6 -> 2.4146369 | CK6: =1/24*CLmaxL -> 0.1125 | CL6: =CD_0+dCD0_fMA+dCD0_gear+K_ind*CK6^2 -> 0.058411737 | CM6: =CK6/CL6 -> 1.9259828 | CR6: =1/28*h_abs -> 409.47917 | CS6: =IF(CR6<=11000,288.15-0.0065*CR6,216.65) -> 285.48839 | CT6: =IF(CR6<=11000,rho_SL*(CS6/288.15)^4.25588,0.36392*EXP(-(CR6-11000)/6341.62)) -> 1.1775629 | CU6: =SQRT(1.4*287.053*CS6) -> 338.71879 | CV6: =TW_p*(CT6/rho_SL)^lapse_n -> 0.27539695 | CW6: =MIN(M_MO*CU6,SQRT(CV6*WS_p*(1+SQRT(1+3/(LD_max^2*CV6^2)))/(3*CT6*CD_0))) -> 210.46976 | CX6: =MAX(0,CW6*(CV6-0.5*CT6*CW6^2*CD_0/WS_p-K_ind*WS_p/(0.5*CT6*CW6^2))) -> 36.402107 | CY6: =IF(CR6>=h_cr,0,(MIN(CR7,h_cr)-CR6)/MAX(0.05,(CX6+CX7)/2)) -> 11.59942 | CZ6: =MAX(0,CV6^2-4*CD_0*K_ind) -> 0.072827914 | DA6: =MAX(SQRT(2*WS_p/(CT6*CLmax_c)),SQRT(2*WS_p*(CV6-SQRT(CZ6))/(2*CD_0)/CT6)) -> 75.016679 | DB6: =MAX(DA6,MIN(M_MO*CU6,SQRT(2*WS_p*(CV6+SQRT(CZ6))/(2*CD_0)/CT6))) -> 277.74941 | DC6: =DA6/CU6 -> 0.22147186 | DD6: =DB6/CU6 -> 0.82 | DE6: =ROC_SL -> 38.702804 | DF6: =h_cr -> 10668 | DJ6: =1/10*V_A -> 11.987531 | DK6: =(1/10*V_A/V_S1)^2 -> 0.025 | DL6: =V_C -> 128.75511 | DM6: =n_gC -> 1.8374317 | DN6: =V_C -> 128.75511 | DO6: =2-n_gC -> 0.16256831 | DQ6: =Design!$D$442 -> 0.46102527 | DR6: =Design!$B$442 -> 49977.3 | DS6: =x_np -> 0.57069573 | DT6: =1.03*MTOW -> 73193.809 | DU6: =x_np-0.05 -> 0.52069573 | DV6: =1.03*MTOW -> 73193.809 | DX6: =d_fus/2*0.96593 -> 1.9230942 | DY6: =d_fus/2*0.25882 -> 0.51529121 | DZ6: 0 | EA6: =z_w0 -> -1.194555 | EB6: =$AH$5+D_nac/2*0.86603 -> 6.9858402 | EC6: =$AJ$5+D_nac/2*0.5 -> -1.4493592 | ED6: =-track/2+0*2.2*w_tyre/2 -> -3.5406441 | EE6: =-h_cg+D_tyre -> -2.5108116 | EG6: =d_fus/2*0.98481 -> 1.9606828 | EH6: =d_fus/2*0.17365 -> 0.34572413 | EI6: =w_cabin/2*0.98481 -> 1.8366706 | EJ6: =w_cabin/2*0.17365 -> 0.32385725 | EK6: =1*SQRT(MAX(0,(w_cabin/2)^2-(z_floor)^2)) -> 1.7658497 | EL6: =z_floor -> -0.6 | EM6: =$AX$5+0.05*seat_w -> -1.8135 | EN6: =z_floor+1.1 -> 0.5 | EO6: =1*0.6*d_fus -> 2.38911 | EP6: =1*0.6*d_fus -> 2.38911 | ER6: =IF(0<n_door,x_door_f+IF(n_door>1,0/(n_door-1),0)*(x_door_r-x_door_f),IF(0<n_door+n_overwing,x_ac_w+(0-n_door-(n_overwing-1)/2)*seat_pitch,x_door_f)) -> 5.75 | ES6: =1*w_cabin/2 -> 1.865 | ET6: =x_seat0-door_len+1*0.6 -> 5.6 | EU6: =w_cabin/2-gal_w+0*gal_w -> 0.265 | EW6: Range x 1.1 | EX6: =W_pl -> 14250 | EY6: =k_res*(1-ff_fixed*EXP(-Range_km*1.1*1000*TSFC_s*1/(V_cr*LD_cr))) -> 0.31229742 | EZ6: =A_emp -> 0.97 | FA6: =MTOW_frac -> 71061.951 | FB6: =IF(1-$EY6-$EZ6*FA6^C_emp>0.02,(W_crew+$EX6)/(1-$EY6-$EZ6*FA6^C_emp),FA6) -> 76847.373 | FC6: =IF(1-$EY6-$EZ6*FB6^C_emp>0.02,(W_crew+$EX6)/(1-$EY6-$EZ6*FB6^C_emp),FB6) -> 75925.538 | FD6: =IF(1-$EY6-$EZ6*FC6^C_emp>0.02,(W_crew+$EX6)/(1-$EY6-$EZ6*FC6^C_emp),FC6) -> 76065.95 | FE6: =IF(1-$EY6-$EZ6*FD6^C_emp>0.02,(W_crew+$EX6)/(1-$EY6-$EZ6*FD6^C_emp),FD6) -> 76044.413 | FF6: =IF(1-$EY6-$EZ6*FE6^C_emp>0.02,(W_crew+$EX6)/(1-$EY6-$EZ6*FE6^C_emp),FE6) -> 76047.713 | FG6: =IF(1-$EY6-$EZ6*FF6^C_emp>0.02,(W_crew+$EX6)/(1-$EY6-$EZ6*FF6^C_emp),FF6) -> 76047.207 | FH6: =IF(1-$EY6-$EZ6*FG6^C_emp>0.02,(W_crew+$EX6)/(1-$EY6-$EZ6*FG6^C_emp),FG6) -> 76047.284 | FI6: =IF(1-$EY6-$EZ6*FH6^C_emp>0.02,(W_crew+$EX6)/(1-$EY6-$EZ6*FH6^C_emp),FH6) -> 76047.273 | ... FY6: =IF(1-$EY6-$EZ6*FX6^C_emp>0.02,(W_crew+$EX6)/(1-$EY6-$EZ6*FX6^C_emp),FX6) -> 76047.274 | GA6: Embraer ERJ 145 | GB6: 50 | GC6: 22000 | GD6: 12114 | GE6: 51.2 | GF6: 20.04 | GG6: 29.87 | GH6: 33.7 | GI6: 2 | GJ6: 2870 | GK6: =ABS(LN(GC6/MTOW))+ABS(LN(MAX(1,GB6)/MAX(1,PaxTyp))) -> 2.2711219 | GZ6: leading edge of MAC | HA6: =HA5*L_fus-0.25*MAC -> 12.492407 | HB6: =HB5*L_fus-0.25*MAC -> 18.19176 | HF6: =HR5 -> 71889.899 | HG6: =HF6*grav/WS_des -> 133.49705 | HH6: =SQRT(AR_*HG6) -> 35.612105 | HI6: =2*HG6/(HH6*(1+taper)) -> 5.9978282 | HJ6: =2/3*HI6*(1+taper+taper^2)/(1+taper) -> 4.1984797 | HK6: =49*MAX(0.5*HG6,HG6-d_fus*HI6*(1-(1-taper)*d_fus/(2*HH6))) -> 5420.183 | HL6: =27*(c_HT*HJ6*HG6/L_tail+c_VT*HH6*HG6/L_tail) -> 1664.7862 | HM6: =24*S_wet_fus -> 9147.0379 | HN6: =0.043*HF6 -> 3091.2657 | HO6: =1.3*N_eng*14.7*(TW_des*HF6*grav/N_eng/1000)^1.1*EXP(-0.045*BPR) -> 4632.2918 | HP6: =0.17*HF6 -> 12221.283 | HQ6: =SUM(HK6:HP6) -> 36176.847 | HR6: =IF(fuel_frac<0.95,MIN(100*MTOW_frac,(W_crew+W_pl+HQ6)/(1-fuel_frac)),HF6) -> 72362.332 | HT6: 1 | HU6: =MIN(HT6,n_SA_b-1) -> 1 | HV6: =-w_cabin/2+0.025+(n_rows_b>0)*(HU6*seat_w_b+aisle_w*((HU6>=aisle1_b)+(HU6>=aisle2_b))) -> -1.84 | HW6: =MAX(0,MIN(1,n_rows_b-1)) -> 0 | HX6: =x_seat0+HW6*(bus_pitch*(n_rows_b>0)) -> 6.5 | HY6: =$HX$5+0.2*(bus_pitch*(n_rows_b>0))*($HW$5*n_SA_b+$HU$5<pax_b) -> 6.5 | HZ6: =$HV$5+seat_w_b*($HW$5*n_SA_b+$HU$5<pax_b) -> -1.84 | IA6: =HY6-L_fus/2 -> -11.31048 | IC6: =x_wLE0+(0.85*b_w/2)*TAN(RADIANS(sweepLE))-L_fus/2+0.15*c_root*(1-(1-taper)*2*(0.85*b_w/2)/b_w) -> 1.3666727 | ID6: =1*0.85*b_w/2 -> 15.047737
A7: =12/50 -> 0.24 | B7: =A7*WS_max -> 1335.9094 | C7: =B7/grav -> 136.22485 | D7: =TO_slope*B7 -> 0.068997 | E7: =TW_2 -> 0.21941554 | F7: =TW_MA -> 0.21104328 | G7: =beta_cr/alpha_cr*(q_cr*CD_0/(beta_cr*B7)+K_ind*beta_cr*B7/q_cr+ROC_cr/V_cr) -> 0.67180832 | H7: =MAX(D7:G7) -> 0.67180832 | S7: nose 0.07 | T7: =0.07*nose_len -> 0.28 | U7: =d_fus/2*SQRT(1-(1-0.07)^2) -> 0.73178344 | V7: =-0.3*(d_fus/2-U7) -> -0.37774247 | X7: =T7-L_fus/2 -> -17.53048 | Y7: =V7+1*U7 -> 0.35404097 | Z7: =1*U7 -> 0.73178344 | AA7: =T7 -> 0.28 | AC7: =x_wLE0+b_w/2*TAN(RADIANS(sweepLE))-L_fus/2+c_tip -> 4.0062695 | AD7: =b_w/2 -> 17.70322 | AE7: =z_w0+b_w/2*TAN(RADIANS(dihedral)) -> 0.35427609 | AG7: =IF(N_eng=4,eta_out,IF(N_eng=3,0,AG5)) -> 0.34 | AH7: =AG7*b_w/2 -> 6.0190949 | AI7: =IF(AG7=0,L_fus-tail_len-0.2*L_nac,x_wLE0+ABS(AH7)*TAN(RADIANS(sweepLE))-0.8*L_nac) -> 10.385503 | AJ7: =IF(AG7=0,z_VT0+0.55*D_nac,z_w0+ABS(AH7)*TAN(RADIANS(dihedral))-0.6*D_nac) -> -2.0075068 | AL7: =AI5+1*L_nac-L_fus/2 -> -3.1011787 | AM7: =AH5+1*D_nac/2 -> 7.1353903 | AN7: =AJ5+1*D_nac/2 -> -0.8912115 | AP7: =x_main-L_fus/2+-0.86603*D_tyre/2 -> -0.80361309 | AQ7: =-h_cg+D_tyre/2+0.5*D_tyre/2 -> -2.7989342 | AV7: 2 | AW7: =MIN(AV7,n_SA-1) -> 2 | AX7: =-w_cabin/2+0.025+(1)*(AW7*seat_w+aisle_w*((AW7>=aisle1)+(AW7>=aisle2))) -> -0.78 | AY7: =MAX(0,MIN(2,n_rows-1)) -> 2 | AZ7: =x_eco0+AY7*(seat_pitch) -> 8.12 | BA7: =nose_len+1*L_cabin -> 29.25 | BB7: =1*w_cabin/2 -> 1.865 | BC7: =BA7-L_fus/2 -> 11.43952 | BD7: =T7-L_fus/2 -> -17.53048 | BE7: =U7*1 -> 0.73178344 | BF7: =V7+U7*0 -> -0.37774247 | BG7: =BD7*COS(RADIANS(view_az))+BE7*SIN(RADIANS(view_az)) -> -12.958745 | BH7: =BF7*COS(RADIANS(view_el))+(BE7*COS(RADIANS(view_az))-BD7*SIN(RADIANS(view_az)))*SIN(RADIANS(view_el)) -> 4.656781 | BK7: ="Horizontal tail: S = "&TEXT(S_HT,"0.0")&" m2, b = "&TEXT(b_HT,"0.0")&" m" -> Horizontal tail: S = 34.4 m2, b = 12.4 m | BM7: =$AZ$5 -> 6.5 | BN7: =$AX$5+seat_w*($AY$5*n_SA+$AW$5<pax_e) -> -1.31 | BO7: =BM7-L_fus/2 -> -11.31048 | BQ7: =0.5*nose_len+1*MIN(0.6,0.2*nose_len) -> 2.6 | BR7: =-1*MIN(0.55,0.2*d_fus)+1*MIN(0.5,0.25*d_fus)/2 -> -0.3 | BT7: 2 | BU7: =MIN(BT7,n_lav-1) -> 2 | BV7: =IF(BU7<n_lav_front,1,0) -> 0 | BW7: =IF(BV7=1,BU7,BU7-n_lav_front) -> 1 | BX7: =IF(BV7=1,nose_len,x_seat_end+door_len)+INT(BW7/lav_slots)*lav_len -> 28.25 | BY7: =CHOOSE(MOD(BW7,lav_slots)+1,-w_cabin/2,w_cabin/2-lav_w,-lav_w/2) -> 0.865 | CA7: =$BX$5+1*lav_len -> 5 | CB7: =$BY$5+1*lav_w -> -0.865 | CE7: =2/24*CLmax_c -> 0.125 | CF7: =CD_0+K_ind*CE7^2 -> 0.01865442 | CG7: =CE7/CF7 -> 6.7008248 | CH7: =2/24*CLmaxTO -> 0.175 | CI7: =CD_0+dCD0_f2+K_ind*CH7^2 -> 0.03719933 | CJ7: =CH7/CI7 -> 4.7043858 | CK7: =2/24*CLmaxL -> 0.225 | CL7: =CD_0+dCD0_fMA+dCD0_gear+K_ind*CK7^2 -> 0.060001978 | CM7: =CK7/CL7 -> 3.7498764 | CR7: =2/28*h_abs -> 818.95834 | CS7: =IF(CR7<=11000,288.15-0.0065*CR7,216.65) -> 282.82677 | CT7: =IF(CR7<=11000,rho_SL*(CS7/288.15)^4.25588,0.36392*EXP(-(CR7-11000)/6341.62)) -> 1.1315442 | CU7: =SQRT(1.4*287.053*CS7) -> 337.13615 | CV7: =TW_p*(CT7/rho_SL)^lapse_n -> 0.26156809 | CW7: =MIN(M_MO*CU7,SQRT(CV7*WS_p*(1+SQRT(1+3/(LD_max^2*CV7^2)))/(3*CT7*CD_0))) -> 209.55673 | CX7: =MAX(0,CW7*(CV7-0.5*CT7*CW7^2*CD_0/WS_p-K_ind*WS_p/(0.5*CT7*CW7^2))) -> 34.201279 | CY7: =IF(CR7>=h_cr,0,(MIN(CR8,h_cr)-CR7)/MAX(0.05,(CX7+CX8)/2)) -> 12.352792 | CZ7: =MAX(0,CV7^2-4*CD_0*K_ind) -> 0.065402296 | DA7: =MAX(SQRT(2*WS_p/(CT7*CLmax_c)),SQRT(2*WS_p*(CV7-SQRT(CZ7))/(2*CD_0)/CT7)) -> 76.526904 | DB7: =MAX(DA7,MIN(M_MO*CU7,SQRT(2*WS_p*(CV7+SQRT(CZ7))/(2*CD_0)/CT7))) -> 276.45164 | DC7: =DA7/CU7 -> 0.2269911 | DD7: =DB7/CU7 -> 0.82 | DJ7: =2/10*V_A -> 23.975063 | DK7: =(2/10*V_A/V_S1)^2 -> 0.1 | DL7: =V_D -> 160.94389 | DM7: =n_gD -> 1.5233948 | DN7: =V_D -> 160.94389 | DO7: =2-n_gD -> 0.4766052 | DQ7: =Design!$D$443 -> 0.45775399 | DR7: =Design!$B$443 -> 71061.951 | DX7: =d_fus/2*0.86603 -> 1.7242008 | DY7: =d_fus/2*0.5 -> 0.9954625 | DZ7: =b_w/2 -> 17.70322 | EA7: =z_w0+b_w/2*TAN(RADIANS(dihedral)) -> 0.35427609 | EB7: =$AH$5+D_nac/2*0.5 -> 6.5772426 | EC7: =$AJ$5+D_nac/2*0.86603 -> -1.0407616 | ED7: =-track/2+-1*2.2*w_tyre/2 -> -4.0039099 | EE7: =-h_cg+D_tyre -> -2.5108116 | EG7: =d_fus/2*0.93969 -> 1.8708523 | EH7: =d_fus/2*0.34202 -> 0.68093617 | EI7: =w_cabin/2*0.93969 -> 1.7525218 | EJ7: =w_cabin/2*0.34202 -> 0.6378673 | EM7: =$AX$5+0.95*seat_w -> -1.3365 | EN7: =z_floor+1.1 -> 0.5 | ER7: =IF(1<n_door,x_door_f+IF(n_door>1,1/(n_door-1),0)*(x_door_r-x_door_f),IF(1<n_door+n_overwing,x_ac_w+(1-n_door-(n_overwing-1)/2)*seat_pitch,x_door_f)) -> 27.5 | ES7: =-1*w_cabin/2 -> -1.865 | ET7: =x_seat0-door_len+1*0.6 -> 5.6 | EU7: =w_cabin/2-gal_w+1*gal_w -> 1.865 | EW7: Payload x 0.9 | EX7: =W_pl*0.9 -> 12825 | EY7: =fuel_frac -> 0.29670802 | EZ7: =A_emp -> 0.97 | FA7: =MTOW_frac -> 71061.951 | FB7: =IF(1-$EY7-$EZ7*FA7^C_emp>0.02,(W_crew+$EX7)/(1-$EY7-$EZ7*FA7^C_emp),FA7) -> 64180.314 | FC7: =IF(1-$EY7-$EZ7*FB7^C_emp>0.02,(W_crew+$EX7)/(1-$EY7-$EZ7*FB7^C_emp),FB7) -> 65137.162 | FD7: =IF(1-$EY7-$EZ7*FC7^C_emp>0.02,(W_crew+$EX7)/(1-$EY7-$EZ7*FC7^C_emp),FC7) -> 64996.005 | FE7: =IF(1-$EY7-$EZ7*FD7^C_emp>0.02,(W_crew+$EX7)/(1-$EY7-$EZ7*FD7^C_emp),FD7) -> 65016.652 | FF7: =IF(1-$EY7-$EZ7*FE7^C_emp>0.02,(W_crew+$EX7)/(1-$EY7-$EZ7*FE7^C_emp),FE7) -> 65013.628 | FG7: =IF(1-$EY7-$EZ7*FF7^C_emp>0.02,(W_crew+$EX7)/(1-$EY7-$EZ7*FF7^C_emp),FF7) -> 65014.071 | FH7: =IF(1-$EY7-$EZ7*FG7^C_emp>0.02,(W_crew+$EX7)/(1-$EY7-$EZ7*FG7^C_emp),FG7) -> 65014.006 | FI7: =IF(1-$EY7-$EZ7*FH7^C_emp>0.02,(W_crew+$EX7)/(1-$EY7-$EZ7*FH7^C_emp),FH7) -> 65014.016 | ... FY7: =IF(1-$EY7-$EZ7*FX7^C_emp>0.02,(W_crew+$EX7)/(1-$EY7-$EZ7*FX7^C_emp),FX7) -> 65014.015 | GA7: Bombardier CRJ900 | GB7: 90 | GC7: 38330 | GD7: 21845 | GE7: 71.1 | GF7: 24.85 | GG7: 36.4 | GH7: 59.4 | GI7: 2 | GJ7: 2880 | GK7: =ABS(LN(GC7/MTOW))+ABS(LN(MAX(1,GB7)/MAX(1,PaxTyp))) -> 1.1281448 | GZ7: wing LE at centreline | HA7: =HA6-y_MAC*TAN(RADIANS(sweepLE)) -> 8.5642791 | HB7: =HB6-y_MAC*TAN(RADIANS(sweepLE)) -> 14.263633 | HF7: =HR6 -> 72362.332 | HG7: =HF7*grav/WS_des -> 134.37435 | HH7: =SQRT(AR_*HG7) -> 35.728928 | HI7: =2*HG7/(HH7*(1+taper)) -> 6.0175037 | HJ7: =2/3*HI7*(1+taper+taper^2)/(1+taper) -> 4.2122526 | HK7: =49*MAX(0.5*HG7,HG7-d_fus*HI7*(1-(1-taper)*d_fus/(2*HH7))) -> 5459.3314 | HL7: =27*(c_HT*HJ7*HG7/L_tail+c_VT*HH7*HG7/L_tail) -> 1681.2236 | HM7: =24*S_wet_fus -> 9147.0379 | HN7: =0.043*HF7 -> 3111.5803 | HO7: =1.3*N_eng*14.7*(TW_des*HF7*grav/N_eng/1000)^1.1*EXP(-0.045*BPR) -> 4665.7886 | HP7: =0.17*HF7 -> 12301.596 | HQ7: =SUM(HK7:HP7) -> 36366.558 | HR7: =IF(fuel_frac<0.95,MIN(100*MTOW_frac,(W_crew+W_pl+HQ7)/(1-fuel_frac)),HF7) -> 72632.079 | HT7: 2 | HU7: =MIN(HT7,n_SA_b-1) -> 2 | HV7: =-w_cabin/2+0.025+(n_rows_b>0)*(HU7*seat_w_b+aisle_w*((HU7>=aisle1_b)+(HU7>=aisle2_b))) -> -1.84 | HW7: =MAX(0,MIN(2,n_rows_b-1)) -> 0 | HX7: =x_seat0+HW7*(bus_pitch*(n_rows_b>0)) -> 6.5 | HY7: =$HX$5 -> 6.5 | HZ7: =$HV$5+seat_w_b*($HW$5*n_SA_b+$HU$5<pax_b) -> -1.84 | IA7: =HY7-L_fus/2 -> -11.31048 | IC7: =x_wLE0+(0.85*b_w/2)*TAN(RADIANS(sweepLE))-L_fus/2+0.65*c_root*(1-(1-taper)*2*(0.85*b_w/2)/b_w) -> 2.4475009 | ID7: =1*0.85*b_w/2 -> 15.047737
A8: =13/50 -> 0.26 | B8: =A8*WS_max -> 1447.2352 | C8: =B8/grav -> 147.57692 | D8: =TO_slope*B8 -> 0.07474675 | E8: =TW_2 -> 0.21941554 | F8: =TW_MA -> 0.21104328 | G8: =beta_cr/alpha_cr*(q_cr*CD_0/(beta_cr*B8)+K_ind*beta_cr*B8/q_cr+ROC_cr/V_cr) -> 0.62581994 | H8: =MAX(D8:G8) -> 0.62581994 | K8: Design W/S | L8: Design T/W | S8: nose 0.15 | T8: =0.15*nose_len -> 0.6 | U8: =d_fus/2*SQRT(1-(1-0.15)^2) -> 1.0487848 | V8: =-0.3*(d_fus/2-U8) -> -0.28264205 | X8: =T8-L_fus/2 -> -17.21048 | Y8: =V8+1*U8 -> 0.76614277 | Z8: =1*U8 -> 1.0487848 | AA8: =T8 -> 0.6 | AC8: =x_wLE0+c_root-L_fus/2 -> -1.3416567 | AD8: 0 | AE8: =z_w0 -> -1.194555 | AG8: =IF(N_eng=4,-eta_out,AG6) -> -0.34 | AH8: =AG8*b_w/2 -> -6.0190949 | AI8: =IF(AG8=0,L_fus-tail_len-0.2*L_nac,x_wLE0+ABS(AH8)*TAN(RADIANS(sweepLE))-0.8*L_nac) -> 10.385503 | AJ8: =IF(AG8=0,z_VT0+0.55*D_nac,z_w0+ABS(AH8)*TAN(RADIANS(dihedral))-0.6*D_nac) -> -2.0075068 | AL8: =AI5+0*L_nac-L_fus/2 -> -7.4249768 | AM8: =AH5+1*D_nac/2 -> 7.1353903 | AN8: =AJ5+1*D_nac/2 -> -0.8912115 | AP8: =x_main-L_fus/2+-1*D_tyre/2 -> -0.88081266 | AQ8: =-h_cg+D_tyre/2+0*D_tyre/2 -> -3.0870568 | AV8: 3 | AW8: =MIN(AV8,n_SA-1) -> 3 | AX8: =-w_cabin/2+0.025+(1)*(AW8*seat_w+aisle_w*((AW8>=aisle1)+(AW8>=aisle2))) -> 0.25 | AY8: =MAX(0,MIN(3,n_rows-1)) -> 3 | AZ8: =x_eco0+AY8*(seat_pitch) -> 8.93 | BA8: =nose_len+0*L_cabin -> 4 | BB8: =1*w_cabin/2 -> 1.865 | BC8: =BA8-L_fus/2 -> -13.81048 | BD8: =T8-L_fus/2 -> -17.21048 | BE8: =U8*1 -> 1.0487848 | BF8: =V8+U8*0 -> -0.28264205 | BG8: =BD8*COS(RADIANS(view_az))+BE8*SIN(RADIANS(view_az)) -> -12.509847 | BH8: =BF8*COS(RADIANS(view_el))+(BE8*COS(RADIANS(view_az))-BD8*SIN(RADIANS(view_az)))*SIN(RADIANS(view_el)) -> 4.7586695 | BK8: ="Vertical tail: S = "&TEXT(S_VT,"0.0")&" m2, h = "&TEXT(b_VT,"0.0")&" m" -> Vertical tail: S = 26.2 m2, h = 6.7 m | BM8: =$AZ$5+1*(seat_pitch)*($AY$5*n_SA+$AW$5<pax_e) -> 7.31 | BN8: =$AX$5+seat_w*($AY$5*n_SA+$AW$5<pax_e) -> -1.31 | BO8: =BM8-L_fus/2 -> -10.50048 | BQ8: =0.5*nose_len+0*MIN(0.6,0.2*nose_len) -> 2 | BR8: =-1*MIN(0.55,0.2*d_fus)+1*MIN(0.5,0.25*d_fus)/2 -> -0.3 | BT8: 3 | BU8: =MIN(BT8,n_lav-1) -> 2 | BV8: =IF(BU8<n_lav_front,1,0) -> 0 | BW8: =IF(BV8=1,BU8,BU8-n_lav_front) -> 1 | BX8: =IF(BV8=1,nose_len,x_seat_end+door_len)+INT(BW8/lav_slots)*lav_len -> 28.25 | BY8: =CHOOSE(MOD(BW8,lav_slots)+1,-w_cabin/2,w_cabin/2-lav_w,-lav_w/2) -> 0.865 | CA8: =$BX$5+0*lav_len -> 4 | CB8: =$BY$5+1*lav_w -> -0.865 | CE8: =3/24*CLmax_c -> 0.1875 | CF8: =CD_0+K_ind*CE8^2 -> 0.019472445 | CG8: =CE8/CF8 -> 9.6289911 | CH8: =3/24*CLmaxTO -> 0.2625 | CI8: =CD_0+dCD0_f2+K_ind*CH8^2 -> 0.038802659 | CJ8: =CH8/CI8 -> 6.7650003 | CK8: =3/24*CLmaxL -> 0.3375 | CL8: =CD_0+dCD0_fMA+dCD0_gear+K_ind*CK8^2 -> 0.062652379 | CM8: =CK8/CL8 -> 5.3868665 | CR8: =3/28*h_abs -> 1228.4375 | CS8: =IF(CR8<=11000,288.15-0.0065*CR8,216.65) -> 280.16516 | CT8: =IF(CR8<=11000,rho_SL*(CS8/288.15)^4.25588,0.36392*EXP(-(CR8-11000)/6341.62)) -> 1.086914 | CU8: =SQRT(1.4*287.053*CS8) -> 335.54604 | CV8: =TW_p*(CT8/rho_SL)^lapse_n -> 0.24831264 | CW8: =MIN(M_MO*CU8,SQRT(CV8*WS_p*(1+SQRT(1+3/(LD_max^2*CV8^2)))/(3*CT8*CD_0))) -> 208.66992 | CX8: =MAX(0,CW8*(CV8-0.5*CT8*CW8^2*CD_0/WS_p-K_ind*WS_p/(0.5*CT8*CW8^2))) -> 32.09615 | CY8: =IF(CR8>=h_cr,0,(MIN(CR9,h_cr)-CR8)/MAX(0.05,(CX8+CX9)/2)) -> 13.171022 | CZ8: =MAX(0,CV8^2-4*CD_0*K_ind) -> 0.058643597 | DA8: =MAX(SQRT(2*WS_p/(CT8*CLmax_c)),SQRT(2*WS_p*(CV8-SQRT(CZ8))/(2*CD_0)/CT8)) -> 78.082247 | DB8: =MAX(DA8,MIN(M_MO*CU8,SQRT(2*WS_p*(CV8+SQRT(CZ8))/(2*CD_0)/CT8))) -> 275.14776 | DC8: =DA8/CU8 -> 0.23270203 | DD8: =DB8/CU8 -> 0.82 | DJ8: =3/10*V_A -> 35.962594 | DK8: =(3/10*V_A/V_S1)^2 -> 0.225 | DQ8: =Design!$D$444 -> 0.44090084 | DR8: =Design!$B$444 -> 56811.951 | DX8: =d_fus/2*0.70711 -> 1.407803 | DY8: =d_fus/2*0.70711 -> 1.407803 | EB8: =$AH$5+D_nac/2*0 -> 6.0190949 | EC8: =$AJ$5+D_nac/2*1 -> -0.8912115 | ED8: =-track/2+-1*2.2*w_tyre/2 -> -4.0039099 | EE8: =-h_cg -> -3.663302 | EG8: =d_fus/2*0.86603 -> 1.7242008 | EH8: =d_fus/2*0.5 -> 0.9954625 | EI8: =w_cabin/2*0.86603 -> 1.6151459 | EJ8: =w_cabin/2*0.5 -> 0.9325 | EK8: =-1*SQRT(MAX(0,(w_cabin/2)^2-(-d_hold)^2)) -> -1.6847032 | EL8: =-d_hold -> -0.8 | EM8: =$AX$5+0.95*seat_w -> -1.3365 | EN8: =z_floor+0 -> -0.6 | ER8: =IF(1<n_door,x_door_f+IF(n_door>1,1/(n_door-1),0)*(x_door_r-x_door_f),IF(1<n_door+n_overwing,x_ac_w+(1-n_door-(n_overwing-1)/2)*seat_pitch,x_door_f)) -> 27.5 | ES8: =1*w_cabin/2 -> 1.865 | ET8: =x_seat0-door_len+0*0.6 -> 5 | EU8: =w_cabin/2-gal_w+1*gal_w -> 1.865 | EW8: Payload x 1.1 | EX8: =W_pl*1.1 -> 15675 | EY8: =fuel_frac -> 0.29670802 | EZ8: =A_emp -> 0.97 | FA8: =MTOW_frac -> 71061.951 | FB8: =IF(1-$EY8-$EZ8*FA8^C_emp>0.02,(W_crew+$EX8)/(1-$EY8-$EZ8*FA8^C_emp),FA8) -> 77943.587 | FC8: =IF(1-$EY8-$EZ8*FB8^C_emp>0.02,(W_crew+$EX8)/(1-$EY8-$EZ8*FB8^C_emp),FB8) -> 76924.084 | FD8: =IF(1-$EY8-$EZ8*FC8^C_emp>0.02,(W_crew+$EX8)/(1-$EY8-$EZ8*FC8^C_emp),FC8) -> 77067.329 | FE8: =IF(1-$EY8-$EZ8*FD8^C_emp>0.02,(W_crew+$EX8)/(1-$EY8-$EZ8*FD8^C_emp),FD8) -> 77047.049 | FF8: =IF(1-$EY8-$EZ8*FE8^C_emp>0.02,(W_crew+$EX8)/(1-$EY8-$EZ8*FE8^C_emp),FE8) -> 77049.917 | FG8: =IF(1-$EY8-$EZ8*FF8^C_emp>0.02,(W_crew+$EX8)/(1-$EY8-$EZ8*FF8^C_emp),FF8) -> 77049.511 | FH8: =IF(1-$EY8-$EZ8*FG8^C_emp>0.02,(W_crew+$EX8)/(1-$EY8-$EZ8*FG8^C_emp),FG8) -> 77049.569 | FI8: =IF(1-$EY8-$EZ8*FH8^C_emp>0.02,(W_crew+$EX8)/(1-$EY8-$EZ8*FH8^C_emp),FH8) -> 77049.561 | ... FY8: =IF(1-$EY8-$EZ8*FX8^C_emp>0.02,(W_crew+$EX8)/(1-$EY8-$EZ8*FX8^C_emp),FX8) -> 77049.562 | GA8: Embraer E190 | GB8: 100 | GC8: 51800 | GD8: 28080 | GE8: 92.5 | GF8: 28.72 | GG8: 36.24 | GH8: 82.3 | GI8: 2 | GJ8: 4540 | GK8: =ABS(LN(GC8/MTOW))+ABS(LN(MAX(1,GB8)/MAX(1,PaxTyp))) -> 0.721627 | GZ8: engine CG | HA8: =IF(N_eng=2,(HA7+eta_in*b_w/2*TAN(RADIANS(sweepLE))-0.8*L_nac),IF(N_eng=4,((HA7+eta_in*b_w/2*TAN(RADIANS(sweepLE))-0.8*L_nac)+(HA7+eta_out*b_w/2*TAN(RADIANS(sweepLE))-0.8*L_nac))/2,(2*(HA7+eta_in*b_w/2*TAN(RADIANS(sweepLE))-0.8*L_nac)+L_fus-tail_len-0.2*L_nac)/3))+0.45*L_nac -> 10.389858 | HB8: =IF(N_eng=2,(HB7+eta_in*b_w/2*TAN(RADIANS(sweepLE))-0.8*L_nac),IF(N_eng=4,((HB7+eta_in*b_w/2*TAN(RADIANS(sweepLE))-0.8*L_nac)+(HB7+eta_out*b_w/2*TAN(RADIANS(sweepLE))-0.8*L_nac))/2,(2*(HB7+eta_in*b_w/2*TAN(RADIANS(sweepLE))-0.8*L_nac)+L_fus-tail_len-0.2*L_nac)/3))+0.45*L_nac -> 16.089212 | HF8: =HR7 -> 72632.079 | HG8: =HF8*grav/WS_des -> 134.87526 | HH8: =SQRT(AR_*HG8) -> 35.79546 | HI8: =2*HG8/(HH8*(1+taper)) -> 6.028709 | HJ8: =2/3*HI8*(1+taper+taper^2)/(1+taper) -> 4.2200963 | HK8: =49*MAX(0.5*HG8,HG8-d_fus*HI8*(1-(1-taper)*d_fus/(2*HH8))) -> 5481.6897 | HL8: =27*(c_HT*HJ8*HG8/L_tail+c_VT*HH8*HG8/L_tail) -> 1690.6331 | HM8: =24*S_wet_fus -> 9147.0379 | HN8: =0.043*HF8 -> 3123.1794 | HO8: =1.3*N_eng*14.7*(TW_des*HF8*grav/N_eng/1000)^1.1*EXP(-0.045*BPR) -> 4684.9242 | HP8: =0.17*HF8 -> 12347.453 | HQ8: =SUM(HK8:HP8) -> 36474.918 | HR8: =IF(fuel_frac<0.95,MIN(100*MTOW_frac,(W_crew+W_pl+HQ8)/(1-fuel_frac)),HF8) -> 72786.154 | HT8: 3 | HU8: =MIN(HT8,n_SA_b-1) -> 3 | HV8: =-w_cabin/2+0.025+(n_rows_b>0)*(HU8*seat_w_b+aisle_w*((HU8>=aisle1_b)+(HU8>=aisle2_b))) -> -1.84 | HW8: =MAX(0,MIN(3,n_rows_b-1)) -> 0 | HX8: =x_seat0+HW8*(bus_pitch*(n_rows_b>0)) -> 6.5 | HY8: =$HX$5+1*(bus_pitch*(n_rows_b>0))*($HW$5*n_SA_b+$HU$5<pax_b) -> 6.5 | HZ8: =$HV$5+seat_w_b*($HW$5*n_SA_b+$HU$5<pax_b) -> -1.84 | IA8: =HY8-L_fus/2 -> -11.31048 | IC8: =x_wLE0+(d_fus/2)*TAN(RADIANS(sweepLE))-L_fus/2+0.65*c_root*(1-(1-taper)*2*(d_fus/2)/b_w) -> -2.6512994 | ID8: =1*d_fus/2 -> 1.990925
A9: =14/50 -> 0.28 | B9: =A9*WS_max -> 1558.561 | C9: =B9/grav -> 158.92899 | D9: =TO_slope*B9 -> 0.080496501 | E9: =TW_2 -> 0.21941554 | F9: =TW_MA -> 0.21104328 | G9: =beta_cr/alpha_cr*(q_cr*CD_0/(beta_cr*B9)+K_ind*beta_cr*B9/q_cr+ROC_cr/V_cr) -> 0.58666542 | H9: =MAX(D9:G9) -> 0.58666542 | K9: =WS_des -> 5281.0085 | L9: =TW_des -> 0.27275334 | S9: nose 0.30 | T9: =0.3*nose_len -> 1.2 | U9: =d_fus/2*SQRT(1-(1-0.3)^2) -> 1.4218048 | V9: =-0.3*(d_fus/2-U9) -> -0.17073605 | X9: =T9-L_fus/2 -> -16.61048 | Y9: =V9+1*U9 -> 1.2510688 | Z9: =1*U9 -> 1.4218048 | AA9: =T9 -> 1.2 | AC9: =x_wLE0+b_w/2*TAN(RADIANS(sweepLE))-L_fus/2+c_tip -> 4.0062695 | AD9: =-b_w/2 -> -17.70322 | AE9: =z_w0+b_w/2*TAN(RADIANS(dihedral)) -> 0.35427609 | AL9: =AI5+0*L_nac-L_fus/2 -> -7.4249768 | AM9: =AH5+-1*D_nac/2 -> 4.9027996 | AN9: =AJ5+-1*D_nac/2 -> -3.1238022 | AP9: =x_main-L_fus/2+-0.86603*D_tyre/2 -> -0.80361309 | AQ9: =-h_cg+D_tyre/2+-0.5*D_tyre/2 -> -3.3751794 | AV9: 4 | AW9: =MIN(AV9,n_SA-1) -> 4 | AX9: =-w_cabin/2+0.025+(1)*(AW9*seat_w+aisle_w*((AW9>=aisle1)+(AW9>=aisle2))) -> 0.78 | AY9: =MAX(0,MIN(4,n_rows-1)) -> 4 | AZ9: =x_eco0+AY9*(seat_pitch) -> 9.74 | BA9: =nose_len+0*L_cabin -> 4 | BB9: =-1*w_cabin/2 -> -1.865 | BC9: =BA9-L_fus/2 -> -13.81048 | BD9: =T9-L_fus/2 -> -16.61048 | BE9: =U9*1 -> 1.4218048 | BF9: =V9+U9*0 -> -0.17073605 | BG9: =BD9*COS(RADIANS(view_az))+BE9*SIN(RADIANS(view_az)) -> -11.810447 | BH9: =BF9*COS(RADIANS(view_el))+(BE9*COS(RADIANS(view_az))-BD9*SIN(RADIANS(view_az)))*SIN(RADIANS(view_el)) -> 4.8178616 | BK9: =N_eng&" engines: "&TEXT(T_eng/1000,"0")&" kN each, nacelle "&TEXT(L_nac,"0.0")&" x "&TEXT(D_nac,"0.0")&" m" -> 2 engines: 95 kN each, nacelle 4.3 x 2.2 m | BM9: =$AZ$5+0.8*(seat_pitch)*($AY$5*n_SA+$AW$5<pax_e) -> 7.148 | BN9: =$AX$5+seat_w*($AY$5*n_SA+$AW$5<pax_e) -> -1.31 | BO9: =BM9-L_fus/2 -> -10.66248 | BQ9: =0.5*nose_len+0*MIN(0.6,0.2*nose_len) -> 2 | BR9: =-1*MIN(0.55,0.2*d_fus)+-1*MIN(0.5,0.25*d_fus)/2 -> -0.8 | BT9: 4 | BU9: =MIN(BT9,n_lav-1) -> 2 | BV9: =IF(BU9<n_lav_front,1,0) -> 0 | BW9: =IF(BV9=1,BU9,BU9-n_lav_front) -> 1 | BX9: =IF(BV9=1,nose_len,x_seat_end+door_len)+INT(BW9/lav_slots)*lav_len -> 28.25 | BY9: =CHOOSE(MOD(BW9,lav_slots)+1,-w_cabin/2,w_cabin/2-lav_w,-lav_w/2) -> 0.865 | CA9: =$BX$5+0*lav_len -> 4 | CB9: =$BY$5+0*lav_w -> -1.865 | CE9: =4/24*CLmax_c -> 0.25 | CF9: =CD_0+K_ind*CE9^2 -> 0.02061768 | CG9: =CE9/CF9 -> 12.125516 | CH9: =4/24*CLmaxTO -> 0.35 | CI9: =CD_0+dCD0_f2+K_ind*CH9^2 -> 0.041047319 | CJ9: =CH9/CI9 -> 8.5267444 | CK9: =4/24*CLmaxL -> 0.45 | CL9: =CD_0+dCD0_fMA+dCD0_gear+K_ind*CK9^2 -> 0.06636294 | CM9: =CK9/CL9 -> 6.7808931 | CR9: =4/28*h_abs -> 1637.9167 | CS9: =IF(CR9<=11000,288.15-0.0065*CR9,216.65) -> 277.50354 | CT9: =IF(CR9<=11000,rho_SL*(CS9/288.15)^4.25588,0.36392*EXP(-(CR9-11000)/6341.62)) -> 1.0436432 | CU9: =SQRT(1.4*287.053*CS9) -> 333.94837 | CV9: =TW_p*(CT9/rho_SL)^lapse_n -> 0.23561194 | CW9: =MIN(M_MO*CU9,SQRT(CV9*WS_p*(1+SQRT(1+3/(LD_max^2*CV9^2)))/(3*CT9*CD_0))) -> 207.81254 | CX9: =MAX(0,CW9*(CV9-0.5*CT9*CW9^2*CD_0/WS_p-K_ind*WS_p/(0.5*CT9*CW9^2))) -> 30.082651 | CY9: =IF(CR9>=h_cr,0,(MIN(CR10,h_cr)-CR9)/MAX(0.05,(CX9+CX10)/2)) -> 14.061915 | CZ9: =MAX(0,CV9^2-4*CD_0*K_ind) -> 0.052497417 | DA9: =MAX(SQRT(2*WS_p/(CT9*CLmax_c)),SQRT(2*WS_p*(CV9-SQRT(CZ9))/(2*CD_0)/CT9)) -> 79.684504 | DB9: =MAX(DA9,MIN(M_MO*CU9,SQRT(2*WS_p*(CV9+SQRT(CZ9))/(2*CD_0)/CT9))) -> 273.83766 | DC9: =DA9/CU9 -> 0.23861324 | DD9: =DB9/CU9 -> 0.82 | DJ9: =4/10*V_A -> 47.950126 | DK9: =(4/10*V_A/V_S1)^2 -> 0.4 | DQ9: =Design!$D$441 -> 0.43553093 | DR9: =Design!$B$441 -> 35727.3 | DX9: =d_fus/2*0.5 -> 0.9954625 | DY9: =d_fus/2*0.86603 -> 1.7242008 | DZ9: =-b_HT/2 -> -6.2176462 | EA9: =z_HT -> 1.194555 | EB9: =$AH$5+D_nac/2*-0.5 -> 5.4609472 | EC9: =$AJ$5+D_nac/2*0.86603 -> -1.0407616 | ED9: =-track/2+1*2.2*w_tyre/2 -> -3.0773782 | EE9: =-h_cg -> -3.663302 | EG9: =d_fus/2*0.76604 -> 1.5251282 | EH9: =d_fus/2*0.64279 -> 1.2797467 | EI9: =w_cabin/2*0.76604 -> 1.4286646 | EJ9: =w_cabin/2*0.64279 -> 1.1988033 | EK9: =1*SQRT(MAX(0,(w_cabin/2)^2-(-d_hold)^2)) -> 1.6847032 | EL9: =-d_hold -> -0.8 | EM9: =$AX$6+0.05*seat_w -> -1.2835 | EN9: =z_floor+0 -> -0.6 | ER9: =IF(2<n_door,x_door_f+IF(n_door>1,2/(n_door-1),0)*(x_door_r-x_door_f),IF(2<n_door+n_overwing,x_ac_w+(2-n_door-(n_overwing-1)/2)*seat_pitch,x_door_f)) -> 15.072319 | ES9: =-1*w_cabin/2 -> -1.865 | ET9: =x_seat0-door_len+0*0.6 -> 5 | EU9: =w_cabin/2-gal_w+0*gal_w -> 0.265 | EW9: TSFC x 0.9 | EX9: =W_pl -> 14250 | EY9: =k_res*(1-ff_fixed*EXP(-Range_km*1*1000*TSFC_s*0.9/(V_cr*LD_cr))) -> 0.2807936 | EZ9: =A_emp -> 0.97 | FA9: =MTOW_frac -> 71061.951 | FB9: =IF(1-$EY9-$EZ9*FA9^C_emp>0.02,(W_crew+$EX9)/(1-$EY9-$EZ9*FA9^C_emp),FA9) -> 65990.314 | FC9: =IF(1-$EY9-$EZ9*FB9^C_emp>0.02,(W_crew+$EX9)/(1-$EY9-$EZ9*FB9^C_emp),FB9) -> 66650.711 | FD9: =IF(1-$EY9-$EZ9*FC9^C_emp>0.02,(W_crew+$EX9)/(1-$EY9-$EZ9*FC9^C_emp),FC9) -> 66560.958 | FE9: =IF(1-$EY9-$EZ9*FD9^C_emp>0.02,(W_crew+$EX9)/(1-$EY9-$EZ9*FD9^C_emp),FD9) -> 66573.086 | FF9: =IF(1-$EY9-$EZ9*FE9^C_emp>0.02,(W_crew+$EX9)/(1-$EY9-$EZ9*FE9^C_emp),FE9) -> 66571.446 | FG9: =IF(1-$EY9-$EZ9*FF9^C_emp>0.02,(W_crew+$EX9)/(1-$EY9-$EZ9*FF9^C_emp),FF9) -> 66571.668 | FH9: =IF(1-$EY9-$EZ9*FG9^C_emp>0.02,(W_crew+$EX9)/(1-$EY9-$EZ9*FG9^C_emp),FG9) -> 66571.638 | FI9: =IF(1-$EY9-$EZ9*FH9^C_emp>0.02,(W_crew+$EX9)/(1-$EY9-$EZ9*FH9^C_emp),FH9) -> 66571.642 | ... FY9: =IF(1-$EY9-$EZ9*FX9^C_emp>0.02,(W_crew+$EX9)/(1-$EY9-$EZ9*FX9^C_emp),FX9) -> 66571.641 | GA9: Airbus A320-200 | GB9: 150 | GC9: 78000 | GD9: 42600 | GE9: 122.6 | GF9: 34.1 | GG9: 37.57 | GH9: 118 | GI9: 2 | GJ9: 6100 | GK9: =ABS(LN(GC9/MTOW))+ABS(LN(MAX(1,GB9)/MAX(1,PaxTyp))) -> 0.093156787 | GZ9: moment without gear | HA9: =Design!$B$427*(HA6+0.4*MAC)+Design!$B$428*(HA5*L_fus+L_tail+0.15*MAC_HT)+Design!$B$429*(HA5*L_fus+L_tail+0.15*MAC_VT)+Design!$B$430*0.45*L_fus+Design!$B$433*HA8+Design!$B$434*0.45*L_fus -> 512805.29 | HB9: =Design!$B$427*(HB6+0.4*MAC)+Design!$B$428*(HB5*L_fus+L_tail+0.15*MAC_HT)+Design!$B$429*(HB5*L_fus+L_tail+0.15*MAC_VT)+Design!$B$430*0.45*L_fus+Design!$B$433*HB8+Design!$B$434*0.45*L_fus -> 578697.55 | HF9: =HR8 -> 72786.154 | HG9: =HF9*grav/WS_des -> 135.16137 | HH9: =SQRT(AR_*HG9) -> 35.833406 | HI9: =2*HG9/(HH9*(1+taper)) -> 6.0351 | HJ9: =2/3*HI9*(1+taper+taper^2)/(1+taper) -> 4.22457 | HK9: =49*MAX(0.5*HG9,HG9-d_fus*HI9*(1-(1-taper)*d_fus/(2*HH9))) -> 5494.4622 | HL9: =27*(c_HT*HJ9*HG9/L_tail+c_VT*HH9*HG9/L_tail) -> 1696.0154 | HM9: =24*S_wet_fus -> 9147.0379 | HN9: =0.043*HF9 -> 3129.8046 | HO9: =1.3*N_eng*14.7*(TW_des*HF9*grav/N_eng/1000)^1.1*EXP(-0.045*BPR) -> 4695.8574 | HP9: =0.17*HF9 -> 12373.646 | HQ9: =SUM(HK9:HP9) -> 36536.824 | HR9: =IF(fuel_frac<0.95,MIN(100*MTOW_frac,(W_crew+W_pl+HQ9)/(1-fuel_frac)),HF9) -> 72874.177 | HT9: 4 | HU9: =MIN(HT9,n_SA_b-1) -> 3 | HV9: =-w_cabin/2+0.025+(n_rows_b>0)*(HU9*seat_w_b+aisle_w*((HU9>=aisle1_b)+(HU9>=aisle2_b))) -> -1.84 | HW9: =MAX(0,MIN(4,n_rows_b-1)) -> 0 | HX9: =x_seat0+HW9*(bus_pitch*(n_rows_b>0)) -> 6.5 | HY9: =$HX$5+0.8*(bus_pitch*(n_rows_b>0))*($HW$5*n_SA_b+$HU$5<pax_b) -> 6.5 | HZ9: =$HV$5+seat_w_b*($HW$5*n_SA_b+$HU$5<pax_b) -> -1.84 | IA9: =HY9-L_fus/2 -> -11.31048 | IC9: =x_wLE0+(d_fus/2)*TAN(RADIANS(sweepLE))-L_fus/2+0.15*c_root*(1-(1-taper)*2*(d_fus/2)/b_w) -> -5.3814091 | ID9: =1*d_fus/2 -> 1.990925
A10: =15/50 -> 0.3 | B10: =A10*WS_max -> 1669.8867 | C10: =B10/grav -> 170.28106 | D10: =TO_slope*B10 -> 0.086246251 | E10: =TW_2 -> 0.21941554 | F10: =TW_MA -> 0.21104328 | G10: =beta_cr/alpha_cr*(q_cr*CD_0/(beta_cr*B10)+K_ind*beta_cr*B10/q_cr+ROC_cr/V_cr) -> 0.552978 | H10: =MAX(D10:G10) -> 0.552978 | S10: nose 0.45 | T10: =0.45*nose_len -> 1.8 | U10: =d_fus/2*SQRT(1-(1-0.45)^2) -> 1.6627502 | V10: =-0.3*(d_fus/2-U10) -> -0.098452443 | X10: =T10-L_fus/2 -> -16.01048 | Y10: =V10+1*U10 -> 1.5642977 | Z10: =1*U10 -> 1.6627502 | AA10: =T10 -> 1.8 | AC10: =x_wLE0+b_w/2*TAN(RADIANS(sweepLE))-L_fus/2 -> 2.515472 | AD10: =-b_w/2 -> -17.70322 | AE10: =z_w0+b_w/2*TAN(RADIANS(dihedral)) -> 0.35427609 | AP10: =x_main-L_fus/2+-0.5*D_tyre/2 -> -0.59269007 | AQ10: =-h_cg+D_tyre/2+-0.86603*D_tyre/2 -> -3.5861024 | AV10: 5 | AW10: =MIN(AV10,n_SA-1) -> 5 | AX10: =-w_cabin/2+0.025+(1)*(AW10*seat_w+aisle_w*((AW10>=aisle1)+(AW10>=aisle2))) -> 1.31 | AY10: =MAX(0,MIN(5,n_rows-1)) -> 5 | AZ10: =x_eco0+AY10*(seat_pitch) -> 10.55 | BD10: =T10-L_fus/2 -> -16.01048 | BE10: =U10*1 -> 1.6627502 | BF10: =V10+U10*0 -> -0.098452443 | BG10: =BD10*COS(RADIANS(view_az))+BE10*SIN(RADIANS(view_az)) -> -11.195944 | BH10: =BF10*COS(RADIANS(view_el))+(BE10*COS(RADIANS(view_az))-BD10*SIN(RADIANS(view_az)))*SIN(RADIANS(view_el)) -> 4.7983852 | BK10: ="Business: "&pax_b&" seats, "&n_SA_b&" abreast x "&n_rows_b&" rows, pitch "&TEXT(bus_pitch,"0.00")&" m" -> Business: 0 seats, 4 abreast x 0 rows, pitch 0.97 m | BM10: =$AZ$5+0.8*(seat_pitch)*($AY$5*n_SA+$AW$5<pax_e) -> 7.148 | BN10: =$AX$5 -> -1.84 | BO10: =BM10-L_fus/2 -> -10.66248 | BT10: 5 | BU10: =MIN(BT10,n_lav-1) -> 2 | BV10: =IF(BU10<n_lav_front,1,0) -> 0 | BW10: =IF(BV10=1,BU10,BU10-n_lav_front) -> 1 | BX10: =IF(BV10=1,nose_len,x_seat_end+door_len)+INT(BW10/lav_slots)*lav_len -> 28.25 | BY10: =CHOOSE(MOD(BW10,lav_slots)+1,-w_cabin/2,w_cabin/2-lav_w,-lav_w/2) -> 0.865 | CA10: =$BX$5+1*lav_len -> 5 | CB10: =$BY$5+1*lav_w -> -0.865 | CE10: =5/24*CLmax_c -> 0.3125 | CF10: =CD_0+K_ind*CE10^2 -> 0.022090125 | CG10: =CE10/CF10 -> 14.146593 | CH10: =5/24*CLmaxTO -> 0.4375 | CI10: =CD_0+dCD0_f2+K_ind*CH10^2 -> 0.043933312 | CJ10: =CH10/CI10 -> 9.958275 | CK10: =5/24*CLmaxL -> 0.5625 | CL10: =CD_0+dCD0_fMA+dCD0_gear+K_ind*CK10^2 -> 0.071133662 | CM10: =CK10/CL10 -> 7.9076486 | CR10: =5/28*h_abs -> 2047.3958 | CS10: =IF(CR10<=11000,288.15-0.0065*CR10,216.65) -> 274.84193 | CT10: =IF(CR10<=11000,rho_SL*(CS10/288.15)^4.25588,0.36392*EXP(-(CR10-11000)/6341.62)) -> 1.0017028 | CU10: =SQRT(1.4*287.053*CS10) -> 332.34301 | CV10: =TW_p*(CT10/rho_SL)^lapse_n -> 0.22344776 | CW10: =MIN(M_MO*CU10,SQRT(CV10*WS_p*(1+SQRT(1+3/(LD_max^2*CV10^2)))/(3*CT10*CD_0))) -> 206.9881 | CX10: =MAX(0,CW10*(CV10-0.5*CT10*CW10^2*CD_0/WS_p-K_ind*WS_p/(0.5*CT10*CW10^2))) -> 28.15681 | CY10: =IF(CR10>=h_cr,0,(MIN(CR11,h_cr)-CR10)/MAX(0.05,(CX10+CX11)/2)) -> 15.034604 | CZ10: =MAX(0,CV10^2-4*CD_0*K_ind) -> 0.046913333 | DA10: =MAX(SQRT(2*WS_p/(CT10*CLmax_c)),SQRT(2*WS_p*(CV10-SQRT(CZ10))/(2*CD_0)/CT10)) -> 81.33556 | DB10: =MAX(DA10,MIN(M_MO*CU10,SQRT(2*WS_p*(CV10+SQRT(CZ10))/(2*CD_0)/CT10))) -> 272.52127 | DC10: =DA10/CU10 -> 0.24473377 | DD10: =DB10/CU10 -> 0.82 | DJ10: =5/10*V_A -> 59.937657 | DK10: =(5/10*V_A/V_S1)^2 -> 0.625 | DX10: =d_fus/2*0.25882 -> 0.51529121 | DY10: =d_fus/2*0.96593 -> 1.9230942 | DZ10: =b_HT/2 -> 6.2176462 | EA10: =z_HT -> 1.194555 | EB10: =$AH$5+D_nac/2*-0.86603 -> 5.0523497 | EC10: =$AJ$5+D_nac/2*0.5 -> -1.4493592 | ED10: =-track/2+1*2.2*w_tyre/2 -> -3.0773782 | EE10: =-h_cg+D_tyre -> -2.5108116 | EG10: =d_fus/2*0.64279 -> 1.2797467 | EH10: =d_fus/2*0.76604 -> 1.5251282 | EI10: =w_cabin/2*0.64279 -> 1.1988033 | EJ10: =w_cabin/2*0.76604 -> 1.4286646 | EM10: =$AX$6+0.05*seat_w -> -1.2835 | EN10: =z_floor+1.1 -> 0.5 | ER10: =IF(2<n_door,x_door_f+IF(n_door>1,2/(n_door-1),0)*(x_door_r-x_door_f),IF(2<n_door+n_overwing,x_ac_w+(2-n_door-(n_overwing-1)/2)*seat_pitch,x_door_f)) -> 15.072319 | ES10: =1*w_cabin/2 -> 1.865 | EW10: TSFC x 1.1 | EX10: =W_pl -> 14250 | EY10: =k_res*(1-ff_fixed*EXP(-Range_km*1*1000*TSFC_s*1.1/(V_cr*LD_cr))) -> 0.31229742 | EZ10: =A_emp -> 0.97 | FA10: =MTOW_frac -> 71061.951 | FB10: =IF(1-$EY10-$EZ10*FA10^C_emp>0.02,(W_crew+$EX10)/(1-$EY10-$EZ10*FA10^C_emp),FA10) -> 76847.373 | FC10: =IF(1-$EY10-$EZ10*FB10^C_emp>0.02,(W_crew+$EX10)/(1-$EY10-$EZ10*FB10^C_emp),FB10) -> 75925.538 | FD10: =IF(1-$EY10-$EZ10*FC10^C_emp>0.02,(W_crew+$EX10)/(1-$EY10-$EZ10*FC10^C_emp),FC10) -> 76065.95 | FE10: =IF(1-$EY10-$EZ10*FD10^C_emp>0.02,(W_crew+$EX10)/(1-$EY10-$EZ10*FD10^C_emp),FD10) -> 76044.413 | FF10: =IF(1-$EY10-$EZ10*FE10^C_emp>0.02,(W_crew+$EX10)/(1-$EY10-$EZ10*FE10^C_emp),FE10) -> 76047.713 | FG10: =IF(1-$EY10-$EZ10*FF10^C_emp>0.02,(W_crew+$EX10)/(1-$EY10-$EZ10*FF10^C_emp),FF10) -> 76047.207 | FH10: =IF(1-$EY10-$EZ10*FG10^C_emp>0.02,(W_crew+$EX10)/(1-$EY10-$EZ10*FG10^C_emp),FG10) -> 76047.284 | FI10: =IF(1-$EY10-$EZ10*FH10^C_emp>0.02,(W_crew+$EX10)/(1-$EY10-$EZ10*FH10^C_emp),FH10) -> 76047.273 | ... FY10: =IF(1-$EY10-$EZ10*FX10^C_emp>0.02,(W_crew+$EX10)/(1-$EY10-$EZ10*FX10^C_emp),FX10) -> 76047.274 | GA10: Boeing 737-800 | GB10: 162 | GC10: 79010 | GD10: 41413 | GE10: 124.6 | GF10: 34.3 | GG10: 39.5 | GH10: 121 | GI10: 2 | GJ10: 5765 | GK10: =ABS(LN(GC10/MTOW))+ABS(LN(MAX(1,GB10)/MAX(1,PaxTyp))) -> 0.18298343 | GZ10: empty CG without gear | HA10: =HA9/(Design!$B$427+Design!$B$428+Design!$B$429+Design!$B$430+Design!$B$433+Design!$B$434) -> 15.639588 | HB10: =HB9/(Design!$B$427+Design!$B$428+Design!$B$429+Design!$B$430+Design!$B$433+Design!$B$434) -> 17.649177 | HF10: =HR9 -> 72874.177 | HG10: =HF10*grav/WS_des -> 135.32482 | HH10: =SQRT(AR_*HG10) -> 35.855067 | HI10: =2*HG10/(HH10*(1+taper)) -> 6.0387481 | HJ10: =2/3*HI10*(1+taper+taper^2)/(1+taper) -> 4.2271237 | HK10: =49*MAX(0.5*HG10,HG10-d_fus*HI10*(1-(1-taper)*d_fus/(2*HH10))) -> 5501.7598 | HL10: =27*(c_HT*HJ10*HG10/L_tail+c_VT*HH10*HG10/L_tail) -> 1699.0929 | HM10: =24*S_wet_fus -> 9147.0379 | HN10: =0.043*HF10 -> 3133.5896 | HO10: =1.3*N_eng*14.7*(TW_des*HF10*grav/N_eng/1000)^1.1*EXP(-0.045*BPR) -> 4702.1045 | HP10: =0.17*HF10 -> 12388.61 | HQ10: =SUM(HK10:HP10) -> 36572.195 | HR10: =IF(fuel_frac<0.95,MIN(100*MTOW_frac,(W_crew+W_pl+HQ10)/(1-fuel_frac)),HF10) -> 72924.47 | HT10: 5 | HU10: =MIN(HT10,n_SA_b-1) -> 3 | HV10: =-w_cabin/2+0.025+(n_rows_b>0)*(HU10*seat_w_b+aisle_w*((HU10>=aisle1_b)+(HU10>=aisle2_b))) -> -1.84 | HW10: =MAX(0,MIN(5,n_rows_b-1)) -> 0 | HX10: =x_seat0+HW10*(bus_pitch*(n_rows_b>0)) -> 6.5 | HY10: =$HX$5+0.8*(bus_pitch*(n_rows_b>0))*($HW$5*n_SA_b+$HU$5<pax_b) -> 6.5 | HZ10: =$HV$5 -> -1.84 | IA10: =HY10-L_fus/2 -> -11.31048
A11: =16/50 -> 0.32 | B11: =A11*WS_max -> 1781.2125 | C11: =B11/grav -> 181.63313 | D11: =TO_slope*B11 -> 0.091996001 | E11: =TW_2 -> 0.21941554 | F11: =TW_MA -> 0.21104328 | G11: =beta_cr/alpha_cr*(q_cr*CD_0/(beta_cr*B11)+K_ind*beta_cr*B11/q_cr+ROC_cr/V_cr) -> 0.52373259 | H11: =MAX(D11:G11) -> 0.52373259 | K11: Crosshair W/S | L11: T/W | S11: nose 0.60 | T11: =0.6*nose_len -> 2.4 | U11: =d_fus/2*SQRT(1-(1-0.6)^2) -> 1.8247129 | V11: =-0.3*(d_fus/2-U11) -> -0.049863629 | X11: =T11-L_fus/2 -> -15.41048 | Y11: =V11+1*U11 -> 1.7748493 | Z11: =1*U11 -> 1.8247129 | AA11: =T11 -> 2.4 | AC11: =x_wLE0-L_fus/2 -> -7.3048467 | AD11: 0 | AE11: =z_w0 -> -1.194555 | AL11: =AI6+0*L_nac-L_fus/2 -> -7.4249768 | AM11: =AH6+-1*D_nac/2 -> -7.1353903 | AN11: =AJ6+-1*D_nac/2 -> -3.1238022 | AP11: =x_main-L_fus/2+0*D_tyre/2 -> -0.30456748 | AQ11: =-h_cg+D_tyre/2+-1*D_tyre/2 -> -3.663302 | AV11: 6 | AW11: =MIN(AV11,n_SA-1) -> 5 | AX11: =-w_cabin/2+0.025+(1)*(AW11*seat_w+aisle_w*((AW11>=aisle1)+(AW11>=aisle2))) -> 1.31 | AY11: =MAX(0,MIN(6,n_rows-1)) -> 6 | AZ11: =x_eco0+AY11*(seat_pitch) -> 11.36 | BD11: =T11-L_fus/2 -> -15.41048 | BE11: =U11*1 -> 1.8247129 | BF11: =V11+U11*0 -> -0.049863629 | BG11: =BD11*COS(RADIANS(view_az))+BE11*SIN(RADIANS(view_az)) -> -10.63221 | BH11: =BF11*COS(RADIANS(view_el))+(BE11*COS(RADIANS(view_az))-BD11*SIN(RADIANS(view_az)))*SIN(RADIANS(view_el)) -> 4.7318639 | BK11: ="Fuel tanks between the spars: "&TEXT(V_tank,"0")&" m3 total" -> Fuel tanks between the spars: 34 m3 total | BM11: =$AZ$5+0.2*(seat_pitch)*($AY$5*n_SA+$AW$5<pax_e) -> 6.662 | BN11: =$AX$5 -> -1.84 | BO11: =BM11-L_fus/2 -> -11.14848 | BQ11: =0.5*nose_len+0*MIN(0.6,0.2*nose_len) -> 2 | BR11: =1*MIN(0.55,0.2*d_fus)+-1*MIN(0.5,0.25*d_fus)/2 -> 0.3 | BT11: 6 | BU11: =MIN(BT11,n_lav-1) -> 2 | BV11: =IF(BU11<n_lav_front,1,0) -> 0 | BW11: =IF(BV11=1,BU11,BU11-n_lav_front) -> 1 | BX11: =IF(BV11=1,nose_len,x_seat_end+door_len)+INT(BW11/lav_slots)*lav_len -> 28.25 | BY11: =CHOOSE(MOD(BW11,lav_slots)+1,-w_cabin/2,w_cabin/2-lav_w,-lav_w/2) -> 0.865 | CA11: =$BX$5+1*lav_len -> 5 | CB11: =$BY$5+0*lav_w -> -1.865 | CE11: =6/24*CLmax_c -> 0.375 | CF11: =CD_0+K_ind*CE11^2 -> 0.02388978 | CG11: =CE11/CF11 -> 15.697089 | CH11: =6/24*CLmaxTO -> 0.525 | CI11: =CD_0+dCD0_f2+K_ind*CH11^2 -> 0.047460635 | CJ11: =CH11/CI11 -> 11.061799 | CK11: =6/24*CLmaxL -> 0.675 | CL11: =CD_0+dCD0_fMA+dCD0_gear+K_ind*CK11^2 -> 0.076964544 | CM11: =CK11/CL11 -> 8.7702722 | CR11: =6/28*h_abs -> 2456.875 | CS11: =IF(CR11<=11000,288.15-0.0065*CR11,216.65) -> 272.18031 | CT11: =IF(CR11<=11000,rho_SL*(CS11/288.15)^4.25588,0.36392*EXP(-(CR11-11000)/6341.62)) -> 0.96106408 | CU11: =SQRT(1.4*287.053*CS11) -> 330.72987 | CV11: =TW_p*(CT11/rho_SL)^lapse_n -> 0.21180231 | CW11: =MIN(M_MO*CU11,SQRT(CV11*WS_p*(1+SQRT(1+3/(LD_max^2*CV11^2)))/(3*CT11*CD_0))) -> 206.20047 | CX11: =MAX(0,CW11*(CV11-0.5*CT11*CW11^2*CD_0/WS_p-K_ind*WS_p/(0.5*CT11*CW11^2))) -> 26.31475 | CY11: =IF(CR11>=h_cr,0,(MIN(CR12,h_cr)-CR11)/MAX(0.05,(CX11+CX12)/2)) -> 16.099855 | CZ11: =MAX(0,CV11^2-4*CD_0*K_ind) -> 0.04184465 | DA11: =MAX(SQRT(2*WS_p/(CT11*CLmax_c)),SQRT(2*WS_p*(CV11-SQRT(CZ11))/(2*CD_0)/CT11)) -> 83.037397 | DB11: =MAX(DA11,MIN(M_MO*CU11,SQRT(2*WS_p*(CV11+SQRT(CZ11))/(2*CD_0)/CT11))) -> 271.19849 | DC11: =DA11/CU11 -> 0.25107317 | DD11: =DB11/CU11 -> 0.82 | DJ11: =6/10*V_A -> 71.925189 | DK11: =(6/10*V_A/V_S1)^2 -> 0.9 | DX11: =d_fus/2*0 -> 0 | DY11: =d_fus/2*1 -> 1.990925 | EB11: =$AH$5+D_nac/2*-1 -> 4.9027996 | EC11: =$AJ$5+D_nac/2*0 -> -2.0075068 | ED11: =-track/2+0*2.2*w_tyre/2 -> -3.5406441 | EE11: =-h_cg+D_tyre -> -2.5108116 | EG11: =d_fus/2*0.5 -> 0.9954625 | EH11: =d_fus/2*0.86603 -> 1.7242008 | EI11: =w_cabin/2*0.5 -> 0.9325 | EJ11: =w_cabin/2*0.86603 -> 1.6151459 | EM11: =$AX$6+0.95*seat_w -> -0.8065 | EN11: =z_floor+1.1 -> 0.5 | ER11: =IF(3<n_door,x_door_f+IF(n_door>1,3/(n_door-1),0)*(x_door_r-x_door_f),IF(3<n_door+n_overwing,x_ac_w+(3-n_door-(n_overwing-1)/2)*seat_pitch,x_door_f)) -> 15.882319 | ES11: =-1*w_cabin/2 -> -1.865 | ET11: =x_seat_end+door_len-0.6+0*0.6 -> 27.65 | EU11: =-w_cabin/2+0*gal_w -> -1.865 | EW11: CDo x 0.9 | EX11: =W_pl -> 14250 | EY11: =k_res*(1-ff_fixed*EXP(-Range_km*1*1000*TSFC_s*1/(V_cr*(CL_cr/(CD_0*0.9+K_ind*CL_cr^2))))) -> 0.28652762 | EZ11: =A_emp -> 0.97 | FA11: =MTOW_frac -> 71061.951 | FB11: =IF(1-$EY11-$EZ11*FA11^C_emp>0.02,(W_crew+$EX11)/(1-$EY11-$EZ11*FA11^C_emp),FA11) -> 67732.015 | FC11: =IF(1-$EY11-$EZ11*FB11^C_emp>0.02,(W_crew+$EX11)/(1-$EY11-$EZ11*FB11^C_emp),FB11) -> 68181.098 | FD11: =IF(1-$EY11-$EZ11*FC11^C_emp>0.02,(W_crew+$EX11)/(1-$EY11-$EZ11*FC11^C_emp),FC11) -> 68118.831 | FE11: =IF(1-$EY11-$EZ11*FD11^C_emp>0.02,(W_crew+$EX11)/(1-$EY11-$EZ11*FD11^C_emp),FD11) -> 68127.432 | FF11: =IF(1-$EY11-$EZ11*FE11^C_emp>0.02,(W_crew+$EX11)/(1-$EY11-$EZ11*FE11^C_emp),FE11) -> 68126.243 | FG11: =IF(1-$EY11-$EZ11*FF11^C_emp>0.02,(W_crew+$EX11)/(1-$EY11-$EZ11*FF11^C_emp),FF11) -> 68126.408 | FH11: =IF(1-$EY11-$EZ11*FG11^C_emp>0.02,(W_crew+$EX11)/(1-$EY11-$EZ11*FG11^C_emp),FG11) -> 68126.385 | FI11: =IF(1-$EY11-$EZ11*FH11^C_emp>0.02,(W_crew+$EX11)/(1-$EY11-$EZ11*FH11^C_emp),FH11) -> 68126.388 | ... FY11: =IF(1-$EY11-$EZ11*FX11^C_emp>0.02,(W_crew+$EX11)/(1-$EY11-$EZ11*FX11^C_emp),FX11) -> 68126.388 | GA11: Airbus A321-200 | GB11: 185 | GC11: 93500 | GD11: 48500 | GE11: 122.6 | GF11: 34.1 | GG11: 44.51 | GH11: 147 | GI11: 2 | GJ11: 5950 | GK11: =ABS(LN(GC11/MTOW))+ABS(LN(MAX(1,GB11)/MAX(1,PaxTyp))) -> 0.48412993 | GZ11: fuel CG | HA11: =HA6+0.45*MAC -> 14.370811 | HB11: =HB6+0.45*MAC -> 20.070165 | HF11: =HR10 -> 72924.47 | HG11: =HF11*grav/WS_des -> 135.41822 | HH11: =SQRT(AR_*HG11) -> 35.867437 | HI11: =2*HG11/(HH11*(1+taper)) -> 6.0408316 | HJ11: =2/3*HI11*(1+taper+taper^2)/(1+taper) -> 4.2285821 | HK11: =49*MAX(0.5*HG11,HG11-d_fus*HI11*(1-(1-taper)*d_fus/(2*HH11))) -> 5505.9296 | HL11: =27*(c_HT*HJ11*HG11/L_tail+c_VT*HH11*HG11/L_tail) -> 1700.8522 | HM11: =24*S_wet_fus -> 9147.0379 | HN11: =0.043*HF11 -> 3135.7522 | HO11: =1.3*N_eng*14.7*(TW_des*HF11*grav/N_eng/1000)^1.1*EXP(-0.045*BPR) -> 4705.6743 | HP11: =0.17*HF11 -> 12397.16 | HQ11: =SUM(HK11:HP11) -> 36592.406 | HR11: =IF(fuel_frac<0.95,MIN(100*MTOW_frac,(W_crew+W_pl+HQ11)/(1-fuel_frac)),HF11) -> 72953.209 | HT11: 6 | HU11: =MIN(HT11,n_SA_b-1) -> 3 | HV11: =-w_cabin/2+0.025+(n_rows_b>0)*(HU11*seat_w_b+aisle_w*((HU11>=aisle1_b)+(HU11>=aisle2_b))) -> -1.84 | HW11: =MAX(0,MIN(6,n_rows_b-1)) -> 0 | HX11: =x_seat0+HW11*(bus_pitch*(n_rows_b>0)) -> 6.5 | HY11: =$HX$5+0.2*(bus_pitch*(n_rows_b>0))*($HW$5*n_SA_b+$HU$5<pax_b) -> 6.5 | HZ11: =$HV$5 -> -1.84 | IA11: =HY11-L_fus/2 -> -11.31048 | IC11: =x_wLE0+(d_fus/2)*TAN(RADIANS(sweepLE))-L_fus/2+0.15*c_root*(1-(1-taper)*2*(d_fus/2)/b_w) -> -5.3814091 | ID11: =-1*d_fus/2 -> -1.990925
A12: =17/50 -> 0.34 | B12: =A12*WS_max -> 1892.5383 | C12: =B12/grav -> 192.9852 | D12: =TO_slope*B12 -> 0.097745751 | E12: =TW_2 -> 0.21941554 | F12: =TW_MA -> 0.21104328 | G12: =beta_cr/alpha_cr*(q_cr*CD_0/(beta_cr*B12)+K_ind*beta_cr*B12/q_cr+ROC_cr/V_cr) -> 0.49814532 | H12: =MAX(D12:G12) -> 0.49814532 | K12: =WS_des -> 5281.0085 | L12: 0 | S12: nose 0.80 | T12: =0.8*nose_len -> 3.2 | U12: =d_fus/2*SQRT(1-(1-0.8)^2) -> 1.9507001 | V12: =-0.3*(d_fus/2-U12) -> -0.012067456 | X12: =T12-L_fus/2 -> -14.61048 | Y12: =V12+1*U12 -> 1.9386327 | Z12: =1*U12 -> 1.9507001 | AA12: =T12 -> 3.2 | AL12: =AI6+1*L_nac-L_fus/2 -> -3.1011787 | AM12: =AH6+-1*D_nac/2 -> -7.1353903 | AN12: =AJ6+-1*D_nac/2 -> -3.1238022 | AP12: =x_main-L_fus/2+0.5*D_tyre/2 -> -0.01644489 | AQ12: =-h_cg+D_tyre/2+-0.86603*D_tyre/2 -> -3.5861024 | AV12: 7 | AW12: =MIN(AV12,n_SA-1) -> 5 | AX12: =-w_cabin/2+0.025+(1)*(AW12*seat_w+aisle_w*((AW12>=aisle1)+(AW12>=aisle2))) -> 1.31 | AY12: =MAX(0,MIN(7,n_rows-1)) -> 7 | AZ12: =x_eco0+AY12*(seat_pitch) -> 12.17 | BD12: =T12-L_fus/2 -> -14.61048 | BE12: =U12*1 -> 1.9507001 | BF12: =V12+U12*0 -> -0.012067456 | BG12: =BD12*COS(RADIANS(view_az))+BE12*SIN(RADIANS(view_az)) -> -9.9383911 | BH12: =BF12*COS(RADIANS(view_el))+(BE12*COS(RADIANS(view_az))-BD12*SIN(RADIANS(view_az)))*SIN(RADIANS(view_el)) -> 4.5895835 | BK12: ="Economy: "&pax_e&" seats: "&n_SA&" abreast x "&n_rows&" rows, seat "&TEXT(seat_w,"0.00")&" m wide, pitch "&TEXT(seat_pitch,"0.00")&" m" -> Economy: 150 seats: 6 abreast x 25 rows, seat 0.53 m wide, pitch 0.81 m | BM12: =$AZ$5+(seat_pitch) -> 7.31 | BN12: =$AX$5 -> -1.84 | BO12: =BM12-L_fus/2 -> -10.50048 | BQ12: =0.5*nose_len+1*MIN(0.6,0.2*nose_len) -> 2.6 | BR12: =1*MIN(0.55,0.2*d_fus)+-1*MIN(0.5,0.25*d_fus)/2 -> 0.3 | BT12: 7 | BU12: =MIN(BT12,n_lav-1) -> 2 | BV12: =IF(BU12<n_lav_front,1,0) -> 0 | BW12: =IF(BV12=1,BU12,BU12-n_lav_front) -> 1 | BX12: =IF(BV12=1,nose_len,x_seat_end+door_len)+INT(BW12/lav_slots)*lav_len -> 28.25 | BY12: =CHOOSE(MOD(BW12,lav_slots)+1,-w_cabin/2,w_cabin/2-lav_w,-lav_w/2) -> 0.865 | CA12: =$BX$5+0*lav_len -> 4 | CB12: =$BY$5+1*lav_w -> -0.865 | CE12: =7/24*CLmax_c -> 0.4375 | CF12: =CD_0+K_ind*CE12^2 -> 0.026016645 | CG12: =CE12/CF12 -> 16.816158 | CH12: =7/24*CLmaxTO -> 0.6125 | CI12: =CD_0+dCD0_f2+K_ind*CH12^2 -> 0.051629291 | CJ12: =CH12/CI12 -> 11.863421 | CK12: =7/24*CLmaxL -> 0.7875 | CL12: =CD_0+dCD0_fMA+dCD0_gear+K_ind*CK12^2 -> 0.083855586 | CM12: =CK12/CL12 -> 9.3911453 | CR12: =7/28*h_abs -> 2866.3542 | CS12: =IF(CR12<=11000,288.15-0.0065*CR12,216.65) -> 269.5187 | CT12: =IF(CR12<=11000,rho_SL*(CS12/288.15)^4.25588,0.36392*EXP(-(CR12-11000)/6341.62)) -> 0.92169889 | CU12: =SQRT(1.4*287.053*CS12) -> 329.10881 | CV12: =TW_p*(CT12/rho_SL)^lapse_n -> 0.20065821 | CW12: =MIN(M_MO*CU12,SQRT(CV12*WS_p*(1+SQRT(1+3/(LD_max^2*CV12^2)))/(3*CT12*CD_0))) -> 205.45388 | CX12: =MAX(0,CW12*(CV12-0.5*CT12*CW12^2*CD_0/WS_p-K_ind*WS_p/(0.5*CT12*CW12^2))) -> 24.552687 | CY12: =IF(CR12>=h_cr,0,(MIN(CR13,h_cr)-CR12)/MAX(0.05,(CX12+CX13)/2)) -> 17.270457 | CZ12: =MAX(0,CV12^2-4*CD_0*K_ind) -> 0.03724815 | DA12: =MAX(SQRT(2*WS_p/(CT12*CLmax_c)),SQRT(2*WS_p*(CV12-SQRT(CZ12))/(2*CD_0)/CT12)) -> 84.792095 | DB12: =MAX(DA12,MIN(M_MO*CU12,SQRT(2*WS_p*(CV12+SQRT(CZ12))/(2*CD_0)/CT12))) -> 269.86923 | DC12: =DA12/CU12 -> 0.25764152 | DD12: =DB12/CU12 -> 0.82 | DJ12: =7/10*V_A -> 83.91272 | DK12: =(7/10*V_A/V_S1)^2 -> 1.225 | DX12: =d_fus/2*-0.25882 -> -0.51529121 | DY12: =d_fus/2*0.96593 -> 1.9230942 | DZ12: 0 | EA12: =z_VT0 -> 1.59274 | EB12: =$AH$5+D_nac/2*-0.86603 -> 5.0523497 | EC12: =$AJ$5+D_nac/2*-0.5 -> -2.5656545 | EG12: =d_fus/2*0.34202 -> 0.68093617 | EH12: =d_fus/2*0.93969 -> 1.8708523 | EI12: =w_cabin/2*0.34202 -> 0.6378673 | EJ12: =w_cabin/2*0.93969 -> 1.7525218 | EM12: =$AX$6+0.95*seat_w -> -0.8065 | EN12: =z_floor+0 -> -0.6 | ER12: =IF(3<n_door,x_door_f+IF(n_door>1,3/(n_door-1),0)*(x_door_r-x_door_f),IF(3<n_door+n_overwing,x_ac_w+(3-n_door-(n_overwing-1)/2)*seat_pitch,x_door_f)) -> 15.882319 | ES12: =1*w_cabin/2 -> 1.865 | ET12: =x_seat_end+door_len-0.6+1*0.6 -> 28.25 | EU12: =-w_cabin/2+0*gal_w -> -1.865 | EW12: CDo x 1.1 | EX12: =W_pl -> 14250 | EY12: =k_res*(1-ff_fixed*EXP(-Range_km*1*1000*TSFC_s*1/(V_cr*(CL_cr/(CD_0*1.1+K_ind*CL_cr^2))))) -> 0.30675443 | EZ12: =A_emp -> 0.97 | FA12: =MTOW_frac -> 71061.951 | FB12: =IF(1-$EY12-$EZ12*FA12^C_emp>0.02,(W_crew+$EX12)/(1-$EY12-$EZ12*FA12^C_emp),FA12) -> 74685.41 | FC12: =IF(1-$EY12-$EZ12*FB12^C_emp>0.02,(W_crew+$EX12)/(1-$EY12-$EZ12*FB12^C_emp),FB12) -> 74129.143 | FD12: =IF(1-$EY12-$EZ12*FC12^C_emp>0.02,(W_crew+$EX12)/(1-$EY12-$EZ12*FC12^C_emp),FC12) -> 74212.128 | FE12: =IF(1-$EY12-$EZ12*FD12^C_emp>0.02,(W_crew+$EX12)/(1-$EY12-$EZ12*FD12^C_emp),FD12) -> 74199.694 | FF12: =IF(1-$EY12-$EZ12*FE12^C_emp>0.02,(W_crew+$EX12)/(1-$EY12-$EZ12*FE12^C_emp),FE12) -> 74201.556 | FG12: =IF(1-$EY12-$EZ12*FF12^C_emp>0.02,(W_crew+$EX12)/(1-$EY12-$EZ12*FF12^C_emp),FF12) -> 74201.277 | FH12: =IF(1-$EY12-$EZ12*FG12^C_emp>0.02,(W_crew+$EX12)/(1-$EY12-$EZ12*FG12^C_emp),FG12) -> 74201.319 | FI12: =IF(1-$EY12-$EZ12*FH12^C_emp>0.02,(W_crew+$EX12)/(1-$EY12-$EZ12*FH12^C_emp),FH12) -> 74201.313 | ... FY12: =IF(1-$EY12-$EZ12*FX12^C_emp>0.02,(W_crew+$EX12)/(1-$EY12-$EZ12*FX12^C_emp),FX12) -> 74201.314 | GA12: Boeing 757-200 | GB12: 200 | GC12: 115680 | GD12: 58390 | GE12: 185.3 | GF12: 38.05 | GG12: 47.32 | GH12: 186 | GI12: 2 | GJ12: 7250 | GK12: =ABS(LN(GC12/MTOW))+ABS(LN(MAX(1,GB12)/MAX(1,PaxTyp))) -> 0.77495779 | GZ12: aft CG for the gear | HA12: =MAX((OEW*HA10)/(OEW),(OEW*HA10+W_pl*x_pay)/(OEW+W_pl),(OEW*HA10+W_pl*x_pay+W_fuel*HA11)/(OEW+W_pl+W_fuel),(OEW*HA10+W_fuel*HA11)/(OEW+W_fuel),(OEW*HA10+PyldMax*x_pay)/(OEW+PyldMax)) -> 15.963571 | HB12: =MAX((OEW*HB10)/(OEW),(OEW*HB10+W_pl*x_pay)/(OEW+W_pl),(OEW*HB10+W_pl*x_pay+W_fuel*HB11)/(OEW+W_pl+W_fuel),(OEW*HB10+W_fuel*HB11)/(OEW+W_fuel),(OEW*HB10+PyldMax*x_pay)/(OEW+PyldMax)) -> 18.54768 | HF12: =HR11 -> 72953.209 | HG12: =HF12*grav/WS_des -> 135.47158 | HH12: =SQRT(AR_*HG12) -> 35.874504 | HI12: =2*HG12/(HH12*(1+taper)) -> 6.0420218 | HJ12: =2/3*HI12*(1+taper+taper^2)/(1+taper) -> 4.2294152 | HK12: =49*MAX(0.5*HG12,HG12-d_fus*HI12*(1-(1-taper)*d_fus/(2*HH12))) -> 5508.3123 | HL12: =27*(c_HT*HJ12*HG12/L_tail+c_VT*HH12*HG12/L_tail) -> 1701.8577 | HM12: =24*S_wet_fus -> 9147.0379 | HN12: =0.043*HF12 -> 3136.988 | HO12: =1.3*N_eng*14.7*(TW_des*HF12*grav/N_eng/1000)^1.1*EXP(-0.045*BPR) -> 4707.7142 | HP12: =0.17*HF12 -> 12402.045 | HQ12: =SUM(HK12:HP12) -> 36603.955 | HR12: =IF(fuel_frac<0.95,MIN(100*MTOW_frac,(W_crew+W_pl+HQ12)/(1-fuel_frac)),HF12) -> 72969.63 | HW12: =MAX(0,MIN(7,n_rows_b-1)) -> 0 | HX12: =x_seat0+HW12*(bus_pitch*(n_rows_b>0)) -> 6.5 | HY12: =$HX$5+(bus_pitch*(n_rows_b>0)) -> 6.5 | HZ12: =$HV$5 -> -1.84 | IA12: =HY12-L_fus/2 -> -11.31048 | IC12: =x_wLE0+(0.85*b_w/2)*TAN(RADIANS(sweepLE))-L_fus/2+0.15*c_root*(1-(1-taper)*2*(0.85*b_w/2)/b_w) -> 1.3666727 | ID12: =-1*0.85*b_w/2 -> -15.047737
A13: =18/50 -> 0.36 | B13: =A13*WS_max -> 2003.8641 | C13: =B13/grav -> 204.33727 | D13: =TO_slope*B13 -> 0.1034955 | E13: =TW_2 -> 0.21941554 | F13: =TW_MA -> 0.21104328 | G13: =beta_cr/alpha_cr*(q_cr*CD_0/(beta_cr*B13)+K_ind*beta_cr*B13/q_cr+ROC_cr/V_cr) -> 0.47560648 | H13: =MAX(D13:G13) -> 0.47560648 | K13: =WS_des -> 5281.0085 | L13: =TW_des -> 0.27275334 | S13: nose 1.00 | T13: =1*nose_len -> 4 | U13: =d_fus/2*SQRT(1-(1-1)^2) -> 1.990925 | V13: =-0.3*(d_fus/2-U13) -> 0 | X13: =T13-L_fus/2 -> -13.81048 | Y13: =V13+1*U13 -> 1.990925 | Z13: =1*U13 -> 1.990925 | AA13: =T13 -> 4 | AC13: =x_hLE0-L_fus/2 -> 11.164541 | AD13: 0 | AE13: =z_HT -> 1.194555 | AL13: =AI6+1*L_nac-L_fus/2 -> -3.1011787 | AM13: =AH6+1*D_nac/2 -> -4.9027996 | AN13: =AJ6+1*D_nac/2 -> -0.8912115 | AP13: =x_main-L_fus/2+0.86603*D_tyre/2 -> 0.19447813 | AQ13: =-h_cg+D_tyre/2+-0.5*D_tyre/2 -> -3.3751794 | AV13: 8 | AW13: =MIN(AV13,n_SA-1) -> 5 | AX13: =-w_cabin/2+0.025+(1)*(AW13*seat_w+aisle_w*((AW13>=aisle1)+(AW13>=aisle2))) -> 1.31 | AY13: =MAX(0,MIN(8,n_rows-1)) -> 8 | AZ13: =x_eco0+AY13*(seat_pitch) -> 12.98 | BD13: =T13-L_fus/2 -> -13.81048 | BE13: =U13*1 -> 1.990925 | BF13: =V13+U13*0 -> 0 | BG13: =BD13*COS(RADIANS(view_az))+BE13*SIN(RADIANS(view_az)) -> -9.2996995 | BH13: =BF13*COS(RADIANS(view_el))+(BE13*COS(RADIANS(view_az))-BD13*SIN(RADIANS(view_az)))*SIN(RADIANS(view_el)) -> 4.3962199 | BK13: ="Cockpit: 2 pilot seats, rear bulkhead at x = "&TEXT(nose_len,"0.0")&" m" -> Cockpit: 2 pilot seats, rear bulkhead at x = 4.0 m | BM13: =$AZ$6+0.2*(seat_pitch)*($AY$6*n_SA+$AW$5<pax_e) -> 7.472 | BN13: =$AX$5 -> -1.84 | BO13: =BM13-L_fus/2 -> -10.33848 | BQ13: =0.5*nose_len+1*MIN(0.6,0.2*nose_len) -> 2.6 | BR13: =1*MIN(0.55,0.2*d_fus)+1*MIN(0.5,0.25*d_fus)/2 -> 0.8 | BT13: 8 | BU13: =MIN(BT13,n_lav-1) -> 2 | BV13: =IF(BU13<n_lav_front,1,0) -> 0 | BW13: =IF(BV13=1,BU13,BU13-n_lav_front) -> 1 | BX13: =IF(BV13=1,nose_len,x_seat_end+door_len)+INT(BW13/lav_slots)*lav_len -> 28.25 | BY13: =CHOOSE(MOD(BW13,lav_slots)+1,-w_cabin/2,w_cabin/2-lav_w,-lav_w/2) -> 0.865 | CE13: =8/24*CLmax_c -> 0.5 | CF13: =CD_0+K_ind*CE13^2 -> 0.02847072 | CG13: =CE13/CF13 -> 17.561902 | CH13: =8/24*CLmaxTO -> 0.7 | CI13: =CD_0+dCD0_f2+K_ind*CH13^2 -> 0.056439278 | CJ13: =CH13/CI13 -> 12.40271 | CK13: =8/24*CLmaxL -> 0.9 | CL13: =CD_0+dCD0_fMA+dCD0_gear+K_ind*CK13^2 -> 0.091806789 | CM13: =CK13/CL13 -> 9.8031965 | CR13: =8/28*h_abs -> 3275.8334 | CS13: =IF(CR13<=11000,288.15-0.0065*CR13,216.65) -> 266.85708 | CT13: =IF(CR13<=11000,rho_SL*(CS13/288.15)^4.25588,0.36392*EXP(-(CR13-11000)/6341.62)) -> 0.88357928 | CU13: =SQRT(1.4*287.053*CS13) -> 327.47973 | CV13: =TW_p*(CT13/rho_SL)^lapse_n -> 0.18999852 | CW13: =MIN(M_MO*CU13,SQRT(CV13*WS_p*(1+SQRT(1+3/(LD_max^2*CV13^2)))/(3*CT13*CD_0))) -> 204.75296 | CX13: =MAX(0,CW13*(CV13-0.5*CT13*CW13^2*CD_0/WS_p-K_ind*WS_p/(0.5*CT13*CW13^2))) -> 22.866925 | CY13: =IF(CR13>=h_cr,0,(MIN(CR14,h_cr)-CR13)/MAX(0.05,(CX13+CX14)/2)) -> 18.561737 | CZ13: =MAX(0,CV13^2-4*CD_0*K_ind) -> 0.03308387 | DA13: =MAX(SQRT(2*WS_p/(CT13*CLmax_c)),SQRT(2*WS_p*(CV13-SQRT(CZ13))/(2*CD_0)/CT13)) -> 86.601844 | DB13: =MAX(DA13,MIN(M_MO*CU13,SQRT(2*WS_p*(CV13+SQRT(CZ13))/(2*CD_0)/CT13))) -> 268.53338 | DC13: =DA13/CU13 -> 0.26444947 | DD13: =DB13/CU13 -> 0.82 | DJ13: =8/10*V_A -> 95.900252 | DK13: =(8/10*V_A/V_S1)^2 -> 1.6 | DX13: =d_fus/2*-0.5 -> -0.9954625 | DY13: =d_fus/2*0.86603 -> 1.7242008 | DZ13: 0 | EA13: =z_VT0+b_VT -> 8.2707682 | EB13: =$AH$5+D_nac/2*-0.5 -> 5.4609472 | EC13: =$AJ$5+D_nac/2*-0.86603 -> -2.9742521 | ED13: =track/2+0*2.2*w_tyre/2 -> 3.5406441 | EE13: =z_w0+track/2*TAN(RADIANS(dihedral)) -> -0.88478878 | EG13: =d_fus/2*0.17365 -> 0.34572413 | EH13: =d_fus/2*0.98481 -> 1.9606828 | EI13: =w_cabin/2*0.17365 -> 0.32385725 | EJ13: =w_cabin/2*0.98481 -> 1.8366706 | EM13: =$AX$7+0.05*seat_w -> -0.7535 | EN13: =z_floor+0 -> -0.6 | ER13: =IF(4<n_door,x_door_f+IF(n_door>1,4/(n_door-1),0)*(x_door_r-x_door_f),IF(4<n_door+n_overwing,x_ac_w+(4-n_door-(n_overwing-1)/2)*seat_pitch,x_door_f)) -> 5.75 | ES13: =-1*w_cabin/2 -> -1.865 | ET13: =x_seat_end+door_len-0.6+1*0.6 -> 28.25 | EU13: =-w_cabin/2+1*gal_w -> -0.265 | EW13: AR x 0.9 | EX13: =W_pl -> 14250 | EY13: =k_res*(1-ff_fixed*EXP(-Range_km*1*1000*TSFC_s*1/(V_cr*(CL_cr/(CD_0+K_ind/0.9*CL_cr^2))))) -> 0.30294648 | EZ13: =A_emp -> 0.97 | FA13: =MTOW_frac -> 71061.951 | FB13: =IF(1-$EY13-$EZ13*FA13^C_emp>0.02,(W_crew+$EX13)/(1-$EY13-$EZ13*FA13^C_emp),FA13) -> 73269.327 | FC13: =IF(1-$EY13-$EZ13*FB13^C_emp>0.02,(W_crew+$EX13)/(1-$EY13-$EZ13*FB13^C_emp),FB13) -> 72938.861 | FD13: =IF(1-$EY13-$EZ13*FC13^C_emp>0.02,(W_crew+$EX13)/(1-$EY13-$EZ13*FC13^C_emp),FC13) -> 72987.47 | FE13: =IF(1-$EY13-$EZ13*FD13^C_emp>0.02,(W_crew+$EX13)/(1-$EY13-$EZ13*FD13^C_emp),FD13) -> 72980.301 | FF13: =IF(1-$EY13-$EZ13*FE13^C_emp>0.02,(W_crew+$EX13)/(1-$EY13-$EZ13*FE13^C_emp),FE13) -> 72981.358 | FG13: =IF(1-$EY13-$EZ13*FF13^C_emp>0.02,(W_crew+$EX13)/(1-$EY13-$EZ13*FF13^C_emp),FF13) -> 72981.202 | FH13: =IF(1-$EY13-$EZ13*FG13^C_emp>0.02,(W_crew+$EX13)/(1-$EY13-$EZ13*FG13^C_emp),FG13) -> 72981.225 | FI13: =IF(1-$EY13-$EZ13*FH13^C_emp>0.02,(W_crew+$EX13)/(1-$EY13-$EZ13*FH13^C_emp),FH13) -> 72981.222 | ... FY13: =IF(1-$EY13-$EZ13*FX13^C_emp>0.02,(W_crew+$EX13)/(1-$EY13-$EZ13*FX13^C_emp),FX13) -> 72981.222 | GA13: Boeing 767-300ER | GB13: 261 | GC13: 186880 | GD13: 90010 | GE13: 283.3 | GF13: 47.57 | GG13: 54.94 | GH13: 276 | GI13: 2 | GJ13: 11070 | GK13: =ABS(LN(GC13/MTOW))+ABS(LN(MAX(1,GB13)/MAX(1,PaxTyp))) -> 1.5207998 | GZ13: empty CG | HA13: =(HA9+Design!$B$431*(HA12-l_nose)+Design!$B$432*(HA12+l_main))/W_e_build -> 15.586433 | HB13: =(HB9+Design!$B$431*(HB12-l_nose)+Design!$B$432*(HB12+l_main))/W_e_build -> 17.644999 | HF13: =HR12 -> 72969.63 | HG13: =HF13*grav/WS_des -> 135.50208 | HH13: =SQRT(AR_*HG13) -> 35.878542 | HI13: =2*HG13/(HH13*(1+taper)) -> 6.0427017 | HJ13: =2/3*HI13*(1+taper+taper^2)/(1+taper) -> 4.2298912 | HK13: =49*MAX(0.5*HG13,HG13-d_fus*HI13*(1-(1-taper)*d_fus/(2*HH13))) -> 5509.6738 | HL13: =27*(c_HT*HJ13*HG13/L_tail+c_VT*HH13*HG13/L_tail) -> 1702.4324 | HM13: =24*S_wet_fus -> 9147.0379 | HN13: =0.043*HF13 -> 3137.6941 | HO13: =1.3*N_eng*14.7*(TW_des*HF13*grav/N_eng/1000)^1.1*EXP(-0.045*BPR) -> 4708.8799 | HP13: =0.17*HF13 -> 12404.837 | HQ13: =SUM(HK13:HP13) -> 36610.555 | HR13: =IF(fuel_frac<0.95,MIN(100*MTOW_frac,(W_crew+W_pl+HQ13)/(1-fuel_frac)),HF13) -> 72979.014 | HW13: =MAX(0,MIN(8,n_rows_b-1)) -> 0 | HX13: =x_seat0+HW13*(bus_pitch*(n_rows_b>0)) -> 6.5 | HY13: =$HX$6+0.2*(bus_pitch*(n_rows_b>0))*($HW$6*n_SA_b+$HU$5<pax_b) -> 6.5 | HZ13: =$HV$5 -> -1.84 | IA13: =HY13-L_fus/2 -> -11.31048 | IC13: =x_wLE0+(0.85*b_w/2)*TAN(RADIANS(sweepLE))-L_fus/2+0.65*c_root*(1-(1-taper)*2*(0.85*b_w/2)/b_w) -> 2.4475009 | ID13: =-1*0.85*b_w/2 -> -15.047737
A14: =19/50 -> 0.38 | B14: =A14*WS_max -> 2115.1899 | C14: =B14/grav -> 215.68934 | D14: =TO_slope*B14 -> 0.10924525 | E14: =TW_2 -> 0.21941554 | F14: =TW_MA -> 0.21104328 | G14: =beta_cr/alpha_cr*(q_cr*CD_0/(beta_cr*B14)+K_ind*beta_cr*B14/q_cr+ROC_cr/V_cr) -> 0.45563475 | H14: =MAX(D14:G14) -> 0.45563475 | K14: 0 | L14: =TW_des -> 0.27275334 | S14: mid 0.33 | T14: =nose_len+0.333333333333333*L_cabin -> 12.416667 | U14: =d_fus/2 -> 1.990925 | V14: 0 | X14: =T14-L_fus/2 -> -5.3938133 | Y14: =V14+1*U14 -> 1.990925 | Z14: =1*U14 -> 1.990925 | AA14: =T14 -> 12.416667 | AC14: =x_hLE0+b_HT/2*TAN(RADIANS(sweepLE_HT))-L_fus/2 -> 15.361236 | AD14: =b_HT/2 -> 6.2176462 | AE14: =z_HT+b_HT/2*TAN(RADIANS(0)) -> 1.194555 | AL14: =AI6+0*L_nac-L_fus/2 -> -7.4249768 | AM14: =AH6+1*D_nac/2 -> -4.9027996 | AN14: =AJ6+1*D_nac/2 -> -0.8912115 | AP14: =x_main-L_fus/2+1*D_tyre/2 -> 0.2716777 | AQ14: =-h_cg+D_tyre/2+0*D_tyre/2 -> -3.0870568 | AV14: 9 | AW14: =MIN(AV14,n_SA-1) -> 5 | AX14: =-w_cabin/2+0.025+(1)*(AW14*seat_w+aisle_w*((AW14>=aisle1)+(AW14>=aisle2))) -> 1.31 | AY14: =MAX(0,MIN(9,n_rows-1)) -> 9 | AZ14: =x_eco0+AY14*(seat_pitch) -> 13.79 | BD14: =T14-L_fus/2 -> -5.3938133 | BE14: =U14*1 -> 1.990925 | BF14: =V14+U14*0 -> 0 | BG14: =BD14*COS(RADIANS(view_az))+BE14*SIN(RADIANS(view_az)) -> -2.8521588 | BH14: =BF14*COS(RADIANS(view_el))+(BE14*COS(RADIANS(view_az))-BD14*SIN(RADIANS(view_az)))*SIN(RADIANS(view_el)) -> 2.1098006 | BK14: ="Lavatories: "&n_lav&" ("&n_lav_front&" front, "&(n_lav-n_lav_front)&" rear), "&TEXT(lav_len,"0.0")&" x "&TEXT(lav_w,"0.0")&" m; door/galley zone "&TEXT(door_len,"0.0")&" m each end" -> Lavatories: 3 (1 front, 2 rear), 1.0 x 1.0 m; door/galley zone 1.5 m each end | BM14: =$AZ$6+0.2*(seat_pitch)*($AY$6*n_SA+$AW$5<pax_e) -> 7.472 | BN14: =$AX$5+seat_w*($AY$6*n_SA+$AW$5<pax_e) -> -1.31 | BO14: =BM14-L_fus/2 -> -10.33848 | BQ14: =0.5*nose_len+0*MIN(0.6,0.2*nose_len) -> 2 | BR14: =1*MIN(0.55,0.2*d_fus)+1*MIN(0.5,0.25*d_fus)/2 -> 0.8 | BT14: 9 | BU14: =MIN(BT14,n_lav-1) -> 2 | BV14: =IF(BU14<n_lav_front,1,0) -> 0 | BW14: =IF(BV14=1,BU14,BU14-n_lav_front) -> 1 | BX14: =IF(BV14=1,nose_len,x_seat_end+door_len)+INT(BW14/lav_slots)*lav_len -> 28.25 | BY14: =CHOOSE(MOD(BW14,lav_slots)+1,-w_cabin/2,w_cabin/2-lav_w,-lav_w/2) -> 0.865 | CA14: =$BX$6+0*lav_len -> 28.25 | CB14: =$BY$6+0*lav_w -> -1.865 | CE14: =9/24*CLmax_c -> 0.5625 | CF14: =CD_0+K_ind*CE14^2 -> 0.031252005 | CG14: =CE14/CF14 -> 17.998845 | CH14: =9/24*CLmaxTO -> 0.7875 | CI14: =CD_0+dCD0_f2+K_ind*CH14^2 -> 0.061890596 | CJ14: =CH14/CI14 -> 12.724065 | CK14: =9/24*CLmaxL -> 1.0125 | CL14: =CD_0+dCD0_fMA+dCD0_gear+K_ind*CK14^2 -> 0.10081815 | CM14: =CK14/CL14 -> 10.042834 | CR14: =9/28*h_abs -> 3685.3125 | CS14: =IF(CR14<=11000,288.15-0.0065*CR14,216.65) -> 264.19547 | CT14: =IF(CR14<=11000,rho_SL*(CS14/288.15)^4.25588,0.36392*EXP(-(CR14-11000)/6341.62)) -> 0.84667766 | CU14: =SQRT(1.4*287.053*CS14) -> 325.84251 | CV14: =TW_p*(CT14/rho_SL)^lapse_n -> 0.1798067 | CW14: =MIN(M_MO*CU14,SQRT(CV14*WS_p*(1+SQRT(1+3/(LD_max^2*CV14^2)))/(3*CT14*CD_0))) -> 204.10279 | CX14: =MAX(0,CW14*(CV14-0.5*CT14*CW14^2*CD_0/WS_p-K_ind*WS_p/(0.5*CT14*CW14^2))) -> 21.253856 | CY14: =IF(CR14>=h_cr,0,(MIN(CR15,h_cr)-CR14)/MAX(0.05,(CX14+CX15)/2)) -> 19.992238 | CZ14: =MAX(0,CV14^2-4*CD_0*K_ind) -> 0.029314881 | DA14: =MAX(SQRT(2*WS_p/(CT14*CLmax_c)),SQRT(2*WS_p*(CV14-SQRT(CZ14))/(2*CD_0)/CT14)) -> 88.468945 | DB14: =MAX(DA14,MIN(M_MO*CU14,SQRT(2*WS_p*(CV14+SQRT(CZ14))/(2*CD_0)/CT14))) -> 267.19086 | DC14: =DA14/CU14 -> 0.2715083 | DD14: =DB14/CU14 -> 0.82 | DJ14: =9/10*V_A -> 107.88778 | DK14: =(9/10*V_A/V_S1)^2 -> 2.025 | DX14: =d_fus/2*-0.70711 -> -1.407803 | DY14: =d_fus/2*0.70711 -> 1.407803 | EB14: =$AH$5+D_nac/2*0 -> 6.0190949 | EC14: =$AJ$5+D_nac/2*-1 -> -3.1238022 | ED14: =track/2+0*2.2*w_tyre/2 -> 3.5406441 | EE14: =-h_cg+D_tyre -> -2.5108116 | EG14: =d_fus/2*0 -> 0 | EH14: =d_fus/2*1 -> 1.990925 | EI14: =w_cabin/2*0 -> 0 | EJ14: =w_cabin/2*1 -> 1.865 | EM14: =$AX$7+0.05*seat_w -> -0.7535 | EN14: =z_floor+1.1 -> 0.5 | ER14: =IF(4<n_door,x_door_f+IF(n_door>1,4/(n_door-1),0)*(x_door_r-x_door_f),IF(4<n_door+n_overwing,x_ac_w+(4-n_door-(n_overwing-1)/2)*seat_pitch,x_door_f)) -> 5.75 | ES14: =1*w_cabin/2 -> 1.865 | ET14: =x_seat_end+door_len-0.6+0*0.6 -> 27.65 | EU14: =-w_cabin/2+1*gal_w -> -0.265 | EW14: AR x 1.1 | EX14: =W_pl -> 14250 | EY14: =k_res*(1-ff_fixed*EXP(-Range_km*1*1000*TSFC_s*1/(V_cr*(CL_cr/(CD_0+K_ind/1.1*CL_cr^2))))) -> 0.29156561 | EZ14: =A_emp -> 0.97 | FA14: =MTOW_frac -> 71061.951 | FB14: =IF(1-$EY14-$EZ14*FA14^C_emp>0.02,(W_crew+$EX14)/(1-$EY14-$EZ14*FA14^C_emp),FA14) -> 69339.973 | FC14: =IF(1-$EY14-$EZ14*FB14^C_emp>0.02,(W_crew+$EX14)/(1-$EY14-$EZ14*FB14^C_emp),FB14) -> 69579.611 | FD14: =IF(1-$EY14-$EZ14*FC14^C_emp>0.02,(W_crew+$EX14)/(1-$EY14-$EZ14*FC14^C_emp),FC14) -> 69545.787 | FE14: =IF(1-$EY14-$EZ14*FD14^C_emp>0.02,(W_crew+$EX14)/(1-$EY14-$EZ14*FD14^C_emp),FD14) -> 69550.552 | FF14: =IF(1-$EY14-$EZ14*FE14^C_emp>0.02,(W_crew+$EX14)/(1-$EY14-$EZ14*FE14^C_emp),FE14) -> 69549.88 | FG14: =IF(1-$EY14-$EZ14*FF14^C_emp>0.02,(W_crew+$EX14)/(1-$EY14-$EZ14*FF14^C_emp),FF14) -> 69549.975 | FH14: =IF(1-$EY14-$EZ14*FG14^C_emp>0.02,(W_crew+$EX14)/(1-$EY14-$EZ14*FG14^C_emp),FG14) -> 69549.961 | FI14: =IF(1-$EY14-$EZ14*FH14^C_emp>0.02,(W_crew+$EX14)/(1-$EY14-$EZ14*FH14^C_emp),FH14) -> 69549.963 | ... FY14: =IF(1-$EY14-$EZ14*FX14^C_emp>0.02,(W_crew+$EX14)/(1-$EY14-$EZ14*FX14^C_emp),FX14) -> 69549.963 | GA14: Airbus A330-300 | GB14: 295 | GC14: 242000 | GD14: 124500 | GE14: 361.6 | GF14: 60.3 | GG14: 63.69 | GH14: 316 | GI14: 2 | GJ14: 11750 | GK14: =ABS(LN(GC14/MTOW))+ABS(LN(MAX(1,GB14)/MAX(1,PaxTyp))) -> 1.9017257 | GZ14: CG station case 1 | HA14: =(OEW*HA13)/(OEW) -> 15.586433 | HB14: =(OEW*HB13)/(OEW) -> 17.644999 | HF14: =HR13 -> 72979.014 | HG14: =HF14*grav/WS_des -> 135.5195 | HH14: =SQRT(AR_*HG14) -> 35.880849 | HI14: =2*HG14/(HH14*(1+taper)) -> 6.0430903 | HJ14: =2/3*HI14*(1+taper+taper^2)/(1+taper) -> 4.2301632 | HK14: =49*MAX(0.5*HG14,HG14-d_fus*HI14*(1-(1-taper)*d_fus/(2*HH14))) -> 5510.4519 | HL14: =27*(c_HT*HJ14*HG14/L_tail+c_VT*HH14*HG14/L_tail) -> 1702.7608 | HM14: =24*S_wet_fus -> 9147.0379 | HN14: =0.043*HF14 -> 3138.0976 | HO14: =1.3*N_eng*14.7*(TW_des*HF14*grav/N_eng/1000)^1.1*EXP(-0.045*BPR) -> 4709.546 | HP14: =0.17*HF14 -> 12406.432 | HQ14: =SUM(HK14:HP14) -> 36614.327 | HR14: =IF(fuel_frac<0.95,MIN(100*MTOW_frac,(W_crew+W_pl+HQ14)/(1-fuel_frac)),HF14) -> 72984.377 | HW14: =MAX(0,MIN(9,n_rows_b-1)) -> 0 | HX14: =x_seat0+HW14*(bus_pitch*(n_rows_b>0)) -> 6.5 | HY14: =$HX$6+0.2*(bus_pitch*(n_rows_b>0))*($HW$6*n_SA_b+$HU$5<pax_b) -> 6.5 | HZ14: =$HV$5+seat_w_b*($HW$6*n_SA_b+$HU$5<pax_b) -> -1.84 | IA14: =HY14-L_fus/2 -> -11.31048 | IC14: =x_wLE0+(d_fus/2)*TAN(RADIANS(sweepLE))-L_fus/2+0.65*c_root*(1-(1-taper)*2*(d_fus/2)/b_w) -> -2.6512994 | ID14: =-1*d_fus/2 -> -1.990925
A15: =20/50 -> 0.4 | B15: =A15*WS_max -> 2226.5157 | C15: =B15/grav -> 227.04141 | D15: =TO_slope*B15 -> 0.114995 | E15: =TW_2 -> 0.21941554 | F15: =TW_MA -> 0.21104328 | G15: =beta_cr/alpha_cr*(q_cr*CD_0/(beta_cr*B15)+K_ind*beta_cr*B15/q_cr+ROC_cr/V_cr) -> 0.43784506 | H15: =MAX(D15:G15) -> 0.43784506 | S15: mid 0.67 | T15: =nose_len+0.666666666666666*L_cabin -> 20.833333 | U15: =d_fus/2 -> 1.990925 | V15: 0 | X15: =T15-L_fus/2 -> 3.0228533 | Y15: =V15+1*U15 -> 1.990925 | Z15: =1*U15 -> 1.990925 | AA15: =T15 -> 20.833333 | AC15: =x_hLE0+b_HT/2*TAN(RADIANS(sweepLE_HT))-L_fus/2+taper_HT*cr_HT -> 16.940321 | AD15: =b_HT/2 -> 6.2176462 | AE15: =z_HT+b_HT/2*TAN(RADIANS(0)) -> 1.194555 | AL15: =AI6+0*L_nac-L_fus/2 -> -7.4249768 | AM15: =AH6+-1*D_nac/2 -> -7.1353903 | AN15: =AJ6+-1*D_nac/2 -> -3.1238022 | AP15: =x_main-L_fus/2+0.86603*D_tyre/2 -> 0.19447813 | AQ15: =-h_cg+D_tyre/2+0.5*D_tyre/2 -> -2.7989342 | AY15: =MAX(0,MIN(10,n_rows-1)) -> 10 | AZ15: =x_eco0+AY15*(seat_pitch) -> 14.6 | BD15: =T15-L_fus/2 -> 3.0228533 | BE15: =U15*1 -> 1.990925 | BF15: =V15+U15*0 -> 0 | BG15: =BD15*COS(RADIANS(view_az))+BE15*SIN(RADIANS(view_az)) -> 3.5953819 | BH15: =BF15*COS(RADIANS(view_el))+(BE15*COS(RADIANS(view_az))-BD15*SIN(RADIANS(view_az)))*SIN(RADIANS(view_el)) -> -0.17661878 | BK15: ="Cabin: "&TEXT(L_cabin,"0.0")&" x "&TEXT(w_cabin,"0.00")&" m, aisle "&TEXT(aisle_w,"0.00")&" m" -> Cabin: 25.3 x 3.73 m, aisle 0.50 m | BM15: =$AZ$6 -> 7.31 | BN15: =$AX$5+seat_w*($AY$6*n_SA+$AW$5<pax_e) -> -1.31 | BO15: =BM15-L_fus/2 -> -10.50048 | BQ15: =0.5*nose_len+0*MIN(0.6,0.2*nose_len) -> 2 | BR15: =1*MIN(0.55,0.2*d_fus)+-1*MIN(0.5,0.25*d_fus)/2 -> 0.3 | BT15: 10 | BU15: =MIN(BT15,n_lav-1) -> 2 | BV15: =IF(BU15<n_lav_front,1,0) -> 0 | BW15: =IF(BV15=1,BU15,BU15-n_lav_front) -> 1 | BX15: =IF(BV15=1,nose_len,x_seat_end+door_len)+INT(BW15/lav_slots)*lav_len -> 28.25 | BY15: =CHOOSE(MOD(BW15,lav_slots)+1,-w_cabin/2,w_cabin/2-lav_w,-lav_w/2) -> 0.865 | CA15: =$BX$6+1*lav_len -> 29.25 | CB15: =$BY$6+0*lav_w -> -1.865 | CE15: =10/24*CLmax_c -> 0.625 | CF15: =CD_0+K_ind*CE15^2 -> 0.0343605 | CG15: =CE15/CF15 -> 18.189491 | CH15: =10/24*CLmaxTO -> 0.875 | CI15: =CD_0+dCD0_f2+K_ind*CH15^2 -> 0.067983246 | CJ15: =CH15/CI15 -> 12.870818 | CK15: =10/24*CLmaxL -> 1.125 | CL15: =CD_0+dCD0_fMA+dCD0_gear+K_ind*CK15^2 -> 0.11088968 | CM15: =CK15/CL15 -> 10.145219 | CR15: =10/28*h_abs -> 4094.7917 | CS15: =IF(CR15<=11000,288.15-0.0065*CR15,216.65) -> 261.53385 | CT15: =IF(CR15<=11000,rho_SL*(CS15/288.15)^4.25588,0.36392*EXP(-(CR15-11000)/6341.62)) -> 0.8109668 | CU15: =SQRT(1.4*287.053*CS15) -> 324.19702 | CV15: =TW_p*(CT15/rho_SL)^lapse_n -> 0.17006661 | CW15: =MIN(M_MO*CU15,SQRT(CV15*WS_p*(1+SQRT(1+3/(LD_max^2*CV15^2)))/(3*CT15*CD_0))) -> 203.50883 | CX15: =MAX(0,CW15*(CV15-0.5*CT15*CW15^2*CD_0/WS_p-K_ind*WS_p/(0.5*CT15*CW15^2))) -> 19.70996 | CY15: =IF(CR15>=h_cr,0,(MIN(CR16,h_cr)-CR15)/MAX(0.05,(CX15+CX16)/2)) -> 21.584619 | CZ15: =MAX(0,CV15^2-4*CD_0*K_ind) -> 0.025907085 | DA15: =MAX(SQRT(2*WS_p/(CT15*CLmax_c)),SQRT(2*WS_p*(CV15-SQRT(CZ15))/(2*CD_0)/CT15)) -> 90.395822 | DB15: =MAX(DA15,MIN(M_MO*CU15,SQRT(2*WS_p*(CV15+SQRT(CZ15))/(2*CD_0)/CT15))) -> 265.84156 | DC15: =DA15/CU15 -> 0.2788299 | DD15: =DB15/CU15 -> 0.82 | DJ15: =10/10*V_A -> 119.87531 | DK15: =(10/10*V_A/V_S1)^2 -> 2.5 | DX15: =d_fus/2*-0.86603 -> -1.7242008 | DY15: =d_fus/2*0.5 -> 0.9954625 | EB15: =$AH$5+D_nac/2*0.5 -> 6.5772426 | EC15: =$AJ$5+D_nac/2*-0.86603 -> -2.9742521 | ED15: =track/2+-1*2.2*w_tyre/2 -> 3.0773782 | EE15: =-h_cg+D_tyre -> -2.5108116 | EG15: =d_fus/2*-0.17365 -> -0.34572413 | EH15: =d_fus/2*0.98481 -> 1.9606828 | EI15: =w_cabin/2*-0.17365 -> -0.32385725 | EJ15: =w_cabin/2*0.98481 -> 1.8366706 | EM15: =$AX$7+0.95*seat_w -> -0.2765 | EN15: =z_floor+1.1 -> 0.5 | ER15: =IF(5<n_door,x_door_f+IF(n_door>1,5/(n_door-1),0)*(x_door_r-x_door_f),IF(5<n_door+n_overwing,x_ac_w+(5-n_door-(n_overwing-1)/2)*seat_pitch,x_door_f)) -> 5.75 | ES15: =-1*w_cabin/2 -> -1.865 | ET15: =x_seat_end+door_len-0.6+0*0.6 -> 27.65 | EU15: =-w_cabin/2+0*gal_w -> -1.865 | EW15: A x 0.9 | EX15: =W_pl -> 14250 | EY15: =fuel_frac -> 0.29670802 | EZ15: =A_emp*0.9 -> 0.873 | FA15: =MTOW_frac -> 71061.951 | FB15: =IF(1-$EY15-$EZ15*FA15^C_emp>0.02,(W_crew+$EX15)/(1-$EY15-$EZ15*FA15^C_emp),FA15) -> 57324.896 | FC15: =IF(1-$EY15-$EZ15*FB15^C_emp>0.02,(W_crew+$EX15)/(1-$EY15-$EZ15*FB15^C_emp),FB15) -> 58648.561 | FD15: =IF(1-$EY15-$EZ15*FC15^C_emp>0.02,(W_crew+$EX15)/(1-$EY15-$EZ15*FC15^C_emp),FC15) -> 58504.177 | FE15: =IF(1-$EY15-$EZ15*FD15^C_emp>0.02,(W_crew+$EX15)/(1-$EY15-$EZ15*FD15^C_emp),FD15) -> 58519.723 | FF15: =IF(1-$EY15-$EZ15*FE15^C_emp>0.02,(W_crew+$EX15)/(1-$EY15-$EZ15*FE15^C_emp),FE15) -> 58518.047 | FG15: =IF(1-$EY15-$EZ15*FF15^C_emp>0.02,(W_crew+$EX15)/(1-$EY15-$EZ15*FF15^C_emp),FF15) -> 58518.227 | FH15: =IF(1-$EY15-$EZ15*FG15^C_emp>0.02,(W_crew+$EX15)/(1-$EY15-$EZ15*FG15^C_emp),FG15) -> 58518.208 | FI15: =IF(1-$EY15-$EZ15*FH15^C_emp>0.02,(W_crew+$EX15)/(1-$EY15-$EZ15*FH15^C_emp),FH15) -> 58518.21 | ... FY15: =IF(1-$EY15-$EZ15*FX15^C_emp>0.02,(W_crew+$EX15)/(1-$EY15-$EZ15*FX15^C_emp),FX15) -> 58518.21 | GA15: Boeing 787-9 | GB15: 290 | GC15: 254000 | GD15: 128850 | GE15: 360.5 | GF15: 60.12 | GG15: 62.81 | GH15: 320 | GI15: 2 | GJ15: 14140 | GK15: =ABS(LN(GC15/MTOW))+ABS(LN(MAX(1,GB15)/MAX(1,PaxTyp))) -> 1.9330279 | GZ15: CG station case 2 | HA15: =(OEW*HA13+W_pl*x_pay)/(OEW+W_pl) -> 15.882559 | HB15: =(OEW*HB13+W_pl*x_pay)/(OEW+W_pl) -> 17.354167 | HF15: =HR14 -> 72984.377 | HG15: =HF15*grav/WS_des -> 135.52946 | HH15: =SQRT(AR_*HG15) -> 35.882167 | HI15: =2*HG15/(HH15*(1+taper)) -> 6.0433123 | HJ15: =2/3*HI15*(1+taper+taper^2)/(1+taper) -> 4.2303186 | HK15: =49*MAX(0.5*HG15,HG15-d_fus*HI15*(1-(1-taper)*d_fus/(2*HH15))) -> 5510.8965 | HL15: =27*(c_HT*HJ15*HG15/L_tail+c_VT*HH15*HG15/L_tail) -> 1702.9485 | HM15: =24*S_wet_fus -> 9147.0379 | HN15: =0.043*HF15 -> 3138.3282 | HO15: =1.3*N_eng*14.7*(TW_des*HF15*grav/N_eng/1000)^1.1*EXP(-0.045*BPR) -> 4709.9267 | HP15: =0.17*HF15 -> 12407.344 | HQ15: =SUM(HK15:HP15) -> 36616.482 | HR15: =IF(fuel_frac<0.95,MIN(100*MTOW_frac,(W_crew+W_pl+HQ15)/(1-fuel_frac)),HF15) -> 72987.441 | HW15: =MAX(0,MIN(10,n_rows_b-1)) -> 0 | HX15: =x_seat0+HW15*(bus_pitch*(n_rows_b>0)) -> 6.5 | HY15: =$HX$6 -> 6.5 | HZ15: =$HV$5+seat_w_b*($HW$6*n_SA_b+$HU$5<pax_b) -> -1.84 | IA15: =HY15-L_fus/2 -> -11.31048 | IC15: =x_wLE0+(d_fus/2)*TAN(RADIANS(sweepLE))-L_fus/2+0.15*c_root*(1-(1-taper)*2*(d_fus/2)/b_w) -> -5.3814091 | ID15: =-1*d_fus/2 -> -1.990925
A16: =21/50 -> 0.42 | B16: =A16*WS_max -> 2337.8414 | C16: =B16/grav -> 238.39348 | D16: =TO_slope*B16 -> 0.12074475 | E16: =TW_2 -> 0.21941554 | F16: =TW_MA -> 0.21104328 | G16: =beta_cr/alpha_cr*(q_cr*CD_0/(beta_cr*B16)+K_ind*beta_cr*B16/q_cr+ROC_cr/V_cr) -> 0.42192569 | H16: =MAX(D16:G16) -> 0.42192569 | S16: tail 0.00 | T16: =L_fus-tail_len+0*tail_len -> 29.25 | U16: =d_fus/2*(1-0.88*0^1.3) -> 1.990925 | V16: =0.75*(d_fus/2-U16) -> 0 | X16: =T16-L_fus/2 -> 11.43952 | Y16: =V16+1*U16 -> 1.990925 | Z16: =1*U16 -> 1.990925 | AA16: =T16 -> 29.25 | AC16: =x_hLE0+cr_HT-L_fus/2 -> 15.112253 | AD16: 0 | AE16: =z_HT -> 1.194555 | AP16: =x_main-L_fus/2+0.5*D_tyre/2 -> -0.01644489 | AQ16: =-h_cg+D_tyre/2+0.86603*D_tyre/2 -> -2.5880112 | AY16: =MAX(0,MIN(11,n_rows-1)) -> 11 | AZ16: =x_eco0+AY16*(seat_pitch) -> 15.41 | BD16: =T16-L_fus/2 -> 11.43952 | BE16: =U16*1 -> 1.990925 | BF16: =V16+U16*0 -> 0 | BG16: =BD16*COS(RADIANS(view_az))+BE16*SIN(RADIANS(view_az)) -> 10.042923 | BH16: =BF16*COS(RADIANS(view_el))+(BE16*COS(RADIANS(view_az))-BD16*SIN(RADIANS(view_az)))*SIN(RADIANS(view_el)) -> -2.4630381 | BK16: ="Main gear: "&n_struts&" x "&n_wps&" wheels, tyre "&TEXT(D_tyre,"0.00")&" m, wheelbase "&TEXT(wheelbase,"0.0")&" m" -> Main gear: 2 x 2 wheels, tyre 1.15 m, wheelbase 13.5 m | BM16: =$AZ$6+1*(seat_pitch)*($AY$6*n_SA+$AW$5<pax_e) -> 8.12 | BN16: =$AX$5+seat_w*($AY$6*n_SA+$AW$5<pax_e) -> -1.31 | BO16: =BM16-L_fus/2 -> -9.69048 | BT16: 11 | BU16: =MIN(BT16,n_lav-1) -> 2 | BV16: =IF(BU16<n_lav_front,1,0) -> 0 | BW16: =IF(BV16=1,BU16,BU16-n_lav_front) -> 1 | BX16: =IF(BV16=1,nose_len,x_seat_end+door_len)+INT(BW16/lav_slots)*lav_len -> 28.25 | BY16: =CHOOSE(MOD(BW16,lav_slots)+1,-w_cabin/2,w_cabin/2-lav_w,-lav_w/2) -> 0.865 | CA16: =$BX$6+1*lav_len -> 29.25 | CB16: =$BY$6+1*lav_w -> -0.865 | CE16: =11/24*CLmax_c -> 0.6875 | CF16: =CD_0+K_ind*CE16^2 -> 0.037796205 | CG16: =CE16/CF16 -> 18.189657 | CH16: =11/24*CLmaxTO -> 0.9625 | CI16: =CD_0+dCD0_f2+K_ind*CH16^2 -> 0.074717228 | CJ16: =CH16/CI16 -> 12.881902 | CK16: =11/24*CLmaxL -> 1.2375 | CL16: =CD_0+dCD0_fMA+dCD0_gear+K_ind*CK16^2 -> 0.12202136 | CM16: =CK16/CL16 -> 10.141667 | CR16: =11/28*h_abs -> 4504.2709 | CS16: =IF(CR16<=11000,288.15-0.0065*CR16,216.65) -> 258.87224 | CT16: =IF(CR16<=11000,rho_SL*(CS16/288.15)^4.25588,0.36392*EXP(-(CR16-11000)/6341.62)) -> 0.77641982 | CU16: =SQRT(1.4*287.053*CS16) -> 322.54314 | CV16: =TW_p*(CT16/rho_SL)^lapse_n -> 0.16076253 | CW16: =MIN(M_MO*CU16,SQRT(CV16*WS_p*(1+SQRT(1+3/(LD_max^2*CV16^2)))/(3*CT16*CD_0))) -> 202.97703 | CX16: =MAX(0,CW16*(CV16-0.5*CT16*CW16^2*CD_0/WS_p-K_ind*WS_p/(0.5*CT16*CW16^2))) -> 18.231796 | CY16: =IF(CR16>=h_cr,0,(MIN(CR17,h_cr)-CR16)/MAX(0.05,(CX16+CX17)/2)) -> 23.366894 | CZ16: =MAX(0,CV16^2-4*CD_0*K_ind) -> 0.022829025 | DA16: =MAX(SQRT(2*WS_p/(CT16*CLmax_c)),SQRT(2*WS_p*(CV16-SQRT(CZ16))/(2*CD_0)/CT16)) -> 92.385027 | DB16: =MAX(DA16,MIN(M_MO*CU16,SQRT(2*WS_p*(CV16+SQRT(CZ16))/(2*CD_0)/CT16))) -> 264.48537 | DC16: =DA16/CU16 -> 0.28642689 | DD16: =DB16/CU16 -> 0.82 | DJ16: =V_D -> 160.94389 | DK16: =n_pos -> 2.5 | DX16: =d_fus/2*-0.96593 -> -1.9230942 | DY16: =d_fus/2*0.25882 -> 0.51529121 | EB16: =$AH$5+D_nac/2*0.86603 -> 6.9858402 | EC16: =$AJ$5+D_nac/2*-0.5 -> -2.5656545 | ED16: =track/2+-1*2.2*w_tyre/2 -> 3.0773782 | EE16: =-h_cg -> -3.663302 | EG16: =d_fus/2*-0.34202 -> -0.68093617 | EH16: =d_fus/2*0.93969 -> 1.8708523 | EI16: =w_cabin/2*-0.34202 -> -0.6378673 | EJ16: =w_cabin/2*0.93969 -> 1.7525218 | EM16: =$AX$7+0.95*seat_w -> -0.2765 | EN16: =z_floor+0 -> -0.6 | ER16: =IF(5<n_door,x_door_f+IF(n_door>1,5/(n_door-1),0)*(x_door_r-x_door_f),IF(5<n_door+n_overwing,x_ac_w+(5-n_door-(n_overwing-1)/2)*seat_pitch,x_door_f)) -> 5.75 | ES16: =1*w_cabin/2 -> 1.865 | EW16: A x 1.1 | EX16: =W_pl -> 14250 | EY16: =fuel_frac -> 0.29670802 | EZ16: =A_emp*1.1 -> 1.067 | FA16: =MTOW_frac -> 71061.951 | FB16: =IF(1-$EY16-$EZ16*FA16^C_emp>0.02,(W_crew+$EX16)/(1-$EY16-$EZ16*FA16^C_emp),FA16) -> 93457.69 | FC16: =IF(1-$EY16-$EZ16*FB16^C_emp>0.02,(W_crew+$EX16)/(1-$EY16-$EZ16*FB16^C_emp),FB16) -> 88458.176 | FD16: =IF(1-$EY16-$EZ16*FC16^C_emp>0.02,(W_crew+$EX16)/(1-$EY16-$EZ16*FC16^C_emp),FC16) -> 89411.772 | FE16: =IF(1-$EY16-$EZ16*FD16^C_emp>0.02,(W_crew+$EX16)/(1-$EY16-$EZ16*FD16^C_emp),FD16) -> 89223.934 | FF16: =IF(1-$EY16-$EZ16*FE16^C_emp>0.02,(W_crew+$EX16)/(1-$EY16-$EZ16*FE16^C_emp),FE16) -> 89260.703 | FG16: =IF(1-$EY16-$EZ16*FF16^C_emp>0.02,(W_crew+$EX16)/(1-$EY16-$EZ16*FF16^C_emp),FF16) -> 89253.496 | FH16: =IF(1-$EY16-$EZ16*FG16^C_emp>0.02,(W_crew+$EX16)/(1-$EY16-$EZ16*FG16^C_emp),FG16) -> 89254.909 | FI16: =IF(1-$EY16-$EZ16*FH16^C_emp>0.02,(W_crew+$EX16)/(1-$EY16-$EZ16*FH16^C_emp),FH16) -> 89254.632 | ... FY16: =IF(1-$EY16-$EZ16*FX16^C_emp>0.02,(W_crew+$EX16)/(1-$EY16-$EZ16*FX16^C_emp),FX16) -> 89254.677 | GA16: Airbus A350-900 | GB16: 315 | GC16: 280000 | GD16: 142400 | GE16: 442 | GF16: 64.75 | GG16: 66.8 | GH16: 374.5 | GI16: 2 | GJ16: 15000 | GK16: =ABS(LN(GC16/MTOW))+ABS(LN(MAX(1,GB16)/MAX(1,PaxTyp))) -> 2.1131749 | GZ16: CG station case 3 | HA16: =(OEW*HA13+W_pl*x_pay+W_fuel*HA11)/(OEW+W_pl+W_fuel) -> 15.434012 | HB16: =(OEW*HB13+W_pl*x_pay+W_fuel*HB11)/(OEW+W_pl+W_fuel) -> 18.160025 | HF16: =HR15 -> 72987.441 | HG16: =HF16*grav/WS_des -> 135.53515 | HH16: =SQRT(AR_*HG16) -> 35.88292 | HI16: =2*HG16/(HH16*(1+taper)) -> 6.0434392 | HJ16: =2/3*HI16*(1+taper+taper^2)/(1+taper) -> 4.2304074 | HK16: =49*MAX(0.5*HG16,HG16-d_fus*HI16*(1-(1-taper)*d_fus/(2*HH16))) -> 5511.1506 | HL16: =27*(c_HT*HJ16*HG16/L_tail+c_VT*HH16*HG16/L_tail) -> 1703.0557 | HM16: =24*S_wet_fus -> 9147.0379 | HN16: =0.043*HF16 -> 3138.46 | HO16: =1.3*N_eng*14.7*(TW_des*HF16*grav/N_eng/1000)^1.1*EXP(-0.045*BPR) -> 4710.1442 | HP16: =0.17*HF16 -> 12407.865 | HQ16: =SUM(HK16:HP16) -> 36617.714 | HR16: =IF(fuel_frac<0.95,MIN(100*MTOW_frac,(W_crew+W_pl+HQ16)/(1-fuel_frac)),HF16) -> 72989.193 | HW16: =MAX(0,MIN(11,n_rows_b-1)) -> 0 | HX16: =x_seat0+HW16*(bus_pitch*(n_rows_b>0)) -> 6.5 | HY16: =$HX$6+1*(bus_pitch*(n_rows_b>0))*($HW$6*n_SA_b+$HU$5<pax_b) -> 6.5 | HZ16: =$HV$5+seat_w_b*($HW$6*n_SA_b+$HU$5<pax_b) -> -1.84 | IA16: =HY16-L_fus/2 -> -11.31048
A17: =22/50 -> 0.44 | B17: =A17*WS_max -> 2449.1672 | C17: =B17/grav -> 249.74555 | D17: =TO_slope*B17 -> 0.1264945 | E17: =TW_2 -> 0.21941554 | F17: =TW_MA -> 0.21104328 | G17: =beta_cr/alpha_cr*(q_cr*CD_0/(beta_cr*B17)+K_ind*beta_cr*B17/q_cr+ROC_cr/V_cr) -> 0.4076216 | H17: =MAX(D17:G17) -> 0.4076216 | S17: tail 0.15 | T17: =L_fus-tail_len+0.15*tail_len -> 30.205644 | U17: =d_fus/2*(1-0.88*0.15^1.3) -> 1.8421753 | V17: =0.75*(d_fus/2-U17) -> 0.1115623 | X17: =T17-L_fus/2 -> 12.395164 | Y17: =V17+1*U17 -> 1.9537376 | Z17: =1*U17 -> 1.8421753 | AA17: =T17 -> 30.205644 | AC17: =x_hLE0+b_HT/2*TAN(RADIANS(sweepLE_HT))-L_fus/2+taper_HT*cr_HT -> 16.940321 | AD17: =-b_HT/2 -> -6.2176462 | AE17: =z_HT+b_HT/2*TAN(RADIANS(0)) -> 1.194555 | AL17: =AI7+0*L_nac-L_fus/2 -> -7.4249768 | AM17: =AH7+-1*D_nac/2 -> 4.9027996 | AN17: =AJ7+-1*D_nac/2 -> -3.1238022 | AP17: =x_main-L_fus/2+0*D_tyre/2 -> -0.30456748 | AQ17: =-h_cg+D_tyre/2+1*D_tyre/2 -> -2.5108116 | AY17: =MAX(0,MIN(12,n_rows-1)) -> 12 | AZ17: =x_eco0+AY17*(seat_pitch) -> 16.22 | BD17: =T17-L_fus/2 -> 12.395164 | BE17: =U17*1 -> 1.8421753 | BF17: =V17+U17*0 -> 0.1115623 | BG17: =BD17*COS(RADIANS(view_az))+BE17*SIN(RADIANS(view_az)) -> 10.679374 | BH17: =BF17*COS(RADIANS(view_el))+(BE17*COS(RADIANS(view_az))-BD17*SIN(RADIANS(view_az)))*SIN(RADIANS(view_el)) -> -2.6696895 | BK17: ="Nose gear: 2 wheels, tyre "&TEXT(D_nose,"0.00")&" m" -> Nose gear: 2 wheels, tyre 0.75 m | BM17: =$AZ$6+0.8*(seat_pitch)*($AY$6*n_SA+$AW$5<pax_e) -> 7.958 | BN17: =$AX$5+seat_w*($AY$6*n_SA+$AW$5<pax_e) -> -1.31 | BO17: =BM17-L_fus/2 -> -9.85248 | CA17: =$BX$6+0*lav_len -> 28.25 | CB17: =$BY$6+1*lav_w -> -0.865 | CE17: =12/24*CLmax_c -> 0.75 | CF17: =CD_0+K_ind*CE17^2 -> 0.04155912 | CG17: =CE17/CF17 -> 18.04658 | CH17: =12/24*CLmaxTO -> 1.05 | CI17: =CD_0+dCD0_f2+K_ind*CH17^2 -> 0.082092542 | CJ17: =CH17/CI17 -> 12.790443 | CK17: =12/24*CLmaxL -> 1.35 | CL17: =CD_0+dCD0_fMA+dCD0_gear+K_ind*CK17^2 -> 0.13421321 | CM17: =CK17/CL17 -> 10.058623 | CR17: =12/28*h_abs -> 4913.75 | CS17: =IF(CR17<=11000,288.15-0.0065*CR17,216.65) -> 256.21062 | CT17: =IF(CR17<=11000,rho_SL*(CS17/288.15)^4.25588,0.36392*EXP(-(CR17-11000)/6341.62)) -> 0.74301017 | CU17: =SQRT(1.4*287.053*CS17) -> 320.88073 | CV17: =TW_p*(CT17/rho_SL)^lapse_n -> 0.15187913 | CW17: =MIN(M_MO*CU17,SQRT(CV17*WS_p*(1+SQRT(1+3/(LD_max^2*CV17^2)))/(3*CT17*CD_0))) -> 202.51379 | CX17: =MAX(0,CW17*(CV17-0.5*CT17*CW17^2*CD_0/WS_p-K_ind*WS_p/(0.5*CT17*CW17^2))) -> 16.816009 | CY17: =IF(CR17>=h_cr,0,(MIN(CR18,h_cr)-CR17)/MAX(0.05,(CX17+CX18)/2)) -> 25.374129 | CZ17: =MAX(0,CV17^2-4*CD_0*K_ind) -> 0.020051703 | DA17: =MAX(SQRT(2*WS_p/(CT17*CLmax_c)),SQRT(2*WS_p*(CV17-SQRT(CZ17))/(2*CD_0)/CT17)) -> 94.439248 | DB17: =MAX(DA17,MIN(M_MO*CU17,SQRT(2*WS_p*(CV17+SQRT(CZ17))/(2*CD_0)/CT17))) -> 263.12219 | DC17: =DA17/CU17 -> 0.29431262 | DD17: =DB17/CU17 -> 0.82 | DJ17: =V_D -> 160.94389 | DK17: 0 | DX17: =d_fus/2*-1 -> -1.990925 | DY17: =d_fus/2*0 -> 0 | EB17: =$AH$5+D_nac/2*1 -> 7.1353903 | EC17: =$AJ$5+D_nac/2*0 -> -2.0075068 | ED17: =track/2+1*2.2*w_tyre/2 -> 4.0039099 | EE17: =-h_cg -> -3.663302 | EG17: =d_fus/2*-0.5 -> -0.9954625 | EH17: =d_fus/2*0.86603 -> 1.7242008 | EI17: =w_cabin/2*-0.5 -> -0.9325 | EJ17: =w_cabin/2*0.86603 -> 1.6151459 | EM17: =$AX$8+0.05*seat_w -> 0.2765 | EN17: =z_floor+0 -> -0.6 | ER17: =IF(6<n_door,x_door_f+IF(n_door>1,6/(n_door-1),0)*(x_door_r-x_door_f),IF(6<n_door+n_overwing,x_ac_w+(6-n_door-(n_overwing-1)/2)*seat_pitch,x_door_f)) -> 5.75 | ES17: =-1*w_cabin/2 -> -1.865 | GA17: Boeing 777-300ER | GB17: 396 | GC17: 351530 | GD17: 167830 | GE17: 436.8 | GF17: 64.8 | GG17: 73.86 | GH17: 513 | GI17: 2 | GJ17: 13650 | GK17: =ABS(LN(GC17/MTOW))+ABS(LN(MAX(1,GB17)/MAX(1,PaxTyp))) -> 2.5695219 | GZ17: CG station case 4 | HA17: =(OEW*HA13+W_fuel*HA11)/(OEW+W_fuel) -> 15.135279 | HB17: =(OEW*HB13+W_fuel*HB11)/(OEW+W_fuel) -> 18.545052 | HF17: =HR16 -> 72989.193 | HG17: =HF17*grav/WS_des -> 135.53841 | HH17: =SQRT(AR_*HG17) -> 35.883351 | HI17: =2*HG17/(HH17*(1+taper)) -> 6.0435117 | HJ17: =2/3*HI17*(1+taper+taper^2)/(1+taper) -> 4.2304582 | HK17: =49*MAX(0.5*HG17,HG17-d_fus*HI17*(1-(1-taper)*d_fus/(2*HH17))) -> 5511.2958 | HL17: =27*(c_HT*HJ17*HG17/L_tail+c_VT*HH17*HG17/L_tail) -> 1703.117 | HM17: =24*S_wet_fus -> 9147.0379 | HN17: =0.043*HF17 -> 3138.5353 | HO17: =1.3*N_eng*14.7*(TW_des*HF17*grav/N_eng/1000)^1.1*EXP(-0.045*BPR) -> 4710.2685 | HP17: =0.17*HF17 -> 12408.163 | HQ17: =SUM(HK17:HP17) -> 36618.417 | HR17: =IF(fuel_frac<0.95,MIN(100*MTOW_frac,(W_crew+W_pl+HQ17)/(1-fuel_frac)),HF17) -> 72990.193 | HW17: =MAX(0,MIN(12,n_rows_b-1)) -> 0 | HX17: =x_seat0+HW17*(bus_pitch*(n_rows_b>0)) -> 6.5 | HY17: =$HX$6+0.8*(bus_pitch*(n_rows_b>0))*($HW$6*n_SA_b+$HU$5<pax_b) -> 6.5 | HZ17: =$HV$5+seat_w_b*($HW$6*n_SA_b+$HU$5<pax_b) -> -1.84 | IA17: =HY17-L_fus/2 -> -11.31048
A18: =23/50 -> 0.46 | B18: =A18*WS_max -> 2560.493 | C18: =B18/grav -> 261.09762 | D18: =TO_slope*B18 -> 0.13224425 | E18: =TW_2 -> 0.21941554 | F18: =TW_MA -> 0.21104328 | G18: =beta_cr/alpha_cr*(q_cr*CD_0/(beta_cr*B18)+K_ind*beta_cr*B18/q_cr+ROC_cr/V_cr) -> 0.3947221 | H18: =MAX(D18:G18) -> 0.3947221 | S18: tail 0.30 | T18: =L_fus-tail_len+0.3*tail_len -> 31.161288 | U18: =d_fus/2*(1-0.88*0.3^1.3) -> 1.6246602 | V18: =0.75*(d_fus/2-U18) -> 0.27469861 | X18: =T18-L_fus/2 -> 13.350808 | Y18: =V18+1*U18 -> 1.8993588 | Z18: =1*U18 -> 1.6246602 | AA18: =T18 -> 31.161288 | AC18: =x_hLE0+b_HT/2*TAN(RADIANS(sweepLE_HT))-L_fus/2 -> 15.361236 | AD18: =-b_HT/2 -> -6.2176462 | AE18: =z_HT+b_HT/2*TAN(RADIANS(0)) -> 1.194555 | AL18: =AI7+1*L_nac-L_fus/2 -> -3.1011787 | AM18: =AH7+-1*D_nac/2 -> 4.9027996 | AN18: =AJ7+-1*D_nac/2 -> -3.1238022 | AP18: =x_main-L_fus/2 -> -0.30456748 | AQ18: =z_w0 -> -1.194555 | AY18: =MAX(0,MIN(13,n_rows-1)) -> 13 | AZ18: =x_eco0+AY18*(seat_pitch) -> 17.03 | BD18: =T18-L_fus/2 -> 13.350808 | BE18: =U18*1 -> 1.6246602 | BF18: =V18+U18*0 -> 0.27469861 | BG18: =BD18*COS(RADIANS(view_az))+BE18*SIN(RADIANS(view_az)) -> 11.271624 | BH18: =BF18*COS(RADIANS(view_el))+(BE18*COS(RADIANS(view_az))-BD18*SIN(RADIANS(view_az)))*SIN(RADIANS(view_el)) -> -2.8518614 | BK18: ="Ground" -> Ground | BM18: =$AZ$6+0.8*(seat_pitch)*($AY$6*n_SA+$AW$5<pax_e) -> 7.958 | BN18: =$AX$5 -> -1.84 | BO18: =BM18-L_fus/2 -> -9.85248 | CA18: =$BX$6+0*lav_len -> 28.25 | CB18: =$BY$6+0*lav_w -> -1.865 | CE18: =13/24*CLmax_c -> 0.8125 | CF18: =CD_0+K_ind*CE18^2 -> 0.045649245 | CG18: =CE18/CF18 -> 17.798761 | CH18: =13/24*CLmaxTO -> 1.1375 | CI18: =CD_0+dCD0_f2+K_ind*CH18^2 -> 0.090109187 | CJ18: =CH18/CI18 -> 12.623574 | CK18: =13/24*CLmaxL -> 1.4625 | CL18: =CD_0+dCD0_fMA+dCD0_gear+K_ind*CK18^2 -> 0.14746521 | CM18: =CK18/CL18 -> 9.9175934 | CR18: =13/28*h_abs -> 5323.2292 | CS18: =IF(CR18<=11000,288.15-0.0065*CR18,216.65) -> 253.54901 | CT18: =IF(CR18<=11000,rho_SL*(CS18/288.15)^4.25588,0.36392*EXP(-(CR18-11000)/6341.62)) -> 0.71071163 | CU18: =SQRT(1.4*287.053*CS18) -> 319.20966 | CV18: =TW_p*(CT18/rho_SL)^lapse_n -> 0.14340146 | CW18: =MIN(M_MO*CU18,SQRT(CV18*WS_p*(1+SQRT(1+3/(LD_max^2*CV18^2)))/(3*CT18*CD_0))) -> 202.12599 | CX18: =MAX(0,CW18*(CV18-0.5*CT18*CW18^2*CD_0/WS_p-K_ind*WS_p/(0.5*CT18*CW18^2))) -> 15.45932 | CY18: =IF(CR18>=h_cr,0,(MIN(CR19,h_cr)-CR18)/MAX(0.05,(CX18+CX19)/2)) -> 27.650837 | CZ18: =MAX(0,CV18^2-4*CD_0*K_ind) -> 0.01754841 | DA18: =MAX(SQRT(2*WS_p/(CT18*CLmax_c)),SQRT(2*WS_p*(CV18-SQRT(CZ18))/(2*CD_0)/CT18)) -> 96.561318 | DB18: =MAX(DA18,MIN(M_MO*CU18,SQRT(2*WS_p*(CV18+SQRT(CZ18))/(2*CD_0)/CT18))) -> 261.75192 | DC18: =DA18/CU18 -> 0.30250124 | DD18: =DB18/CU18 -> 0.82 | DJ18: =V_C -> 128.75511 | DK18: =n_neg -> -1 | DX18: =d_fus/2*-0.96593 -> -1.9230942 | DY18: =d_fus/2*-0.25882 -> -0.51529121 | ED18: =track/2+1*2.2*w_tyre/2 -> 4.0039099 | EE18: =-h_cg+D_tyre -> -2.5108116 | EG18: =d_fus/2*-0.64279 -> -1.2797467 | EH18: =d_fus/2*0.76604 -> 1.5251282 | EI18: =w_cabin/2*-0.64279 -> -1.1988033 | EJ18: =w_cabin/2*0.76604 -> 1.4286646 | EM18: =$AX$8+0.05*seat_w -> 0.2765 | EN18: =z_floor+1.1 -> 0.5 | ER18: =IF(6<n_door,x_door_f+IF(n_door>1,6/(n_door-1),0)*(x_door_r-x_door_f),IF(6<n_door+n_overwing,x_ac_w+(6-n_door-(n_overwing-1)/2)*seat_pitch,x_door_f)) -> 5.75 | ES18: =1*w_cabin/2 -> 1.865 | GA18: Boeing 747-400 | GB18: 416 | GC18: 396890 | GD18: 183520 | GE18: 541.2 | GF18: 64.44 | GG18: 70.66 | GH18: 276 | GI18: 4 | GJ18: 13450 | GK18: =ABS(LN(GC18/MTOW))+ABS(LN(MAX(1,GB18)/MAX(1,PaxTyp))) -> 2.7401571 | GZ18: CG station case 5 | HA18: =(OEW*HA13+PyldMax*x_pay)/(OEW+PyldMax) -> 15.927892 | HB18: =(OEW*HB13+PyldMax*x_pay)/(OEW+PyldMax) -> 17.309645 | HF18: =HR17 -> 72990.193 | HG18: =HF18*grav/WS_des -> 135.54026 | HH18: =SQRT(AR_*HG18) -> 35.883597 | HI18: =2*HG18/(HH18*(1+taper)) -> 6.0435531 | HJ18: =2/3*HI18*(1+taper+taper^2)/(1+taper) -> 4.2304872 | HK18: =49*MAX(0.5*HG18,HG18-d_fus*HI18*(1-(1-taper)*d_fus/(2*HH18))) -> 5511.3788 | HL18: =27*(c_HT*HJ18*HG18/L_tail+c_VT*HH18*HG18/L_tail) -> 1703.152 | HM18: =24*S_wet_fus -> 9147.0379 | HN18: =0.043*HF18 -> 3138.5783 | HO18: =1.3*N_eng*14.7*(TW_des*HF18*grav/N_eng/1000)^1.1*EXP(-0.045*BPR) -> 4710.3396 | HP18: =0.17*HF18 -> 12408.333 | HQ18: =SUM(HK18:HP18) -> 36618.82 | HR18: =IF(fuel_frac<0.95,MIN(100*MTOW_frac,(W_crew+W_pl+HQ18)/(1-fuel_frac)),HF18) -> 72990.765 | HW18: =MAX(0,MIN(13,n_rows_b-1)) -> 0 | HX18: =x_seat0+HW18*(bus_pitch*(n_rows_b>0)) -> 6.5 | HY18: =$HX$6+0.8*(bus_pitch*(n_rows_b>0))*($HW$6*n_SA_b+$HU$5<pax_b) -> 6.5 | HZ18: =$HV$5 -> -1.84 | IA18: =HY18-L_fus/2 -> -11.31048
A19: =24/50 -> 0.48 | B19: =A19*WS_max -> 2671.8188 | C19: =B19/grav -> 272.44969 | D19: =TO_slope*B19 -> 0.137994 | E19: =TW_2 -> 0.21941554 | F19: =TW_MA -> 0.21104328 | G19: =beta_cr/alpha_cr*(q_cr*CD_0/(beta_cr*B19)+K_ind*beta_cr*B19/q_cr+ROC_cr/V_cr) -> 0.38305161 | H19: =MAX(D19:G19) -> 0.38305161 | S19: tail 0.45 | T19: =L_fus-tail_len+0.45*tail_len -> 32.116932 | U19: =d_fus/2*(1-0.88*0.45^1.3) -> 1.3704649 | V19: =0.75*(d_fus/2-U19) -> 0.46534506 | X19: =T19-L_fus/2 -> 14.306452 | Y19: =V19+1*U19 -> 1.83581 | Z19: =1*U19 -> 1.3704649 | AA19: =T19 -> 32.116932 | AC19: =x_hLE0-L_fus/2 -> 11.164541 | AD19: 0 | AE19: =z_HT -> 1.194555 | AL19: =AI7+1*L_nac-L_fus/2 -> -3.1011787 | AM19: =AH7+1*D_nac/2 -> 7.1353903 | AN19: =AJ7+1*D_nac/2 -> -0.8912115 | AY19: =MAX(0,MIN(14,n_rows-1)) -> 14 | AZ19: =x_eco0+AY19*(seat_pitch) -> 17.84 | BD19: =T19-L_fus/2 -> 14.306452 | BE19: =U19*1 -> 1.3704649 | BF19: =V19+U19*0 -> 0.46534506 | BG19: =BD19*COS(RADIANS(view_az))+BE19*SIN(RADIANS(view_az)) -> 11.840296 | BH19: =BF19*COS(RADIANS(view_el))+(BE19*COS(RADIANS(view_az))-BD19*SIN(RADIANS(view_az)))*SIN(RADIANS(view_el)) -> -3.0209756 | BK19: ="Design mission: "&TEXT(Range_km,"#,##0")&" km with "&TEXT(W_pl,"#,##0")&" kg" -> Design mission: 5,000 km with 14,250 kg | BM19: =$AZ$6+0.2*(seat_pitch)*($AY$6*n_SA+$AW$5<pax_e) -> 7.472 | BN19: =$AX$5 -> -1.84 | BO19: =BM19-L_fus/2 -> -10.33848 | CA19: =$BX$6+1*lav_len -> 29.25 | CB19: =$BY$6+1*lav_w -> -0.865 | CE19: =14/24*CLmax_c -> 0.875 | CF19: =CD_0+K_ind*CE19^2 -> 0.05006658 | CG19: =CE19/CF19 -> 17.476728 | CH19: =14/24*CLmaxTO -> 1.225 | CI19: =CD_0+dCD0_f2+K_ind*CH19^2 -> 0.098767163 | CJ19: =CH19/CI19 -> 12.402908 | CK19: =14/24*CLmaxL -> 1.575 | CL19: =CD_0+dCD0_fMA+dCD0_gear+K_ind*CK19^2 -> 0.16177738 | CM19: =CK19/CL19 -> 9.7356011 | CR19: =14/28*h_abs -> 5732.7084 | CS19: =IF(CR19<=11000,288.15-0.0065*CR19,216.65) -> 250.8874 | CT19: =IF(CR19<=11000,rho_SL*(CS19/288.15)^4.25588,0.36392*EXP(-(CR19-11000)/6341.62)) -> 0.67949834 | CU19: =SQRT(1.4*287.053*CS19) -> 317.5298 | CV19: =TW_p*(CT19/rho_SL)^lapse_n -> 0.13531495 | CW19: =MIN(M_MO*CU19,SQRT(CV19*WS_p*(1+SQRT(1+3/(LD_max^2*CV19^2)))/(3*CT19*CD_0))) -> 201.82095 | CX19: =MAX(0,CW19*(CV19-0.5*CT19*CW19^2*CD_0/WS_p-K_ind*WS_p/(0.5*CT19*CW19^2))) -> 14.15853 | CY19: =IF(CR19>=h_cr,0,(MIN(CR20,h_cr)-CR19)/MAX(0.05,(CX19+CX20)/2)) -> 30.254419 | CZ19: =MAX(0,CV19^2-4*CD_0*K_ind) -> 0.015294568 | DA19: =MAX(SQRT(2*WS_p/(CT19*CLmax_c)),SQRT(2*WS_p*(CV19-SQRT(CZ19))/(2*CD_0)/CT19)) -> 98.754228 | DB19: =MAX(DA19,MIN(M_MO*CU19,SQRT(2*WS_p*(CV19+SQRT(CZ19))/(2*CD_0)/CT19))) -> 260.37443 | DC19: =DA19/CU19 -> 0.31100775 | DD19: =DB19/CU19 -> 0.82 | DJ19: =10/10*V_S1*SQRT(-n_neg/0.8) -> 84.764648 | DK19: =-0.8*(10/10*SQRT(-n_neg/0.8))^2 -> -1 | DX19: =d_fus/2*-0.86603 -> -1.7242008 | DY19: =d_fus/2*-0.5 -> -0.9954625 | EB19: =$AH$6+D_nac/2*1 -> -4.9027996 | EC19: =$AJ$6+D_nac/2*0 -> -2.0075068 | ED19: =track/2+0*2.2*w_tyre/2 -> 3.5406441 | EE19: =-h_cg+D_tyre -> -2.5108116 | EG19: =d_fus/2*-0.76604 -> -1.5251282 | EH19: =d_fus/2*0.64279 -> 1.2797467 | EI19: =w_cabin/2*-0.76604 -> -1.4286646 | EJ19: =w_cabin/2*0.64279 -> 1.1988033 | EM19: =$AX$8+0.95*seat_w -> 0.7535 | EN19: =z_floor+1.1 -> 0.5 | ER19: =IF(7<n_door,x_door_f+IF(n_door>1,7/(n_door-1),0)*(x_door_r-x_door_f),IF(7<n_door+n_overwing,x_ac_w+(7-n_door-(n_overwing-1)/2)*seat_pitch,x_door_f)) -> 5.75 | ES19: =-1*w_cabin/2 -> -1.865 | GA19: Airbus A380-800 | GB19: 525 | GC19: 575000 | GD19: 277000 | GE19: 845 | GF19: 79.75 | GG19: 72.72 | GH19: 311 | GI19: 4 | GJ19: 15200 | GK19: =ABS(LN(GC19/MTOW))+ABS(LN(MAX(1,GB19)/MAX(1,PaxTyp))) -> 3.343581 | GZ19: CG % MAC case 1 | HA19: =(HA14-HA6)/MAC -> 0.74122046 | HB19: =(HB14-HB6)/MAC -> -0.1309849 | HF19: =HR18 -> 72990.765 | HG19: =HF19*grav/WS_des -> 135.54133 | HH19: =SQRT(AR_*HG19) -> 35.883737 | HI19: =2*HG19/(HH19*(1+taper)) -> 6.0435768 | HJ19: =2/3*HI19*(1+taper+taper^2)/(1+taper) -> 4.2305038 | HK19: =49*MAX(0.5*HG19,HG19-d_fus*HI19*(1-(1-taper)*d_fus/(2*HH19))) -> 5511.4262 | HL19: =27*(c_HT*HJ19*HG19/L_tail+c_VT*HH19*HG19/L_tail) -> 1703.172 | HM19: =24*S_wet_fus -> 9147.0379 | HN19: =0.043*HF19 -> 3138.6029 | HO19: =1.3*N_eng*14.7*(TW_des*HF19*grav/N_eng/1000)^1.1*EXP(-0.045*BPR) -> 4710.3802 | HP19: =0.17*HF19 -> 12408.43 | HQ19: =SUM(HK19:HP19) -> 36619.049 | HR19: =IF(fuel_frac<0.95,MIN(100*MTOW_frac,(W_crew+W_pl+HQ19)/(1-fuel_frac)),HF19) -> 72991.092 | HW19: =MAX(0,MIN(14,n_rows_b-1)) -> 0 | HX19: =x_seat0+HW19*(bus_pitch*(n_rows_b>0)) -> 6.5 | HY19: =$HX$6+0.2*(bus_pitch*(n_rows_b>0))*($HW$6*n_SA_b+$HU$5<pax_b) -> 6.5 | HZ19: =$HV$5 -> -1.84 | IA19: =HY19-L_fus/2 -> -11.31048
A20: =25/50 -> 0.5 | B20: =A20*WS_max -> 2783.1446 | C20: =B20/grav -> 283.80176 | D20: =TO_slope*B20 -> 0.14374375 | E20: =TW_2 -> 0.21941554 | F20: =TW_MA -> 0.21104328 | G20: =beta_cr/alpha_cr*(q_cr*CD_0/(beta_cr*B20)+K_ind*beta_cr*B20/q_cr+ROC_cr/V_cr) -> 0.37246266 | H20: =MAX(D20:G20) -> 0.37246266 | S20: tail 0.60 | T20: =L_fus-tail_len+0.6*tail_len -> 33.072576 | U20: =d_fus/2*(1-0.88*0.6^1.3) -> 1.0890752 | V20: =0.75*(d_fus/2-U20) -> 0.67638733 | X20: =T20-L_fus/2 -> 15.262096 | Y20: =V20+1*U20 -> 1.7654626 | Z20: =1*U20 -> 1.0890752 | AA20: =T20 -> 33.072576 | AL20: =AI7+0*L_nac-L_fus/2 -> -7.4249768 | AM20: =AH7+1*D_nac/2 -> 7.1353903 | AN20: =AJ7+1*D_nac/2 -> -0.8912115 | AP20: =x_nose-L_fus/2+0*D_nose/2 -> -13.840532 | AQ20: =-h_cg+D_nose/2+1*D_nose/2 -> -2.9141833 | AY20: =MAX(0,MIN(15,n_rows-1)) -> 15 | AZ20: =x_eco0+AY20*(seat_pitch) -> 18.65 | BD20: =T20-L_fus/2 -> 15.262096 | BE20: =U20*1 -> 1.0890752 | BF20: =V20+U20*0 -> 0.67638733 | BG20: =BD20*COS(RADIANS(view_az))+BE20*SIN(RADIANS(view_az)) -> 12.391488 | BH20: =BF20*COS(RADIANS(view_el))+(BE20*COS(RADIANS(view_az))-BD20*SIN(RADIANS(view_az)))*SIN(RADIANS(view_el)) -> -3.180409 | BK20: ="Optimised design point: W/S = "&TEXT(WS_des,"0")&" N/m2, T/W = "&TEXT(TW_des,"0.000") -> Optimised design point: W/S = 5281 N/m2, T/W = 0.273 | BM20: =$AZ$6+(seat_pitch) -> 8.12 | BN20: =$AX$5 -> -1.84 | BO20: =BM20-L_fus/2 -> -9.69048 | CA20: =$BX$6+1*lav_len -> 29.25 | CB20: =$BY$6+0*lav_w -> -1.865 | CE20: =15/24*CLmax_c -> 0.9375 | CF20: =CD_0+K_ind*CE20^2 -> 0.054811125 | CG20: =CE20/CF20 -> 17.104192 | CH20: =15/24*CLmaxTO -> 1.3125 | CI20: =CD_0+dCD0_f2+K_ind*CH20^2 -> 0.10806647 | CJ20: =CH20/CI20 -> 12.145303 | CK20: =15/24*CLmaxL -> 1.6875 | CL20: =CD_0+dCD0_fMA+dCD0_gear+K_ind*CK20^2 -> 0.1771497 | CM20: =CK20/CL20 -> 9.5258416 | CR20: =15/28*h_abs -> 6142.1875 | CS20: =IF(CR20<=11000,288.15-0.0065*CR20,216.65) -> 248.22578 | CT20: =IF(CR20<=11000,rho_SL*(CS20/288.15)^4.25588,0.36392*EXP(-(CR20-11000)/6341.62)) -> 0.64934477 | CU20: =SQRT(1.4*287.053*CS20) -> 315.841 | CV20: =TW_p*(CT20/rho_SL)^lapse_n -> 0.12760543 | CW20: =MIN(M_MO*CU20,SQRT(CV20*WS_p*(1+SQRT(1+3/(LD_max^2*CV20^2)))/(3*CT20*CD_0))) -> 201.60647 | CX20: =MAX(0,CW20*(CV20-0.5*CT20*CW20^2*CD_0/WS_p-K_ind*WS_p/(0.5*CT20*CW20^2))) -> 12.910518 | CY20: =IF(CR20>=h_cr,0,(MIN(CR21,h_cr)-CR20)/MAX(0.05,(CX20+CX21)/2)) -> 33.26022 | CZ20: =MAX(0,CV20^2-4*CD_0*K_ind) -> 0.013267577 | DA20: =MAX(SQRT(2*WS_p/(CT20*CLmax_c)),SQRT(2*WS_p*(CV20-SQRT(CZ20))/(2*CD_0)/CT20)) -> 101.02113 | DB20: =MAX(DA20,MIN(M_MO*CU20,SQRT(2*WS_p*(CV20+SQRT(CZ20))/(2*CD_0)/CT20))) -> 258.98962 | DC20: =DA20/CU20 -> 0.31984806 | DD20: =DB20/CU20 -> 0.82 | DJ20: =9/10*V_S1*SQRT(-n_neg/0.8) -> 76.288183 | DK20: =-0.8*(9/10*SQRT(-n_neg/0.8))^2 -> -0.81 | DX20: =d_fus/2*-0.70711 -> -1.407803 | DY20: =d_fus/2*-0.70711 -> -1.407803 | EB20: =$AH$6+D_nac/2*0.86603 -> -5.0523497 | EC20: =$AJ$6+D_nac/2*0.5 -> -1.4493592 | EG20: =d_fus/2*-0.86603 -> -1.7242008 | EH20: =d_fus/2*0.5 -> 0.9954625 | EI20: =w_cabin/2*-0.86603 -> -1.6151459 | EJ20: =w_cabin/2*0.5 -> 0.9325 | EM20: =$AX$8+0.95*seat_w -> 0.7535 | EN20: =z_floor+0 -> -0.6 | ER20: =IF(7<n_door,x_door_f+IF(n_door>1,7/(n_door-1),0)*(x_door_r-x_door_f),IF(7<n_door+n_overwing,x_ac_w+(7-n_door-(n_overwing-1)/2)*seat_pitch,x_door_f)) -> 5.75 | ES20: =1*w_cabin/2 -> 1.865 | GA20: Cessna 172S (piston) | GB20: 3 | GC20: 1157 | GD20: 767 | GE20: 16.2 | GF20: 11 | GG20: 8.28 | GH20: 0 | GI20: 1 | GJ20: 1185 | GK20: =ABS(LN(GC20/MTOW))+ABS(LN(MAX(1,GB20)/MAX(1,PaxTyp))) -> 8.0297446 | GZ20: CG % MAC case 2 | HA20: =(HA15-HA6)/MAC -> 0.81216186 | HB20: =(HB15-HB6)/MAC -> -0.20065798 | HF20: =HR19 -> 72991.092 | HG20: =HF20*grav/WS_des -> 135.54193 | HH20: =SQRT(AR_*HG20) -> 35.883818 | HI20: =2*HG20/(HH20*(1+taper)) -> 6.0435903 | HJ20: =2/3*HI20*(1+taper+taper^2)/(1+taper) -> 4.2305132 | HK20: =49*MAX(0.5*HG20,HG20-d_fus*HI20*(1-(1-taper)*d_fus/(2*HH20))) -> 5511.4533 | HL20: =27*(c_HT*HJ20*HG20/L_tail+c_VT*HH20*HG20/L_tail) -> 1703.1835 | HM20: =24*S_wet_fus -> 9147.0379 | HN20: =0.043*HF20 -> 3138.617 | HO20: =1.3*N_eng*14.7*(TW_des*HF20*grav/N_eng/1000)^1.1*EXP(-0.045*BPR) -> 4710.4034 | HP20: =0.17*HF20 -> 12408.486 | HQ20: =SUM(HK20:HP20) -> 36619.181 | HR20: =IF(fuel_frac<0.95,MIN(100*MTOW_frac,(W_crew+W_pl+HQ20)/(1-fuel_frac)),HF20) -> 72991.279 | HW20: =MAX(0,MIN(15,n_rows_b-1)) -> 0 | HX20: =x_seat0+HW20*(bus_pitch*(n_rows_b>0)) -> 6.5 | HY20: =$HX$6+(bus_pitch*(n_rows_b>0)) -> 6.5 | HZ20: =$HV$5 -> -1.84 | IA20: =HY20-L_fus/2 -> -11.31048
A21: =26/50 -> 0.52 | B21: =A21*WS_max -> 2894.4704 | C21: =B21/grav -> 295.15384 | D21: =TO_slope*B21 -> 0.1494935 | E21: =TW_2 -> 0.21941554 | F21: =TW_MA -> 0.21104328 | G21: =beta_cr/alpha_cr*(q_cr*CD_0/(beta_cr*B21)+K_ind*beta_cr*B21/q_cr+ROC_cr/V_cr) -> 0.36283045 | H21: =MAX(D21:G21) -> 0.36283045 | S21: tail 0.75 | T21: =L_fus-tail_len+0.75*tail_len -> 34.02822 | U21: =d_fus/2*(1-0.88*0.75^1.3) -> 0.78556378 | V21: =0.75*(d_fus/2-U21) -> 0.90402091 | X21: =T21-L_fus/2 -> 16.21774 | Y21: =V21+1*U21 -> 1.6895847 | Z21: =1*U21 -> 0.78556378 | AA21: =T21 -> 34.02822 | AC21: =x_vLE0-L_fus/2 -> 10.524635 | AD21: 0 | AE21: =z_VT0 -> 1.59274 | AL21: =AI7+0*L_nac-L_fus/2 -> -7.4249768 | AM21: =AH7+-1*D_nac/2 -> 4.9027996 | AN21: =AJ7+-1*D_nac/2 -> -3.1238022 | AP21: =x_nose-L_fus/2+-0.5*D_nose/2 -> -14.027812 | AQ21: =-h_cg+D_nose/2+0.86603*D_nose/2 -> -2.964363 | AY21: =MAX(0,MIN(16,n_rows-1)) -> 16 | AZ21: =x_eco0+AY21*(seat_pitch) -> 19.46 | BD21: =T21-L_fus/2 -> 16.21774 | BE21: =U21*1 -> 0.78556378 | BF21: =V21+U21*0 -> 0.90402091 | BG21: =BD21*COS(RADIANS(view_az))+BE21*SIN(RADIANS(view_az)) -> 12.92846 | BH21: =BF21*COS(RADIANS(view_el))+(BE21*COS(RADIANS(view_az))-BD21*SIN(RADIANS(view_az)))*SIN(RADIANS(view_el)) -> -3.3319674 | BM21: =$AZ$7+0.2*(seat_pitch)*($AY$7*n_SA+$AW$5<pax_e) -> 8.282 | BN21: =$AX$5 -> -1.84 | BO21: =BM21-L_fus/2 -> -9.52848 | CA21: =$BX$6+0*lav_len -> 28.25 | CB21: =$BY$6+1*lav_w -> -0.865 | CE21: =16/24*CLmax_c -> 1 | CF21: =CD_0+K_ind*CE21^2 -> 0.05988288 | CG21: =CE21/CF21 -> 16.699264 | CH21: =16/24*CLmaxTO -> 1.4 | CI21: =CD_0+dCD0_f2+K_ind*CH21^2 -> 0.11800711 | CJ21: =CH21/CI21 -> 11.863692 | CK21: =16/24*CLmaxL -> 1.8 | CL21: =CD_0+dCD0_fMA+dCD0_gear+K_ind*CK21^2 -> 0.19358219 | CM21: =CK21/CL21 -> 9.2983762 | CR21: =16/28*h_abs -> 6551.6667 | CS21: =IF(CR21<=11000,288.15-0.0065*CR21,216.65) -> 245.56417 | CT21: =IF(CR21<=11000,rho_SL*(CS21/288.15)^4.25588,0.36392*EXP(-(CR21-11000)/6341.62)) -> 0.62022572 | CU21: =SQRT(1.4*287.053*CS21) -> 314.14312 | CV21: =TW_p*(CT21/rho_SL)^lapse_n -> 0.12025907 | CW21: =MIN(M_MO*CU21,SQRT(CV21*WS_p*(1+SQRT(1+3/(LD_max^2*CV21^2)))/(3*CT21*CD_0))) -> 201.49078 | CX21: =MAX(0,CW21*(CV21-0.5*CT21*CW21^2*CD_0/WS_p-K_ind*WS_p/(0.5*CT21*CW21^2))) -> 11.712239 | CY21: =IF(CR21>=h_cr,0,(MIN(CR22,h_cr)-CR21)/MAX(0.05,(CX21+CX22)/2)) -> 36.769173 | CZ21: =MAX(0,CV21^2-4*CD_0*K_ind) -> 0.011446677 | DA21: =MAX(SQRT(2*WS_p/(CT21*CLmax_c)),SQRT(2*WS_p*(CV21-SQRT(CZ21))/(2*CD_0)/CT21)) -> 103.36536 | DB21: =MAX(DA21,MIN(M_MO*CU21,SQRT(2*WS_p*(CV21+SQRT(CZ21))/(2*CD_0)/CT21))) -> 257.59736 | DC21: =DA21/CU21 -> 0.32903906 | DD21: =DB21/CU21 -> 0.82 | DJ21: =8/10*V_S1*SQRT(-n_neg/0.8) -> 67.811718 | DK21: =-0.8*(8/10*SQRT(-n_neg/0.8))^2 -> -0.64 | DX21: =d_fus/2*-0.5 -> -0.9954625 | DY21: =d_fus/2*-0.86603 -> -1.7242008 | EB21: =$AH$6+D_nac/2*0.5 -> -5.4609472 | EC21: =$AJ$6+D_nac/2*0.86603 -> -1.0407616 | ED21: =0+0*2.2*nose_scale*w_tyre/2 -> 0 | EE21: =-0.35*d_fus -> -1.3936475 | EG21: =d_fus/2*-0.93969 -> -1.8708523 | EH21: =d_fus/2*0.34202 -> 0.68093617 | EI21: =w_cabin/2*-0.93969 -> -1.7525218 | EJ21: =w_cabin/2*0.34202 -> 0.6378673 | EM21: =$AX$9+0.05*seat_w -> 0.8065 | EN21: =z_floor+0 -> -0.6 | GA21: Pilatus PC-12 (turboprop) | GB21: 9 | GC21: 4740 | GD21: 2810 | GE21: 25.8 | GF21: 16.28 | GG21: 14.4 | GH21: 0 | GI21: 1 | GJ21: 3300 | GK21: =ABS(LN(GC21/MTOW))+ABS(LN(MAX(1,GB21)/MAX(1,PaxTyp))) -> 5.5209256 | GZ21: CG % MAC case 3 | HA21: =(HA16-HA6)/MAC -> 0.70470553 | HB21: =(HB16-HB6)/MAC -> -0.0076025352 | HF21: =HR20 -> 72991.279 | HG21: =HF21*grav/WS_des -> 135.54228 | HH21: =SQRT(AR_*HG21) -> 35.883863 | HI21: =2*HG21/(HH21*(1+taper)) -> 6.043598 | HJ21: =2/3*HI21*(1+taper+taper^2)/(1+taper) -> 4.2305186 | HK21: =49*MAX(0.5*HG21,HG21-d_fus*HI21*(1-(1-taper)*d_fus/(2*HH21))) -> 5511.4688 | HL21: =27*(c_HT*HJ21*HG21/L_tail+c_VT*HH21*HG21/L_tail) -> 1703.19 | HM21: =24*S_wet_fus -> 9147.0379 | HN21: =0.043*HF21 -> 3138.625 | HO21: =1.3*N_eng*14.7*(TW_des*HF21*grav/N_eng/1000)^1.1*EXP(-0.045*BPR) -> 4710.4166 | HP21: =0.17*HF21 -> 12408.517 | HQ21: =SUM(HK21:HP21) -> 36619.256 | HR21: =IF(fuel_frac<0.95,MIN(100*MTOW_frac,(W_crew+W_pl+HQ21)/(1-fuel_frac)),HF21) -> 72991.386 | HW21: =MAX(0,MIN(16,n_rows_b-1)) -> 0 | HX21: =x_seat0+HW21*(bus_pitch*(n_rows_b>0)) -> 6.5 | HY21: =$HX$7+0.2*(bus_pitch*(n_rows_b>0))*($HW$7*n_SA_b+$HU$5<pax_b) -> 6.5 | HZ21: =$HV$5 -> -1.84 | IA21: =HY21-L_fus/2 -> -11.31048
A22: =27/50 -> 0.54 | B22: =A22*WS_max -> 3005.7961 | C22: =B22/grav -> 306.50591 | D22: =TO_slope*B22 -> 0.15524325 | E22: =TW_2 -> 0.21941554 | F22: =TW_MA -> 0.21104328 | G22: =beta_cr/alpha_cr*(q_cr*CD_0/(beta_cr*B22)+K_ind*beta_cr*B22/q_cr+ROC_cr/V_cr) -> 0.35404867 | H22: =MAX(D22:G22) -> 0.35404867 | S22: tail 0.90 | T22: =L_fus-tail_len+0.9*tail_len -> 34.983864 | U22: =d_fus/2*(1-0.88*0.9^1.3) -> 0.46317309 | V22: =0.75*(d_fus/2-U22) -> 1.1458139 | X22: =T22-L_fus/2 -> 17.173384 | Y22: =V22+1*U22 -> 1.608987 | Z22: =1*U22 -> 0.46317309 | AA22: =T22 -> 34.983864 | AC22: =x_vLE0+b_VT*TAN(RADIANS(sweepLE_VT))-L_fus/2 -> 15.560177 | AD22: 0 | AE22: =z_VT0+b_VT -> 8.2707682 | AP22: =x_nose-L_fus/2+-0.86603*D_nose/2 -> -14.164912 | AQ22: =-h_cg+D_nose/2+0.5*D_nose/2 -> -3.1014629 | AY22: =MAX(0,MIN(17,n_rows-1)) -> 17 | AZ22: =x_eco0+AY22*(seat_pitch) -> 20.27 | BD22: =T22-L_fus/2 -> 17.173384 | BE22: =U22*1 -> 0.46317309 | BF22: =V22+U22*0 -> 1.1458139 | BG22: =BD22*COS(RADIANS(view_az))+BE22*SIN(RADIANS(view_az)) -> 13.453297 | BH22: =BF22*COS(RADIANS(view_el))+(BE22*COS(RADIANS(view_az))-BD22*SIN(RADIANS(view_az)))*SIN(RADIANS(view_el)) -> -3.4768049 | BM22: =$AZ$7+0.2*(seat_pitch)*($AY$7*n_SA+$AW$5<pax_e) -> 8.282 | BN22: =$AX$5+seat_w*($AY$7*n_SA+$AW$5<pax_e) -> -1.31 | BO22: =BM22-L_fus/2 -> -9.52848 | CE22: =17/24*CLmax_c -> 1.0625 | CF22: =CD_0+K_ind*CE22^2 -> 0.065281845 | CG22: =CE22/CF22 -> 16.275582 | CH22: =17/24*CLmaxTO -> 1.4875 | CI22: =CD_0+dCD0_f2+K_ind*CH22^2 -> 0.12858908 | CJ22: =CH22/CI22 -> 11.567856 | CK22: =17/24*CLmaxL -> 1.9125 | CL22: =CD_0+dCD0_fMA+dCD0_gear+K_ind*CK22^2 -> 0.21107483 | CM22: =CK22/CL22 -> 9.0607675 | CR22: =17/28*h_abs -> 6961.1459 | CS22: =IF(CR22<=11000,288.15-0.0065*CR22,216.65) -> 242.90255 | CT22: =IF(CR22<=11000,rho_SL*(CS22/288.15)^4.25588,0.36392*EXP(-(CR22-11000)/6341.62)) -> 0.59211634 | CU22: =SQRT(1.4*287.053*CS22) -> 312.43602 | CV22: =TW_p*(CT22/rho_SL)^lapse_n -> 0.11326244 | CW22: =MIN(M_MO*CU22,SQRT(CV22*WS_p*(1+SQRT(1+3/(LD_max^2*CV22^2)))/(3*CT22*CD_0))) -> 201.48252 | CX22: =MAX(0,CW22*(CV22-0.5*CT22*CW22^2*CD_0/WS_p-K_ind*WS_p/(0.5*CT22*CW22^2))) -> 10.560721 | CY22: =IF(CR22>=h_cr,0,(MIN(CR23,h_cr)-CR22)/MAX(0.05,(CX22+CX23)/2)) -> 40.9197 | CZ22: =MAX(0,CV22^2-4*CD_0*K_ind) -> 0.0098128138 | DA22: =MAX(SQRT(2*WS_p/(CT22*CLmax_c)),SQRT(2*WS_p*(CV22-SQRT(CZ22))/(2*CD_0)/CT22)) -> 105.79043 | DB22: =MAX(DA22,MIN(M_MO*CU22,SQRT(2*WS_p*(CV22+SQRT(CZ22))/(2*CD_0)/CT22))) -> 256.19754 | DC22: =DA22/CU22 -> 0.33859869 | DD22: =DB22/CU22 -> 0.82 | DJ22: =7/10*V_S1*SQRT(-n_neg/0.8) -> 59.335254 | DK22: =-0.8*(7/10*SQRT(-n_neg/0.8))^2 -> -0.49 | DX22: =d_fus/2*-0.25882 -> -0.51529121 | DY22: =d_fus/2*-0.96593 -> -1.9230942 | EB22: =$AH$6+D_nac/2*0 -> -6.0190949 | EC22: =$AJ$6+D_nac/2*1 -> -0.8912115 | ED22: =0+0*2.2*nose_scale*w_tyre/2 -> 0 | EE22: =-h_cg+D_nose -> -2.9141833 | EG22: =d_fus/2*-0.98481 -> -1.9606828 | EH22: =d_fus/2*0.17365 -> 0.34572413 | EI22: =w_cabin/2*-0.98481 -> -1.8366706 | EJ22: =w_cabin/2*0.17365 -> 0.32385725 | EM22: =$AX$9+0.05*seat_w -> 0.8065 | EN22: =z_floor+1.1 -> 0.5 | GA22: Beechcraft 1900D (turboprop) | GB22: 19 | GC22: 7765 | GD22: 4932 | GE22: 28.8 | GF22: 17.65 | GG22: 17.63 | GH22: 0 | GI22: 2 | GJ22: 1300 | GK22: =ABS(LN(GC22/MTOW))+ABS(LN(MAX(1,GB22)/MAX(1,PaxTyp))) -> 4.2801219 | GZ22: CG % MAC case 4 | HA22: =(HA17-HA6)/MAC -> 0.63313965 | HB22: =(HB17-HB6)/MAC -> 0.084636349 | HF22: =HR21 -> 72991.386 | HG22: =HF22*grav/WS_des -> 135.54248 | HH22: =SQRT(AR_*HG22) -> 35.88389 | HI22: =2*HG22/(HH22*(1+taper)) -> 6.0436025 | HJ22: =2/3*HI22*(1+taper+taper^2)/(1+taper) -> 4.2305217 | HK22: =49*MAX(0.5*HG22,HG22-d_fus*HI22*(1-(1-taper)*d_fus/(2*HH22))) -> 5511.4776 | HL22: =27*(c_HT*HJ22*HG22/L_tail+c_VT*HH22*HG22/L_tail) -> 1703.1938 | HM22: =24*S_wet_fus -> 9147.0379 | HN22: =0.043*HF22 -> 3138.6296 | HO22: =1.3*N_eng*14.7*(TW_des*HF22*grav/N_eng/1000)^1.1*EXP(-0.045*BPR) -> 4710.4242 | HP22: =0.17*HF22 -> 12408.536 | HQ22: =SUM(HK22:HP22) -> 36619.299 | HR22: =IF(fuel_frac<0.95,MIN(100*MTOW_frac,(W_crew+W_pl+HQ22)/(1-fuel_frac)),HF22) -> 72991.447 | HW22: =MAX(0,MIN(17,n_rows_b-1)) -> 0 | HX22: =x_seat0+HW22*(bus_pitch*(n_rows_b>0)) -> 6.5 | HY22: =$HX$7+0.2*(bus_pitch*(n_rows_b>0))*($HW$7*n_SA_b+$HU$5<pax_b) -> 6.5 | HZ22: =$HV$5+seat_w_b*($HW$7*n_SA_b+$HU$5<pax_b) -> -1.84 | IA22: =HY22-L_fus/2 -> -11.31048
A23: =28/50 -> 0.56 | B23: =A23*WS_max -> 3117.1219 | C23: =B23/grav -> 317.85798 | D23: =TO_slope*B23 -> 0.160993 | E23: =TW_2 -> 0.21941554 | F23: =TW_MA -> 0.21104328 | G23: =beta_cr/alpha_cr*(q_cr*CD_0/(beta_cr*B23)+K_ind*beta_cr*B23/q_cr+ROC_cr/V_cr) -> 0.34602622 | H23: =MAX(D23:G23) -> 0.34602622 | S23: tail 1.00 | T23: =L_fus-tail_len+1*tail_len -> 35.62096 | U23: =d_fus/2*(1-0.88*1^1.3) -> 0.238911 | V23: =0.75*(d_fus/2-U23) -> 1.3140105 | X23: =T23-L_fus/2 -> 17.81048 | Y23: =V23+1*U23 -> 1.5529215 | Z23: =1*U23 -> 0.238911 | AA23: =T23 -> 35.62096 | AC23: =x_vLE0+b_VT*TAN(RADIANS(sweepLE_VT))+taper_VT*cr_VT-L_fus/2 -> 17.597048 | AD23: 0 | AE23: =z_VT0+b_VT -> 8.2707682 | AL23: =AI8+0*L_nac-L_fus/2 -> -7.4249768 | AM23: =AH8+-1*D_nac/2 -> -7.1353903 | AN23: =AJ8+-1*D_nac/2 -> -3.1238022 | AP23: =x_nose-L_fus/2+-1*D_nose/2 -> -14.215092 | AQ23: =-h_cg+D_nose/2+0*D_nose/2 -> -3.2887426 | AY23: =MAX(0,MIN(18,n_rows-1)) -> 18 | AZ23: =x_eco0+AY23*(seat_pitch) -> 21.08 | BD23: =T23-L_fus/2 -> 17.81048 | BE23: =U23*1 -> 0.238911 | BF23: =V23+U23*0 -> 1.3140105 | BG23: =BD23*COS(RADIANS(view_az))+BE23*SIN(RADIANS(view_az)) -> 13.797188 | BH23: =BF23*COS(RADIANS(view_el))+(BE23*COS(RADIANS(view_az))-BD23*SIN(RADIANS(view_az)))*SIN(RADIANS(view_el)) -> -3.5700402 | BM23: =$AZ$7 -> 8.12 | BN23: =$AX$5+seat_w*($AY$7*n_SA+$AW$5<pax_e) -> -1.31 | BO23: =BM23-L_fus/2 -> -9.69048 | CA23: =$BX$7+0*lav_len -> 28.25 | CB23: =$BY$7+0*lav_w -> 0.865 | CE23: =18/24*CLmax_c -> 1.125 | CF23: =CD_0+K_ind*CE23^2 -> 0.07100802 | CG23: =CE23/CF23 -> 15.843281 | CH23: =18/24*CLmaxTO -> 1.575 | CI23: =CD_0+dCD0_f2+K_ind*CH23^2 -> 0.13981239 | CJ23: =CH23/CI23 -> 11.265096 | CK23: =18/24*CLmaxL -> 2.025 | CL23: =CD_0+dCD0_fMA+dCD0_gear+K_ind*CK23^2 -> 0.22962764 | CM23: =CK23/CL23 -> 8.8186248 | CR23: =18/28*h_abs -> 7370.625 | CS23: =IF(CR23<=11000,288.15-0.0065*CR23,216.65) -> 240.24094 | CT23: =IF(CR23<=11000,rho_SL*(CS23/288.15)^4.25588,0.36392*EXP(-(CR23-11000)/6341.62)) -> 0.56499212 | CU23: =SQRT(1.4*287.053*CS23) -> 310.71954 | CV23: =TW_p*(CT23/rho_SL)^lapse_n -> 0.10660245 | CW23: =MIN(M_MO*CU23,SQRT(CV23*WS_p*(1+SQRT(1+3/(LD_max^2*CV23^2)))/(3*CT23*CD_0))) -> 201.59072 | CX23: =MAX(0,CW23*(CV23-0.5*CT23*CW23^2*CD_0/WS_p-K_ind*WS_p/(0.5*CT23*CW23^2))) -> 9.4530702 | CY23: =IF(CR23>=h_cr,0,(MIN(CR24,h_cr)-CR23)/MAX(0.05,(CX23+CX24)/2)) -> 45.906936 | CZ23: =MAX(0,CV23^2-4*CD_0*K_ind) -> 0.0083485145 | DA23: =MAX(SQRT(2*WS_p/(CT23*CLmax_c)),SQRT(2*WS_p*(CV23-SQRT(CZ23))/(2*CD_0)/CT23)) -> 108.30006 | DB23: =MAX(DA23,MIN(M_MO*CU23,SQRT(2*WS_p*(CV23+SQRT(CZ23))/(2*CD_0)/CT23))) -> 254.79003 | DC23: =DA23/CU23 -> 0.34854602 | DD23: =DB23/CU23 -> 0.82 | DJ23: =6/10*V_S1*SQRT(-n_neg/0.8) -> 50.858789 | DK23: =-0.8*(6/10*SQRT(-n_neg/0.8))^2 -> -0.36 | DX23: =d_fus/2*0 -> 0 | DY23: =d_fus/2*-1 -> -1.990925 | EB23: =$AH$6+D_nac/2*-0.5 -> -6.5772426 | EC23: =$AJ$6+D_nac/2*0.86603 -> -1.0407616 | ED23: =0+-1*2.2*nose_scale*w_tyre/2 -> -0.30112281 | EE23: =-h_cg+D_nose -> -2.9141833 | EG23: =d_fus/2*-1 -> -1.990925 | EH23: =d_fus/2*0 -> 0 | EI23: =w_cabin/2*-1 -> -1.865 | EJ23: =w_cabin/2*0 -> 0 | EM23: =$AX$9+0.95*seat_w -> 1.2835 | EN23: =z_floor+1.1 -> 0.5 | GA23: ATR 72-600 (turboprop) | GB23: 70 | GC23: 23000 | GD23: 13500 | GE23: 61 | GF23: 27.05 | GG23: 27.17 | GH23: 0 | GI23: 2 | GJ23: 1530 | GK23: =ABS(LN(GC23/MTOW))+ABS(LN(MAX(1,GB23)/MAX(1,PaxTyp))) -> 1.8901979 | GZ23: CG % MAC case 5 | HA23: =(HA18-HA6)/MAC -> 0.82302196 | HB23: =(HB18-HB6)/MAC -> -0.21132392 | HF23: =HR22 -> 72991.447 | HG23: =HF23*grav/WS_des -> 135.54259 | HH23: =SQRT(AR_*HG23) -> 35.883905 | HI23: =2*HG23/(HH23*(1+taper)) -> 6.043605 | HJ23: =2/3*HI23*(1+taper+taper^2)/(1+taper) -> 4.2305235 | HK23: =49*MAX(0.5*HG23,HG23-d_fus*HI23*(1-(1-taper)*d_fus/(2*HH23))) -> 5511.4827 | HL23: =27*(c_HT*HJ23*HG23/L_tail+c_VT*HH23*HG23/L_tail) -> 1703.1959 | HM23: =24*S_wet_fus -> 9147.0379 | HN23: =0.043*HF23 -> 3138.6322 | HO23: =1.3*N_eng*14.7*(TW_des*HF23*grav/N_eng/1000)^1.1*EXP(-0.045*BPR) -> 4710.4285 | HP23: =0.17*HF23 -> 12408.546 | HQ23: =SUM(HK23:HP23) -> 36619.323 | HR23: =IF(fuel_frac<0.95,MIN(100*MTOW_frac,(W_crew+W_pl+HQ23)/(1-fuel_frac)),HF23) -> 72991.481 | HW23: =MAX(0,MIN(18,n_rows_b-1)) -> 0 | HX23: =x_seat0+HW23*(bus_pitch*(n_rows_b>0)) -> 6.5 | HY23: =$HX$7 -> 6.5 | HZ23: =$HV$5+seat_w_b*($HW$7*n_SA_b+$HU$5<pax_b) -> -1.84 | IA23: =HY23-L_fus/2 -> -11.31048
A24: =29/50 -> 0.58 | B24: =A24*WS_max -> 3228.4477 | C24: =B24/grav -> 329.21005 | D24: =TO_slope*B24 -> 0.16674275 | E24: =TW_2 -> 0.21941554 | F24: =TW_MA -> 0.21104328 | G24: =beta_cr/alpha_cr*(q_cr*CD_0/(beta_cr*B24)+K_ind*beta_cr*B24/q_cr+ROC_cr/V_cr) -> 0.33868453 | H24: =MAX(D24:G24) -> 0.33868453 | X24: =T23-L_fus/2 -> 17.81048 | Y24: =V23+-1*U23 -> 1.0750995 | Z24: =-1*U23 -> -0.238911 | AA24: =T23 -> 35.62096 | AC24: =x_vLE0+cr_VT-L_fus/2 -> 16.344268 | AD24: 0 | AE24: =z_VT0 -> 1.59274 | AL24: =AI8+1*L_nac-L_fus/2 -> -3.1011787 | AM24: =AH8+-1*D_nac/2 -> -7.1353903 | AN24: =AJ8+-1*D_nac/2 -> -3.1238022 | AP24: =x_nose-L_fus/2+-0.86603*D_nose/2 -> -14.164912 | AQ24: =-h_cg+D_nose/2+-0.5*D_nose/2 -> -3.4760223 | AY24: =MAX(0,MIN(19,n_rows-1)) -> 19 | AZ24: =x_eco0+AY24*(seat_pitch) -> 21.89 | BD24: =T23-L_fus/2 -> 17.81048 | BE24: =U23*0.86603 -> 0.20690409 | BF24: =V23+U23*0.5 -> 1.433466 | BG24: =BD24*COS(RADIANS(view_az))+BE24*SIN(RADIANS(view_az)) -> 13.776615 | BH24: =BF24*COS(RADIANS(view_el))+(BE24*COS(RADIANS(view_az))-BD24*SIN(RADIANS(view_az)))*SIN(RADIANS(view_el)) -> -3.4721388 | BM24: =$AZ$7+1*(seat_pitch)*($AY$7*n_SA+$AW$5<pax_e) -> 8.93 | BN24: =$AX$5+seat_w*($AY$7*n_SA+$AW$5<pax_e) -> -1.31 | BO24: =BM24-L_fus/2 -> -8.88048 | CA24: =$BX$7+1*lav_len -> 29.25 | CB24: =$BY$7+0*lav_w -> 0.865 | CE24: =19/24*CLmax_c -> 1.1875 | CF24: =CD_0+K_ind*CE24^2 -> 0.077061405 | CG24: =CE24/CF24 -> 15.409789 | CH24: =19/24*CLmaxTO -> 1.6625 | CI24: =CD_0+dCD0_f2+K_ind*CH24^2 -> 0.15167702 | CJ24: =CH24/CI24 -> 10.96079 | CK24: =19/24*CLmaxL -> 2.1375 | CL24: =CD_0+dCD0_fMA+dCD0_gear+K_ind*CK24^2 -> 0.24924061 | CM24: =CK24/CL24 -> 8.5760503 | CR24: =19/28*h_abs -> 7780.1042 | CS24: =IF(CR24<=11000,288.15-0.0065*CR24,216.65) -> 237.57932 | CT24: =IF(CR24<=11000,rho_SL*(CS24/288.15)^4.25588,0.36392*EXP(-(CR24-11000)/6341.62)) -> 0.53882887 | CU24: =SQRT(1.4*287.053*CS24) -> 308.99353 | CV24: =TW_p*(CT24/rho_SL)^lapse_n -> 0.10026635 | CW24: =MIN(M_MO*CU24,SQRT(CV24*WS_p*(1+SQRT(1+3/(LD_max^2*CV24^2)))/(3*CT24*CD_0))) -> 201.82475 | CX24: =MAX(0,CW24*(CV24-0.5*CT24*CW24^2*CD_0/WS_p-K_ind*WS_p/(0.5*CT24*CW24^2))) -> 8.3864637 | CY24: =IF(CR24>=h_cr,0,(MIN(CR25,h_cr)-CR24)/MAX(0.05,(CX24+CX25)/2)) -> 52.01513 | CZ24: =MAX(0,CV24^2-4*CD_0*K_ind) -> 0.0070377739 | DA24: =MAX(SQRT(2*WS_p/(CT24*CLmax_c)),SQRT(2*WS_p*(CV24-SQRT(CZ24))/(2*CD_0)/CT24)) -> 110.89819 | DB24: =MAX(DA24,MIN(M_MO*CU24,SQRT(2*WS_p*(CV24+SQRT(CZ24))/(2*CD_0)/CT24))) -> 253.37469 | DC24: =DA24/CU24 -> 0.35890135 | DD24: =DB24/CU24 -> 0.82 | DJ24: =5/10*V_S1*SQRT(-n_neg/0.8) -> 42.382324 | DK24: =-0.8*(5/10*SQRT(-n_neg/0.8))^2 -> -0.25 | DX24: =d_fus/2*0.25882 -> 0.51529121 | DY24: =d_fus/2*-0.96593 -> -1.9230942 | EB24: =$AH$6+D_nac/2*-0.86603 -> -6.9858402 | EC24: =$AJ$6+D_nac/2*0.5 -> -1.4493592 | ED24: =0+-1*2.2*nose_scale*w_tyre/2 -> -0.30112281 | EE24: =-h_cg -> -3.663302 | EG24: =d_fus/2*-0.98481 -> -1.9606828 | EH24: =d_fus/2*-0.17365 -> -0.34572413 | EI24: =w_cabin/2*-0.98481 -> -1.8366706 | EJ24: =w_cabin/2*-0.17365 -> -0.32385725 | EM24: =$AX$9+0.95*seat_w -> 1.2835 | EN24: =z_floor+0 -> -0.6 | GA24: Dash 8 Q400 (turboprop) | GB24: 78 | GC24: 29574 | GD24: 17819 | GE24: 63.1 | GF24: 28.42 | GG24: 32.83 | GH24: 0 | GI24: 2 | GJ24: 2040 | GK24: =ABS(LN(GC24/MTOW))+ABS(LN(MAX(1,GB24)/MAX(1,PaxTyp))) -> 1.5305829 | GZ24: neutral point | HA24: =(CLa_w*(0.25-1.8/CLa_w*d_fus^2*(HA7+d_fus/2*TAN(RADIANS(sweepLE)))/(S_ref*MAC))+tail_k*(0.25+L_tail/MAC))/(CLa_w+tail_k) -> 0.58978222 | HB24: =(CLa_w*(0.25-1.8/CLa_w*d_fus^2*(HB7+d_fus/2*TAN(RADIANS(sweepLE)))/(S_ref*MAC))+tail_k*(0.25+L_tail/MAC))/(CLa_w+tail_k) -> 0.53374882 | HF24: =HR23 -> 72991.481 | HG24: =HF24*grav/WS_des -> 135.54266 | HH24: =SQRT(AR_*HG24) -> 35.883913 | HI24: =2*HG24/(HH24*(1+taper)) -> 6.0436064 | HJ24: =2/3*HI24*(1+taper+taper^2)/(1+taper) -> 4.2305245 | HK24: =49*MAX(0.5*HG24,HG24-d_fus*HI24*(1-(1-taper)*d_fus/(2*HH24))) -> 5511.4856 | HL24: =27*(c_HT*HJ24*HG24/L_tail+c_VT*HH24*HG24/L_tail) -> 1703.1971 | HM24: =24*S_wet_fus -> 9147.0379 | HN24: =0.043*HF24 -> 3138.6337 | HO24: =1.3*N_eng*14.7*(TW_des*HF24*grav/N_eng/1000)^1.1*EXP(-0.045*BPR) -> 4710.431 | HP24: =0.17*HF24 -> 12408.552 | HQ24: =SUM(HK24:HP24) -> 36619.337 | HR24: =IF(fuel_frac<0.95,MIN(100*MTOW_frac,(W_crew+W_pl+HQ24)/(1-fuel_frac)),HF24) -> 72991.501 | HW24: =MAX(0,MIN(19,n_rows_b-1)) -> 0 | HX24: =x_seat0+HW24*(bus_pitch*(n_rows_b>0)) -> 6.5 | HY24: =$HX$7+1*(bus_pitch*(n_rows_b>0))*($HW$7*n_SA_b+$HU$5<pax_b) -> 6.5 | HZ24: =$HV$5+seat_w_b*($HW$7*n_SA_b+$HU$5<pax_b) -> -1.84 | IA24: =HY24-L_fus/2 -> -11.31048
A25: =30/50 -> 0.6 | B25: =A25*WS_max -> 3339.7735 | C25: =B25/grav -> 340.56212 | D25: =TO_slope*B25 -> 0.1724925 | E25: =TW_2 -> 0.21941554 | F25: =TW_MA -> 0.21104328 | G25: =beta_cr/alpha_cr*(q_cr*CD_0/(beta_cr*B25)+K_ind*beta_cr*B25/q_cr+ROC_cr/V_cr) -> 0.33195553 | H25: =MAX(D25:G25) -> 0.33195553 | X25: =T22-L_fus/2 -> 17.173384 | Y25: =V22+-1*U22 -> 0.68264084 | Z25: =-1*U22 -> -0.46317309 | AA25: =T22 -> 34.983864 | AC25: =x_vLE0-L_fus/2 -> 10.524635 | AD25: 0 | AE25: =z_VT0 -> 1.59274 | AL25: =AI8+1*L_nac-L_fus/2 -> -3.1011787 | AM25: =AH8+1*D_nac/2 -> -4.9027996 | AN25: =AJ8+1*D_nac/2 -> -0.8912115 | AP25: =x_nose-L_fus/2+-0.5*D_nose/2 -> -14.027812 | AQ25: =-h_cg+D_nose/2+-0.86603*D_nose/2 -> -3.6131223 | AY25: =MAX(0,MIN(20,n_rows-1)) -> 20 | AZ25: =x_eco0+AY25*(seat_pitch) -> 22.7 | BD25: =T22-L_fus/2 -> 17.173384 | BE25: =U22*0.86603 -> 0.40112179 | BF25: =V22+U22*0.5 -> 1.3774005 | BG25: =BD25*COS(RADIANS(view_az))+BE25*SIN(RADIANS(view_az)) -> 13.413412 | BH25: =BF25*COS(RADIANS(view_el))+(BE25*COS(RADIANS(view_az))-BD25*SIN(RADIANS(view_az)))*SIN(RADIANS(view_el)) -> -3.287005 | BM25: =$AZ$7+0.8*(seat_pitch)*($AY$7*n_SA+$AW$5<pax_e) -> 8.768 | BN25: =$AX$5+seat_w*($AY$7*n_SA+$AW$5<pax_e) -> -1.31 | BO25: =BM25-L_fus/2 -> -9.04248 | CA25: =$BX$7+1*lav_len -> 29.25 | CB25: =$BY$7+1*lav_w -> 1.865 | CE25: =20/24*CLmax_c -> 1.25 | CF25: =CD_0+K_ind*CE25^2 -> 0.083442 | CG25: =CE25/CF25 -> 14.980466 | CH25: =20/24*CLmaxTO -> 1.75 | CI25: =CD_0+dCD0_f2+K_ind*CH25^2 -> 0.16418299 | CJ25: =CH25/CI25 -> 10.658839 | CK25: =20/24*CLmaxL -> 2.25 | CL25: =CD_0+dCD0_fMA+dCD0_gear+K_ind*CK25^2 -> 0.26991374 | CM25: =CK25/CL25 -> 8.3359967 | CR25: =20/28*h_abs -> 8189.5834 | CS25: =IF(CR25<=11000,288.15-0.0065*CR25,216.65) -> 234.91771 | CT25: =IF(CR25<=11000,rho_SL*(CS25/288.15)^4.25588,0.36392*EXP(-(CR25-11000)/6341.62)) -> 0.51360273 | CU25: =SQRT(1.4*287.053*CS25) -> 307.25782 | CV25: =TW_p*(CT25/rho_SL)^lapse_n -> 0.094241768 | CW25: =MIN(M_MO*CU25,SQRT(CV25*WS_p*(1+SQRT(1+3/(LD_max^2*CV25^2)))/(3*CT25*CD_0))) -> 202.19427 | CX25: =MAX(0,CW25*(CV25-0.5*CT25*CW25^2*CD_0/WS_p-K_ind*WS_p/(0.5*CT25*CW25^2))) -> 7.3581541 | CY25: =IF(CR25>=h_cr,0,(MIN(CR26,h_cr)-CR25)/MAX(0.05,(CX25+CX26)/2)) -> 59.675094 | CZ25: =MAX(0,CV25^2-4*CD_0*K_ind) -> 0.0058659435 | DA25: =MAX(SQRT(2*WS_p/(CT25*CLmax_c)),SQRT(2*WS_p*(CV25-SQRT(CZ25))/(2*CD_0)/CT25)) -> 113.58899 | DB25: =MAX(DA25,MIN(M_MO*CU25,SQRT(2*WS_p*(CV25+SQRT(CZ25))/(2*CD_0)/CT25))) -> 251.95141 | DC25: =DA25/CU25 -> 0.36968625 | DD25: =DB25/CU25 -> 0.82 | DJ25: =4/10*V_S1*SQRT(-n_neg/0.8) -> 33.905859 | DK25: =-0.8*(4/10*SQRT(-n_neg/0.8))^2 -> -0.16 | DX25: =d_fus/2*0.5 -> 0.9954625 | DY25: =d_fus/2*-0.86603 -> -1.7242008 | EB25: =$AH$6+D_nac/2*-1 -> -7.1353903 | EC25: =$AJ$6+D_nac/2*0 -> -2.0075068 | ED25: =0+1*2.2*nose_scale*w_tyre/2 -> 0.30112281 | EE25: =-h_cg -> -3.663302 | EG25: =d_fus/2*-0.93969 -> -1.8708523 | EH25: =d_fus/2*-0.34202 -> -0.68093617 | EI25: =w_cabin/2*-0.93969 -> -1.7525218 | EJ25: =w_cabin/2*-0.34202 -> -0.6378673 | EM25: =$AX$10+0.05*seat_w -> 1.3365 | EN25: =z_floor+0 -> -0.6 | GA25: Learjet 45 (business jet) | GB25: 8 | GC25: 9752 | GD25: 6146 | GE25: 28.95 | GF25: 14.58 | GG25: 17.68 | GH25: 15.6 | GI25: 2 | GJ25: 3170 | GK25: =ABS(LN(GC25/MTOW))+ABS(LN(MAX(1,GB25)/MAX(1,PaxTyp))) -> 4.9172734 | GZ25: static margin case 1 | HA25: =HA24-HA19 -> -0.15143824 | HB25: =HB24-HB19 -> 0.66473372 | HC25: =$HA$5+(SM_target-HA25)*($HB$5-$HA$5)/IF(ABS(HB25-HA25)<0.000000001,0.000000001,HB25-HA25) -> 0.42929123 | HF25: =HR24 -> 72991.501 | HG25: =HF25*grav/WS_des -> 135.54269 | HH25: =SQRT(AR_*HG25) -> 35.883918 | HI25: =2*HG25/(HH25*(1+taper)) -> 6.0436073 | HJ25: =2/3*HI25*(1+taper+taper^2)/(1+taper) -> 4.2305251 | HK25: =49*MAX(0.5*HG25,HG25-d_fus*HI25*(1-(1-taper)*d_fus/(2*HH25))) -> 5511.4872 | HL25: =27*(c_HT*HJ25*HG25/L_tail+c_VT*HH25*HG25/L_tail) -> 1703.1978 | HM25: =24*S_wet_fus -> 9147.0379 | HN25: =0.043*HF25 -> 3138.6346 | HO25: =1.3*N_eng*14.7*(TW_des*HF25*grav/N_eng/1000)^1.1*EXP(-0.045*BPR) -> 4710.4324 | HP25: =0.17*HF25 -> 12408.555 | HQ25: =SUM(HK25:HP25) -> 36619.345 | HR25: =IF(fuel_frac<0.95,MIN(100*MTOW_frac,(W_crew+W_pl+HQ25)/(1-fuel_frac)),HF25) -> 72991.513 | HY25: =$HX$7+0.8*(bus_pitch*(n_rows_b>0))*($HW$7*n_SA_b+$HU$5<pax_b) -> 6.5 | HZ25: =$HV$5+seat_w_b*($HW$7*n_SA_b+$HU$5<pax_b) -> -1.84 | IA25: =HY25-L_fus/2 -> -11.31048
A26: =31/50 -> 0.62 | B26: =A26*WS_max -> 3451.0993 | C26: =B26/grav -> 351.91419 | D26: =TO_slope*B26 -> 0.17824225 | E26: =TW_2 -> 0.21941554 | F26: =TW_MA -> 0.21104328 | G26: =beta_cr/alpha_cr*(q_cr*CD_0/(beta_cr*B26)+K_ind*beta_cr*B26/q_cr+ROC_cr/V_cr) -> 0.32577994 | H26: =MAX(D26:G26) -> 0.32577994 | X26: =T21-L_fus/2 -> 16.21774 | Y26: =V21+-1*U21 -> 0.11845713 | Z26: =-1*U21 -> -0.78556378 | AA26: =T21 -> 34.02822 | AL26: =AI8+0*L_nac-L_fus/2 -> -7.4249768 | AM26: =AH8+1*D_nac/2 -> -4.9027996 | AN26: =AJ8+1*D_nac/2 -> -0.8912115 | AP26: =x_nose-L_fus/2+0*D_nose/2 -> -13.840532 | AQ26: =-h_cg+D_nose/2+-1*D_nose/2 -> -3.663302 | AY26: =MAX(0,MIN(21,n_rows-1)) -> 21 | AZ26: =x_eco0+AY26*(seat_pitch) -> 23.51 | BD26: =T21-L_fus/2 -> 16.21774 | BE26: =U21*0.86603 -> 0.6803218 | BF26: =V21+U21*0.5 -> 1.2968028 | BG26: =BD26*COS(RADIANS(view_az))+BE26*SIN(RADIANS(view_az)) -> 12.860812 | BH26: =BF26*COS(RADIANS(view_el))+(BE26*COS(RADIANS(view_az))-BD26*SIN(RADIANS(view_az)))*SIN(RADIANS(view_el)) -> -3.0100576 | BM26: =$AZ$7+0.8*(seat_pitch)*($AY$7*n_SA+$AW$5<pax_e) -> 8.768 | BN26: =$AX$5 -> -1.84 | BO26: =BM26-L_fus/2 -> -9.04248 | CA26: =$BX$7+0*lav_len -> 28.25 | CB26: =$BY$7+1*lav_w -> 1.865 | CE26: =21/24*CLmax_c -> 1.3125 | CF26: =CD_0+K_ind*CE26^2 -> 0.090149805 | CG26: =CE26/CF26 -> 14.5591 | CH26: =21/24*CLmaxTO -> 1.8375 | CI26: =CD_0+dCD0_f2+K_ind*CH26^2 -> 0.17733028 | CJ26: =CH26/CI26 -> 10.36202 | CK26: =21/24*CLmaxL -> 2.3625 | CL26: =CD_0+dCD0_fMA+dCD0_gear+K_ind*CK26^2 -> 0.29164702 | CM26: =CK26/CL26 -> 8.1005456 | CR26: =21/28*h_abs -> 8599.0625 | CS26: =IF(CR26<=11000,288.15-0.0065*CR26,216.65) -> 232.25609 | CT26: =IF(CR26<=11000,rho_SL*(CS26/288.15)^4.25588,0.36392*EXP(-(CR26-11000)/6341.62)) -> 0.4892902 | CU26: =SQRT(1.4*287.053*CS26) -> 305.51224 | CV26: =TW_p*(CT26/rho_SL)^lapse_n -> 0.088516653 | CW26: =MIN(M_MO*CU26,SQRT(CV26*WS_p*(1+SQRT(1+3/(LD_max^2*CV26^2)))/(3*CT26*CD_0))) -> 202.7092 | CX26: =MAX(0,CW26*(CV26-0.5*CT26*CW26^2*CD_0/WS_p-K_ind*WS_p/(0.5*CT26*CW26^2))) -> 6.3654663 | CY26: =IF(CR26>=h_cr,0,(MIN(CR27,h_cr)-CR26)/MAX(0.05,(CX26+CX27)/2)) -> 69.572677 | CZ26: =MAX(0,CV26^2-4*CD_0*K_ind) -> 0.0048196306 | DA26: =MAX(SQRT(2*WS_p/(CT26*CLmax_c)),SQRT(2*WS_p*(CV26-SQRT(CZ26))/(2*CD_0)/CT26)) -> 116.37686 | DB26: =MAX(DA26,MIN(M_MO*CU26,SQRT(2*WS_p*(CV26+SQRT(CZ26))/(2*CD_0)/CT26))) -> 250.52004 | DC26: =DA26/CU26 -> 0.38092372 | DD26: =DB26/CU26 -> 0.82 | DJ26: =3/10*V_S1*SQRT(-n_neg/0.8) -> 25.429394 | DK26: =-0.8*(3/10*SQRT(-n_neg/0.8))^2 -> -0.09 | DX26: =d_fus/2*0.70711 -> 1.407803 | DY26: =d_fus/2*-0.70711 -> -1.407803 | EB26: =$AH$6+D_nac/2*-0.86603 -> -6.9858402 | EC26: =$AJ$6+D_nac/2*-0.5 -> -2.5656545 | ED26: =0+1*2.2*nose_scale*w_tyre/2 -> 0.30112281 | EE26: =-h_cg+D_nose -> -2.9141833 | EG26: =d_fus/2*-0.86603 -> -1.7242008 | EH26: =d_fus/2*-0.5 -> -0.9954625 | EI26: =w_cabin/2*-0.86603 -> -1.6151459 | EJ26: =w_cabin/2*-0.5 -> -0.9325 | EM26: =$AX$10+0.05*seat_w -> 1.3365 | EN26: =z_floor+1.1 -> 0.5 | GA26: Gulfstream G650 (business jet) | GB26: 16 | GC26: 45178 | GD26: 24494 | GE26: 119.2 | GF26: 30.36 | GG26: 30.41 | GH26: 75.2 | GI26: 2 | GJ26: 12960 | GK26: =ABS(LN(GC26/MTOW))+ABS(LN(MAX(1,GB26)/MAX(1,PaxTyp))) -> 2.6909884 | GZ26: static margin case 2 | HA26: =HA24-HA20 -> -0.22237963 | HB26: =HB24-HB20 -> 0.7344068 | HC26: =$HA$5+(SM_target-HA26)*($HB$5-$HA$5)/IF(ABS(HB26-HA26)<0.000000001,0.000000001,HB26-HA26) -> 0.4339104 | HF26: =HR25 -> 72991.513 | HG26: =HF26*grav/WS_des -> 135.54271 | HH26: =SQRT(AR_*HG26) -> 35.883921 | HI26: =2*HG26/(HH26*(1+taper)) -> 6.0436077 | HJ26: =2/3*HI26*(1+taper+taper^2)/(1+taper) -> 4.2305254 | HK26: =49*MAX(0.5*HG26,HG26-d_fus*HI26*(1-(1-taper)*d_fus/(2*HH26))) -> 5511.4882 | HL26: =27*(c_HT*HJ26*HG26/L_tail+c_VT*HH26*HG26/L_tail) -> 1703.1982 | HM26: =24*S_wet_fus -> 9147.0379 | HN26: =0.043*HF26 -> 3138.635 | HO26: =1.3*N_eng*14.7*(TW_des*HF26*grav/N_eng/1000)^1.1*EXP(-0.045*BPR) -> 4710.4332 | HP26: =0.17*HF26 -> 12408.557 | HQ26: =SUM(HK26:HP26) -> 36619.35 | HR26: =IF(fuel_frac<0.95,MIN(100*MTOW_frac,(W_crew+W_pl+HQ26)/(1-fuel_frac)),HF26) -> 72991.519 | HY26: =$HX$7+0.8*(bus_pitch*(n_rows_b>0))*($HW$7*n_SA_b+$HU$5<pax_b) -> 6.5 | HZ26: =$HV$5 -> -1.84 | IA26: =HY26-L_fus/2 -> -11.31048
A27: =32/50 -> 0.64 | B27: =A27*WS_max -> 3562.4251 | C27: =B27/grav -> 363.26626 | D27: =TO_slope*B27 -> 0.183992 | E27: =TW_2 -> 0.21941554 | F27: =TW_MA -> 0.21104328 | G27: =beta_cr/alpha_cr*(q_cr*CD_0/(beta_cr*B27)+K_ind*beta_cr*B27/q_cr+ROC_cr/V_cr) -> 0.32010586 | H27: =MAX(D27:G27) -> 0.32010586 | X27: =T20-L_fus/2 -> 15.262096 | Y27: =V20+-1*U20 -> -0.41268791 | Z27: =-1*U20 -> -1.0890752 | AA27: =T20 -> 33.072576 | AL27: =AI8+0*L_nac-L_fus/2 -> -7.4249768 | AM27: =AH8+-1*D_nac/2 -> -7.1353903 | AN27: =AJ8+-1*D_nac/2 -> -3.1238022 | AP27: =x_nose-L_fus/2+0.5*D_nose/2 -> -13.653253 | AQ27: =-h_cg+D_nose/2+-0.86603*D_nose/2 -> -3.6131223 | AY27: =MAX(0,MIN(22,n_rows-1)) -> 22 | AZ27: =x_eco0+AY27*(seat_pitch) -> 24.32 | BD27: =T20-L_fus/2 -> 15.262096 | BE27: =U20*0.86603 -> 0.94317182 | BF27: =V20+U20*0.5 -> 1.2209249 | BG27: =BD27*COS(RADIANS(view_az))+BE27*SIN(RADIANS(view_az)) -> 12.297703 | BH27: =BF27*COS(RADIANS(view_el))+(BE27*COS(RADIANS(view_az))-BD27*SIN(RADIANS(view_az)))*SIN(RADIANS(view_el)) -> -2.7341258 | BM27: =$AZ$7+0.2*(seat_pitch)*($AY$7*n_SA+$AW$5<pax_e) -> 8.282 | BN27: =$AX$5 -> -1.84 | BO27: =BM27-L_fus/2 -> -9.52848 | CA27: =$BX$7+0*lav_len -> 28.25 | CB27: =$BY$7+0*lav_w -> 0.865 | CE27: =22/24*CLmax_c -> 1.375 | CF27: =CD_0+K_ind*CE27^2 -> 0.09718482 | CG27: =CE27/CF27 -> 14.1483 | CH27: =22/24*CLmaxTO -> 1.925 | CI27: =CD_0+dCD0_f2+K_ind*CH27^2 -> 0.19111891 | CJ27: =CH27/CI27 -> 10.072263 | CK27: =22/24*CLmaxL -> 2.475 | CL27: =CD_0+dCD0_fMA+dCD0_gear+K_ind*CK27^2 -> 0.31444047 | CM27: =CK27/CL27 -> 7.8711242 | CR27: =22/28*h_abs -> 9008.5417 | CS27: =IF(CR27<=11000,288.15-0.0065*CR27,216.65) -> 229.59448 | CT27: =IF(CR27<=11000,rho_SL*(CS27/288.15)^4.25588,0.36392*EXP(-(CR27-11000)/6341.62)) -> 0.46586808 | CU27: =SQRT(1.4*287.053*CS27) -> 303.75664 | CV27: =TW_p*(CT27/rho_SL)^lapse_n -> 0.083079299 | CW27: =MIN(M_MO*CU27,SQRT(CV27*WS_p*(1+SQRT(1+3/(LD_max^2*CV27^2)))/(3*CT27*CD_0))) -> 203.37964 | CX27: =MAX(0,CW27*(CV27-0.5*CT27*CW27^2*CD_0/WS_p-K_ind*WS_p/(0.5*CT27*CW27^2))) -> 5.4057975 | CY27: =IF(CR27>=h_cr,0,(MIN(CR28,h_cr)-CR27)/MAX(0.05,(CX27+CX28)/2)) -> 82.870268 | CZ27: =MAX(0,CV27^2-4*CD_0*K_ind) -> 0.0038866026 | DA27: =MAX(SQRT(2*WS_p/(CT27*CLmax_c)),SQRT(2*WS_p*(CV27-SQRT(CZ27))/(2*CD_0)/CT27)) -> 119.26649 | DB27: =MAX(DA27,MIN(M_MO*CU27,SQRT(2*WS_p*(CV27+SQRT(CZ27))/(2*CD_0)/CT27))) -> 249.08045 | DC27: =DA27/CU27 -> 0.39263828 | DD27: =DB27/CU27 -> 0.82 | DJ27: =2/10*V_S1*SQRT(-n_neg/0.8) -> 16.95293 | DK27: =-0.8*(2/10*SQRT(-n_neg/0.8))^2 -> -0.04 | DX27: =d_fus/2*0.86603 -> 1.7242008 | DY27: =d_fus/2*-0.5 -> -0.9954625 | EB27: =$AH$6+D_nac/2*-0.5 -> -6.5772426 | EC27: =$AJ$6+D_nac/2*-0.86603 -> -2.9742521 | ED27: =0+0*2.2*nose_scale*w_tyre/2 -> 0 | EE27: =-h_cg+D_nose -> -2.9141833 | EG27: =d_fus/2*-0.76604 -> -1.5251282 | EH27: =d_fus/2*-0.64279 -> -1.2797467 | EI27: =w_cabin/2*-0.76604 -> -1.4286646 | EJ27: =w_cabin/2*-0.64279 -> -1.1988033 | EM27: =$AX$10+0.95*seat_w -> 1.8135 | EN27: =z_floor+1.1 -> 0.5 | GA27: Boeing 777F (freighter) | GB27: 0 | GC27: 347800 | GD27: 144400 | GE27: 436.8 | GF27: 64.8 | GG27: 63.7 | GH27: 512 | GI27: 2 | GJ27: 9200 | GK27: =ABS(LN(GC27/MTOW))+ABS(LN(MAX(1,GB27)/MAX(1,PaxTyp))) -> 6.5987109 | GZ27: static margin case 3 | HA27: =HA24-HA21 -> -0.1149233 | HB27: =HB24-HB21 -> 0.54135136 | HC27: =$HA$5+(SM_target-HA27)*($HB$5-$HA$5)/IF(ABS(HB27-HA27)<0.000000001,0.000000001,HB27-HA27) -> 0.43239838 | HF27: =HR26 -> 72991.519 | HG27: =HF27*grav/WS_des -> 135.54273 | HH27: =SQRT(AR_*HG27) -> 35.883922 | HI27: =2*HG27/(HH27*(1+taper)) -> 6.043608 | HJ27: =2/3*HI27*(1+taper+taper^2)/(1+taper) -> 4.2305256 | HK27: =49*MAX(0.5*HG27,HG27-d_fus*HI27*(1-(1-taper)*d_fus/(2*HH27))) -> 5511.4887 | HL27: =27*(c_HT*HJ27*HG27/L_tail+c_VT*HH27*HG27/L_tail) -> 1703.1984 | HM27: =24*S_wet_fus -> 9147.0379 | HN27: =0.043*HF27 -> 3138.6353 | HO27: =1.3*N_eng*14.7*(TW_des*HF27*grav/N_eng/1000)^1.1*EXP(-0.045*BPR) -> 4710.4337 | HP27: =0.17*HF27 -> 12408.558 | HQ27: =SUM(HK27:HP27) -> 36619.352 | HR27: =IF(fuel_frac<0.95,MIN(100*MTOW_frac,(W_crew+W_pl+HQ27)/(1-fuel_frac)),HF27) -> 72991.523 | HY27: =$HX$7+0.2*(bus_pitch*(n_rows_b>0))*($HW$7*n_SA_b+$HU$5<pax_b) -> 6.5 | HZ27: =$HV$5 -> -1.84 | IA27: =HY27-L_fus/2 -> -11.31048
A28: =33/50 -> 0.66 | B28: =A28*WS_max -> 3673.7508 | C28: =B28/grav -> 374.61833 | D28: =TO_slope*B28 -> 0.18974175 | E28: =TW_2 -> 0.21941554 | F28: =TW_MA -> 0.21104328 | G28: =beta_cr/alpha_cr*(q_cr*CD_0/(beta_cr*B28)+K_ind*beta_cr*B28/q_cr+ROC_cr/V_cr) -> 0.3148877 | H28: =MAX(D28:G28) -> 0.3148877 | X28: =T19-L_fus/2 -> 14.306452 | Y28: =V19+-1*U19 -> -0.90511987 | Z28: =-1*U19 -> -1.3704649 | AA28: =T19 -> 32.116932 | AP28: =x_nose-L_fus/2+0.86603*D_nose/2 -> -13.516153 | AQ28: =-h_cg+D_nose/2+-0.5*D_nose/2 -> -3.4760223 | AY28: =MAX(0,MIN(23,n_rows-1)) -> 23 | AZ28: =x_eco0+AY28*(seat_pitch) -> 25.13 | BD28: =T19-L_fus/2 -> 14.306452 | BE28: =U19*0.86603 -> 1.1868637 | BF28: =V19+U19*0.5 -> 1.1505775 | BG28: =BD28*COS(RADIANS(view_az))+BE28*SIN(RADIANS(view_az)) -> 11.722279 | BH28: =BF28*COS(RADIANS(view_el))+(BE28*COS(RADIANS(view_az))-BD28*SIN(RADIANS(view_az)))*SIN(RADIANS(view_el)) -> -2.459384 | BM28: =$AZ$7+(seat_pitch) -> 8.93 | BN28: =$AX$5 -> -1.84 | BO28: =BM28-L_fus/2 -> -8.88048 | CA28: =$BX$7+1*lav_len -> 29.25 | CB28: =$BY$7+1*lav_w -> 1.865 | CE28: =23/24*CLmax_c -> 1.4375 | CF28: =CD_0+K_ind*CE28^2 -> 0.10454704 | CG28: =CE28/CF28 -> 13.749791 | CH28: =23/24*CLmaxTO -> 2.0125 | CI28: =CD_0+dCD0_f2+K_ind*CH28^2 -> 0.20554887 | CJ28: =CH28/CI28 -> 9.7908588 | CK28: =23/24*CLmaxL -> 2.5875 | CL28: =CD_0+dCD0_fMA+dCD0_gear+K_ind*CK28^2 -> 0.33829408 | CM28: =CK28/CL28 -> 7.6486706 | CR28: =23/28*h_abs -> 9418.0209 | CS28: =IF(CR28<=11000,288.15-0.0065*CR28,216.65) -> 226.93286 | CT28: =IF(CR28<=11000,rho_SL*(CS28/288.15)^4.25588,0.36392*EXP(-(CR28-11000)/6341.62)) -> 0.44331353 | CU28: =SQRT(1.4*287.053*CS28) -> 301.99083 | CV28: =TW_p*(CT28/rho_SL)^lapse_n -> 0.077918327 | CW28: =MIN(M_MO*CU28,SQRT(CV28*WS_p*(1+SQRT(1+3/(LD_max^2*CV28^2)))/(3*CT28*CD_0))) -> 204.21585 | CX28: =MAX(0,CW28*(CV28-0.5*CT28*CW28^2*CD_0/WS_p-K_ind*WS_p/(0.5*CT28*CW28^2))) -> 4.476617 | CY28: =IF(CR28>=h_cr,0,(MIN(CR29,h_cr)-CR28)/MAX(0.05,(CX28+CX29)/2)) -> 101.70766 | CZ28: =MAX(0,CV28^2-4*CD_0*K_ind) -> 0.0030556984 | DA28: =MAX(SQRT(2*WS_p/(CT28*CLmax_c)),SQRT(2*WS_p*(CV28-SQRT(CZ28))/(2*CD_0)/CT28)) -> 122.26282 | DB28: =MAX(DA28,MIN(M_MO*CU28,SQRT(2*WS_p*(CV28+SQRT(CZ28))/(2*CD_0)/CT28))) -> 247.63248 | DC28: =DA28/CU28 -> 0.40485606 | DD28: =DB28/CU28 -> 0.82 | DJ28: =1/10*V_S1*SQRT(-n_neg/0.8) -> 8.4764648 | DK28: =-0.8*(1/10*SQRT(-n_neg/0.8))^2 -> -0.01 | DX28: =d_fus/2*0.96593 -> 1.9230942 | DY28: =d_fus/2*-0.25882 -> -0.51529121 | EB28: =$AH$6+D_nac/2*0 -> -6.0190949 | EC28: =$AJ$6+D_nac/2*-1 -> -3.1238022 | EG28: =d_fus/2*-0.64279 -> -1.2797467 | EH28: =d_fus/2*-0.76604 -> -1.5251282 | EI28: =w_cabin/2*-0.64279 -> -1.1988033 | EJ28: =w_cabin/2*-0.76604 -> -1.4286646 | EM28: =$AX$10+0.95*seat_w -> 1.8135 | EN28: =z_floor+0 -> -0.6 | GA28: Boeing 747-8F (freighter) | GB28: 0 | GC28: 447700 | GD28: 197130 | GE28: 554 | GF28: 68.4 | GG28: 76.3 | GH28: 296 | GI28: 4 | GJ28: 8130 | GK28: =ABS(LN(GC28/MTOW))+ABS(LN(MAX(1,GB28)/MAX(1,PaxTyp))) -> 6.8512066 | GZ28: static margin case 4 | HA28: =HA24-HA22 -> -0.043357427 | HB28: =HB24-HB22 -> 0.44911247 | HC28: =$HA$5+(SM_target-HA28)*($HB$5-$HA$5)/IF(ABS(HB28-HA28)<0.000000001,0.000000001,HB28-HA28) -> 0.42657582 | HF28: =HR27 -> 72991.523 | HG28: =HF28*grav/WS_des -> 135.54273 | HH28: =SQRT(AR_*HG28) -> 35.883923 | HI28: =2*HG28/(HH28*(1+taper)) -> 6.0436082 | HJ28: =2/3*HI28*(1+taper+taper^2)/(1+taper) -> 4.2305257 | HK28: =49*MAX(0.5*HG28,HG28-d_fus*HI28*(1-(1-taper)*d_fus/(2*HH28))) -> 5511.489 | HL28: =27*(c_HT*HJ28*HG28/L_tail+c_VT*HH28*HG28/L_tail) -> 1703.1986 | HM28: =24*S_wet_fus -> 9147.0379 | HN28: =0.043*HF28 -> 3138.6355 | HO28: =1.3*N_eng*14.7*(TW_des*HF28*grav/N_eng/1000)^1.1*EXP(-0.045*BPR) -> 4710.4339 | HP28: =0.17*HF28 -> 12408.559 | HQ28: =SUM(HK28:HP28) -> 36619.354 | HR28: =IF(fuel_frac<0.95,MIN(100*MTOW_frac,(W_crew+W_pl+HQ28)/(1-fuel_frac)),HF28) -> 72991.525 | HY28: =$HX$7+(bus_pitch*(n_rows_b>0)) -> 6.5 | HZ28: =$HV$5 -> -1.84 | IA28: =HY28-L_fus/2 -> -11.31048
A29: =34/50 -> 0.68 | B29: =A29*WS_max -> 3785.0766 | C29: =B29/grav -> 385.9704 | D29: =TO_slope*B29 -> 0.1954915 | E29: =TW_2 -> 0.21941554 | F29: =TW_MA -> 0.21104328 | G29: =beta_cr/alpha_cr*(q_cr*CD_0/(beta_cr*B29)+K_ind*beta_cr*B29/q_cr+ROC_cr/V_cr) -> 0.31008525 | H29: =MAX(D29:G29) -> 0.31008525 | X29: =T18-L_fus/2 -> 13.350808 | Y29: =V18+-1*U18 -> -1.3499616 | Z29: =-1*U18 -> -1.6246602 | AA29: =T18 -> 31.161288 | AP29: =x_nose-L_fus/2+1*D_nose/2 -> -13.465973 | AQ29: =-h_cg+D_nose/2+0*D_nose/2 -> -3.2887426 | AY29: =MAX(0,MIN(24,n_rows-1)) -> 24 | AZ29: =x_eco0+AY29*(seat_pitch) -> 25.94 | BD29: =T18-L_fus/2 -> 13.350808 | BE29: =U18*0.86603 -> 1.4070045 | BF29: =V18+U18*0.5 -> 1.0870287 | BG29: =BD29*COS(RADIANS(view_az))+BE29*SIN(RADIANS(view_az)) -> 11.131717 | BH29: =BF29*COS(RADIANS(view_el))+(BE29*COS(RADIANS(view_az))-BD29*SIN(RADIANS(view_az)))*SIN(RADIANS(view_el)) -> -2.1861051 | BM29: =$AZ$8+0.2*(seat_pitch)*($AY$8*n_SA+$AW$5<pax_e) -> 9.092 | BN29: =$AX$5 -> -1.84 | BO29: =BM29-L_fus/2 -> -8.71848 | CA29: =$BX$7+1*lav_len -> 29.25 | CB29: =$BY$7+0*lav_w -> 0.865 | CE29: =24/24*CLmax_c -> 1.5 | CF29: =CD_0+K_ind*CE29^2 -> 0.11223648 | CG29: =CE29/CF29 -> 13.364639 | CH29: =24/24*CLmaxTO -> 2.1 | CI29: =CD_0+dCD0_f2+K_ind*CH29^2 -> 0.22062017 | CJ29: =CH29/CI29 -> 9.5186221 | CK29: =24/24*CLmaxL -> 2.7 | CL29: =CD_0+dCD0_fMA+dCD0_gear+K_ind*CK29^2 -> 0.36320785 | CM29: =CK29/CL29 -> 7.43376 | CR29: =24/28*h_abs -> 9827.5001 | CS29: =IF(CR29<=11000,288.15-0.0065*CR29,216.65) -> 224.27125 | CT29: =IF(CR29<=11000,rho_SL*(CS29/288.15)^4.25588,0.36392*EXP(-(CR29-11000)/6341.62)) -> 0.42160402 | CU29: =SQRT(1.4*287.053*CS29) -> 300.21464 | CV29: =TW_p*(CT29/rho_SL)^lapse_n -> 0.073022686 | CW29: =MIN(M_MO*CU29,SQRT(CV29*WS_p*(1+SQRT(1+3/(LD_max^2*CV29^2)))/(3*CT29*CD_0))) -> 205.2282 | CX29: =MAX(0,CW29*(CV29-0.5*CT29*CW29^2*CD_0/WS_p-K_ind*WS_p/(0.5*CT29*CW29^2))) -> 3.5754641 | CY29: =IF(CR29>=h_cr,0,(MIN(CR30,h_cr)-CR29)/MAX(0.05,(CX29+CX30)/2)) -> 130.50272 | CZ29: =MAX(0,CV29^2-4*CD_0*K_ind) -> 0.0023167453 | DA29: =MAX(SQRT(2*WS_p/(CT29*CLmax_c)),SQRT(2*WS_p*(CV29-SQRT(CZ29))/(2*CD_0)/CT29)) -> 127.67483 | DB29: =MAX(DA29,MIN(M_MO*CU29,SQRT(2*WS_p*(CV29+SQRT(CZ29))/(2*CD_0)/CT29))) -> 246.176 | DC29: =DA29/CU29 -> 0.42527848 | DD29: =DB29/CU29 -> 0.82 | DJ29: =0/10*V_S1*SQRT(-n_neg/0.8) -> 0 | DK29: =-0.8*(0/10*SQRT(-n_neg/0.8))^2 -> 0 | DX29: =d_fus/2*1 -> 1.990925 | DY29: =d_fus/2*0 -> 0 | EB29: =$AH$6+D_nac/2*0.5 -> -5.4609472 | EC29: =$AJ$6+D_nac/2*-0.86603 -> -2.9742521 | ED29: =-1*0.48*B_box -> -18.807867 | EE29: =-h_cg -> -3.663302 | EG29: =d_fus/2*-0.5 -> -0.9954625 | EH29: =d_fus/2*-0.86603 -> -1.7242008 | EI29: =w_cabin/2*-0.5 -> -0.9325 | EJ29: =w_cabin/2*-0.86603 -> -1.6151459 | EM29: =$AX$11+0.05*seat_w -> 1.3365 | EN29: =z_floor+0 -> -0.6 | GZ29: static margin case 5 | HA29: =HA24-HA23 -> -0.23323974 | HB29: =HB24-HB23 -> 0.74507274 | HC29: =$HA$5+(SM_target-HA29)*($HB$5-$HA$5)/IF(ABS(HB29-HA29)<0.000000001,0.000000001,HB29-HA29) -> 0.43450034 | HF29: =HR28 -> 72991.525 | HG29: =HF29*grav/WS_des -> 135.54274 | HH29: =SQRT(AR_*HG29) -> 35.883924 | HI29: =2*HG29/(HH29*(1+taper)) -> 6.0436082 | HJ29: =2/3*HI29*(1+taper+taper^2)/(1+taper) -> 4.2305258 | HK29: =49*MAX(0.5*HG29,HG29-d_fus*HI29*(1-(1-taper)*d_fus/(2*HH29))) -> 5511.4892 | HL29: =27*(c_HT*HJ29*HG29/L_tail+c_VT*HH29*HG29/L_tail) -> 1703.1986 | HM29: =24*S_wet_fus -> 9147.0379 | HN29: =0.043*HF29 -> 3138.6356 | HO29: =1.3*N_eng*14.7*(TW_des*HF29*grav/N_eng/1000)^1.1*EXP(-0.045*BPR) -> 4710.4341 | HP29: =0.17*HF29 -> 12408.559 | HQ29: =SUM(HK29:HP29) -> 36619.355 | HR29: =IF(fuel_frac<0.95,MIN(100*MTOW_frac,(W_crew+W_pl+HQ29)/(1-fuel_frac)),HF29) -> 72991.526 | HY29: =$HX$8+0.2*(bus_pitch*(n_rows_b>0))*($HW$8*n_SA_b+$HU$5<pax_b) -> 6.5 | HZ29: =$HV$5 -> -1.84 | IA29: =HY29-L_fus/2 -> -11.31048
A30: =35/50 -> 0.7 | B30: =A30*WS_max -> 3896.4024 | C30: =B30/grav -> 397.32247 | D30: =TO_slope*B30 -> 0.20124125 | E30: =TW_2 -> 0.21941554 | F30: =TW_MA -> 0.21104328 | G30: =beta_cr/alpha_cr*(q_cr*CD_0/(beta_cr*B30)+K_ind*beta_cr*B30/q_cr+ROC_cr/V_cr) -> 0.30566285 | H30: =MAX(D30:G30) -> 0.30566285 | X30: =T17-L_fus/2 -> 12.395164 | Y30: =V17+-1*U17 -> -1.730613 | Z30: =-1*U17 -> -1.8421753 | AA30: =T17 -> 30.205644 | AP30: =x_nose-L_fus/2+0.86603*D_nose/2 -> -13.516153 | AQ30: =-h_cg+D_nose/2+0.5*D_nose/2 -> -3.1014629 | AY30: =MAX(0,MIN(25,n_rows-1)) -> 24 | AZ30: =x_eco0+AY30*(seat_pitch) -> 25.94 | BD30: =T17-L_fus/2 -> 12.395164 | BE30: =U17*0.86603 -> 1.595379 | BF30: =V17+U17*0.5 -> 1.0326499 | BG30: =BD30*COS(RADIANS(view_az))+BE30*SIN(RADIANS(view_az)) -> 10.520736 | BH30: =BF30*COS(RADIANS(view_el))+(BE30*COS(RADIANS(view_az))-BD30*SIN(RADIANS(view_az)))*SIN(RADIANS(view_el)) -> -1.9147995 | BM30: =$AZ$8+0.2*(seat_pitch)*($AY$8*n_SA+$AW$5<pax_e) -> 9.092 | BN30: =$AX$5+seat_w*($AY$8*n_SA+$AW$5<pax_e) -> -1.31 | BO30: =BM30-L_fus/2 -> -8.71848 | CA30: =$BX$7+0*lav_len -> 28.25 | CB30: =$BY$7+1*lav_w -> 1.865 | CR30: =25/28*h_abs -> 10236.979 | CS30: =IF(CR30<=11000,288.15-0.0065*CR30,216.65) -> 221.60964 | CT30: =IF(CR30<=11000,rho_SL*(CS30/288.15)^4.25588,0.36392*EXP(-(CR30-11000)/6341.62)) -> 0.40071736 | CU30: =SQRT(1.4*287.053*CS30) -> 298.42787 | CV30: =TW_p*(CT30/rho_SL)^lapse_n -> 0.068381642 | CW30: =MIN(M_MO*CU30,SQRT(CV30*WS_p*(1+SQRT(1+3/(LD_max^2*CV30^2)))/(3*CT30*CD_0))) -> 206.4271 | CX30: =MAX(0,CW30*(CV30-0.5*CT30*CW30^2*CD_0/WS_p-K_ind*WS_p/(0.5*CT30*CW30^2))) -> 2.6999478 | CY30: =IF(CR30>=h_cr,0,(MIN(CR31,h_cr)-CR30)/MAX(0.05,(CX30+CX31)/2)) -> 180.08218 | CZ30: =MAX(0,CV30^2-4*CD_0*K_ind) -> 0.0016604816 | DA30: =MAX(SQRT(2*WS_p/(CT30*CLmax_c)),SQRT(2*WS_p*(CV30-SQRT(CZ30))/(2*CD_0)/CT30)) -> 137.98642 | DB30: =MAX(DA30,MIN(M_MO*CU30,SQRT(2*WS_p*(CV30+SQRT(CZ30))/(2*CD_0)/CT30))) -> 244.71086 | DC30: =DA30/CU30 -> 0.46237779 | DD30: =DB30/CU30 -> 0.82 | EB30: =$AH$6+D_nac/2*0.86603 -> -5.0523497 | EC30: =$AJ$6+D_nac/2*-0.5 -> -2.5656545 | ED30: =1*0.48*B_box -> 18.807867 | EE30: =-h_cg -> -3.663302 | EG30: =d_fus/2*-0.34202 -> -0.68093617 | EH30: =d_fus/2*-0.93969 -> -1.8708523 | EI30: =w_cabin/2*-0.34202 -> -0.6378673 | EJ30: =w_cabin/2*-0.93969 -> -1.7525218 | EM30: =$AX$11+0.05*seat_w -> 1.3365 | EN30: =z_floor+1.1 -> 0.5 | HF30: =HR29 -> 72991.526 | HG30: =HF30*grav/WS_des -> 135.54274 | HH30: =SQRT(AR_*HG30) -> 35.883924 | HI30: =2*HG30/(HH30*(1+taper)) -> 6.0436083 | HJ30: =2/3*HI30*(1+taper+taper^2)/(1+taper) -> 4.2305258 | HK30: =49*MAX(0.5*HG30,HG30-d_fus*HI30*(1-(1-taper)*d_fus/(2*HH30))) -> 5511.4893 | HL30: =27*(c_HT*HJ30*HG30/L_tail+c_VT*HH30*HG30/L_tail) -> 1703.1987 | HM30: =24*S_wet_fus -> 9147.0379 | HN30: =0.043*HF30 -> 3138.6356 | HO30: =1.3*N_eng*14.7*(TW_des*HF30*grav/N_eng/1000)^1.1*EXP(-0.045*BPR) -> 4710.4342 | HP30: =0.17*HF30 -> 12408.559 | HQ30: =SUM(HK30:HP30) -> 36619.355 | HR30: =IF(fuel_frac<0.95,MIN(100*MTOW_frac,(W_crew+W_pl+HQ30)/(1-fuel_frac)),HF30) -> 72991.527 | HY30: =$HX$8+0.2*(bus_pitch*(n_rows_b>0))*($HW$8*n_SA_b+$HU$5<pax_b) -> 6.5 | HZ30: =$HV$5+seat_w_b*($HW$8*n_SA_b+$HU$5<pax_b) -> -1.84 | IA30: =HY30-L_fus/2 -> -11.31048
A31: =36/50 -> 0.72 | B31: =A31*WS_max -> 4007.7282 | C31: =B31/grav -> 408.67454 | D31: =TO_slope*B31 -> 0.206991 | E31: =TW_2 -> 0.21941554 | F31: =TW_MA -> 0.21104328 | G31: =beta_cr/alpha_cr*(q_cr*CD_0/(beta_cr*B31)+K_ind*beta_cr*B31/q_cr+ROC_cr/V_cr) -> 0.30158885 | H31: =MAX(D31:G31) -> 0.30158885 | X31: =T16-L_fus/2 -> 11.43952 | Y31: =V16+-1*U16 -> -1.990925 | Z31: =-1*U16 -> -1.990925 | AA31: =T16 -> 29.25 | AP31: =x_nose-L_fus/2+0.5*D_nose/2 -> -13.653253 | AQ31: =-h_cg+D_nose/2+0.86603*D_nose/2 -> -2.964363 | AY31: =MAX(0,MIN(26,n_rows-1)) -> 24 | AZ31: =x_eco0+AY31*(seat_pitch) -> 25.94 | BD31: =T16-L_fus/2 -> 11.43952 | BE31: =U16*0.86603 -> 1.7242008 | BF31: =V16+U16*0.5 -> 0.9954625 | BG31: =BD31*COS(RADIANS(view_az))+BE31*SIN(RADIANS(view_az)) -> 9.8714756 | BH31: =BF31*COS(RADIANS(view_el))+(BE31*COS(RADIANS(view_az))-BD31*SIN(RADIANS(view_az)))*SIN(RADIANS(view_el)) -> -1.6471932 | BM31: =$AZ$8 -> 8.93 | BN31: =$AX$5+seat_w*($AY$8*n_SA+$AW$5<pax_e) -> -1.31 | BO31: =BM31-L_fus/2 -> -8.88048 | CR31: =26/28*h_abs -> 10646.458 | CS31: =IF(CR31<=11000,288.15-0.0065*CR31,216.65) -> 218.94802 | CT31: =IF(CR31<=11000,rho_SL*(CS31/288.15)^4.25588,0.36392*EXP(-(CR31-11000)/6341.62)) -> 0.38063168 | CU31: =SQRT(1.4*287.053*CS31) -> 296.63034 | CV31: =TW_p*(CT31/rho_SL)^lapse_n -> 0.063984776 | CW31: =MIN(M_MO*CU31,SQRT(CV31*WS_p*(1+SQRT(1+3/(LD_max^2*CV31^2)))/(3*CT31*CD_0))) -> 207.82303 | CX31: =MAX(0,CW31*(CV31-0.5*CT31*CW31^2*CD_0/WS_p-K_ind*WS_p/(0.5*CT31*CW31^2))) -> 1.8477443 | CY31: =IF(CR31>=h_cr,0,(MIN(CR32,h_cr)-CR31)/MAX(0.05,(CX31+CX32)/2)) -> 15.179603 | CZ31: =MAX(0,CV31^2-4*CD_0*K_ind) -> 0.0010784842 | DA31: =MAX(SQRT(2*WS_p/(CT31*CLmax_c)),SQRT(2*WS_p*(CV31-SQRT(CZ31))/(2*CD_0)/CT31)) -> 150.30812 | DB31: =MAX(DA31,MIN(M_MO*CU31,SQRT(2*WS_p*(CV31+SQRT(CZ31))/(2*CD_0)/CT31))) -> 243.23688 | DC31: =DA31/CU31 -> 0.50671862 | DD31: =DB31/CU31 -> 0.82 | EB31: =$AH$6+D_nac/2*1 -> -4.9027996 | EC31: =$AJ$6+D_nac/2*0 -> -2.0075068 | EG31: =d_fus/2*-0.17365 -> -0.34572413 | EH31: =d_fus/2*-0.98481 -> -1.9606828 | EI31: =w_cabin/2*-0.17365 -> -0.32385725 | EJ31: =w_cabin/2*-0.98481 -> -1.8366706 | EM31: =$AX$11+0.95*seat_w -> 1.8135 | EN31: =z_floor+1.1 -> 0.5 | HF31: =HR30 -> 72991.527 | HG31: =HF31*grav/WS_des -> 135.54274 | HH31: =SQRT(AR_*HG31) -> 35.883924 | HI31: =2*HG31/(HH31*(1+taper)) -> 6.0436083 | HJ31: =2/3*HI31*(1+taper+taper^2)/(1+taper) -> 4.2305258 | HK31: =49*MAX(0.5*HG31,HG31-d_fus*HI31*(1-(1-taper)*d_fus/(2*HH31))) -> 5511.4894 | HL31: =27*(c_HT*HJ31*HG31/L_tail+c_VT*HH31*HG31/L_tail) -> 1703.1987 | HM31: =24*S_wet_fus -> 9147.0379 | HN31: =0.043*HF31 -> 3138.6357 | HO31: =1.3*N_eng*14.7*(TW_des*HF31*grav/N_eng/1000)^1.1*EXP(-0.045*BPR) -> 4710.4342 | HP31: =0.17*HF31 -> 12408.56 | HQ31: =SUM(HK31:HP31) -> 36619.355 | HR31: =IF(fuel_frac<0.95,MIN(100*MTOW_frac,(W_crew+W_pl+HQ31)/(1-fuel_frac)),HF31) -> 72991.527 | HY31: =$HX$8 -> 6.5 | HZ31: =$HV$5+seat_w_b*($HW$8*n_SA_b+$HU$5<pax_b) -> -1.84 | IA31: =HY31-L_fus/2 -> -11.31048
A32: =37/50 -> 0.74 | B32: =A32*WS_max -> 4119.054 | C32: =B32/grav -> 420.02661 | D32: =TO_slope*B32 -> 0.21274075 | E32: =TW_2 -> 0.21941554 | F32: =TW_MA -> 0.21104328 | G32: =beta_cr/alpha_cr*(q_cr*CD_0/(beta_cr*B32)+K_ind*beta_cr*B32/q_cr+ROC_cr/V_cr) -> 0.297835 | H32: =MAX(D32:G32) -> 0.297835 | X32: =T15-L_fus/2 -> 3.0228533 | Y32: =V15+-1*U15 -> -1.990925 | Z32: =-1*U15 -> -1.990925 | AA32: =T15 -> 20.833333 | AP32: =x_nose-L_fus/2+0*D_nose/2 -> -13.840532 | AQ32: =-h_cg+D_nose/2+1*D_nose/2 -> -2.9141833 | AY32: =MAX(0,MIN(27,n_rows-1)) -> 24 | AZ32: =x_eco0+AY32*(seat_pitch) -> 25.94 | BD32: =T15-L_fus/2 -> 3.0228533 | BE32: =U15*0.86603 -> 1.7242008 | BF32: =V15+U15*0.5 -> 0.9954625 | BG32: =BD32*COS(RADIANS(view_az))+BE32*SIN(RADIANS(view_az)) -> 3.4239349 | BH32: =BF32*COS(RADIANS(view_el))+(BE32*COS(RADIANS(view_az))-BD32*SIN(RADIANS(view_az)))*SIN(RADIANS(view_el)) -> 0.63922617 | BM32: =$AZ$8+1*(seat_pitch)*($AY$8*n_SA+$AW$5<pax_e) -> 9.74 | BN32: =$AX$5+seat_w*($AY$8*n_SA+$AW$5<pax_e) -> -1.31 | BO32: =BM32-L_fus/2 -> -8.07048 | CA32: =$BX$8+0*lav_len -> 28.25 | CB32: =$BY$8+0*lav_w -> 0.865 | CR32: =27/28*h_abs -> 11055.938 | CS32: =IF(CR32<=11000,288.15-0.0065*CR32,216.65) -> 216.65 | CT32: =IF(CR32<=11000,rho_SL*(CS32/288.15)^4.25588,0.36392*EXP(-(CR32-11000)/6341.62)) -> 0.36072408 | CU32: =SQRT(1.4*287.053*CS32) -> 295.06956 | CV32: =TW_p*(CT32/rho_SL)^lapse_n -> 0.059693335 | CW32: =MIN(M_MO*CU32,SQRT(CV32*WS_p*(1+SQRT(1+3/(LD_max^2*CV32^2)))/(3*CT32*CD_0))) -> 209.48099 | CX32: =MAX(0,CW32*(CV32-0.5*CT32*CW32^2*CD_0/WS_p-K_ind*WS_p/(0.5*CT32*CW32^2))) -> 0.99048613 | CY32: =IF(CR32>=h_cr,0,(MIN(CR33,h_cr)-CR32)/MAX(0.05,(CX32+CX33)/2)) -> 0 | CZ32: =MAX(0,CV32^2-4*CD_0*K_ind) -> 0.00054772686 | DA32: =MAX(SQRT(2*WS_p/(CT32*CLmax_c)),SQRT(2*WS_p*(CV32-SQRT(CZ32))/(2*CD_0)/CT32)) -> 166.66669 | DB32: =MAX(DA32,MIN(M_MO*CU32,SQRT(2*WS_p*(CV32+SQRT(CZ32))/(2*CD_0)/CT32))) -> 241.95704 | DC32: =DA32/CU32 -> 0.56483865 | DD32: =DB32/CU32 -> 0.82 | EG32: =d_fus/2*0 -> 0 | EH32: =d_fus/2*-1 -> -1.990925 | EI32: =w_cabin/2*0 -> 0 | EJ32: =w_cabin/2*-1 -> -1.865 | EM32: =$AX$11+0.95*seat_w -> 1.8135 | EN32: =z_floor+0 -> -0.6 | HF32: =HR31 -> 72991.527 | HG32: =HF32*grav/WS_des -> 135.54274 | HH32: =SQRT(AR_*HG32) -> 35.883924 | HI32: =2*HG32/(HH32*(1+taper)) -> 6.0436083 | HJ32: =2/3*HI32*(1+taper+taper^2)/(1+taper) -> 4.2305258 | HK32: =49*MAX(0.5*HG32,HG32-d_fus*HI32*(1-(1-taper)*d_fus/(2*HH32))) -> 5511.4894 | HL32: =27*(c_HT*HJ32*HG32/L_tail+c_VT*HH32*HG32/L_tail) -> 1703.1987 | HM32: =24*S_wet_fus -> 9147.0379 | HN32: =0.043*HF32 -> 3138.6357 | HO32: =1.3*N_eng*14.7*(TW_des*HF32*grav/N_eng/1000)^1.1*EXP(-0.045*BPR) -> 4710.4343 | HP32: =0.17*HF32 -> 12408.56 | HQ32: =SUM(HK32:HP32) -> 36619.356 | HR32: =IF(fuel_frac<0.95,MIN(100*MTOW_frac,(W_crew+W_pl+HQ32)/(1-fuel_frac)),HF32) -> 72991.528 | HY32: =$HX$8+1*(bus_pitch*(n_rows_b>0))*($HW$8*n_SA_b+$HU$5<pax_b) -> 6.5 | HZ32: =$HV$5+seat_w_b*($HW$8*n_SA_b+$HU$5<pax_b) -> -1.84 | IA32: =HY32-L_fus/2 -> -11.31048
A33: =38/50 -> 0.76 | B33: =A33*WS_max -> 4230.3798 | C33: =B33/grav -> 431.37868 | D33: =TO_slope*B33 -> 0.2184905 | E33: =TW_2 -> 0.21941554 | F33: =TW_MA -> 0.21104328 | G33: =beta_cr/alpha_cr*(q_cr*CD_0/(beta_cr*B33)+K_ind*beta_cr*B33/q_cr+ROC_cr/V_cr) -> 0.29437602 | H33: =MAX(D33:G33) -> 0.29437602 | X33: =T14-L_fus/2 -> -5.3938133 | Y33: =V14+-1*U14 -> -1.990925 | Z33: =-1*U14 -> -1.990925 | AA33: =T14 -> 12.416667 | AP33: =x_nose-L_fus/2 -> -13.840532 | AQ33: =-0.35*d_fus -> -1.3936475 | AY33: =MAX(0,MIN(28,n_rows-1)) -> 24 | AZ33: =x_eco0+AY33*(seat_pitch) -> 25.94 | BD33: =T14-L_fus/2 -> -5.3938133 | BE33: =U14*0.86603 -> 1.7242008 | BF33: =V14+U14*0.5 -> 0.9954625 | BG33: =BD33*COS(RADIANS(view_az))+BE33*SIN(RADIANS(view_az)) -> -3.0236058 | BH33: =BF33*COS(RADIANS(view_el))+(BE33*COS(RADIANS(view_az))-BD33*SIN(RADIANS(view_az)))*SIN(RADIANS(view_el)) -> 2.9256455 | BM33: =$AZ$8+0.8*(seat_pitch)*($AY$8*n_SA+$AW$5<pax_e) -> 9.578 | BN33: =$AX$5+seat_w*($AY$8*n_SA+$AW$5<pax_e) -> -1.31 | BO33: =BM33-L_fus/2 -> -8.23248 | CA33: =$BX$8+1*lav_len -> 29.25 | CB33: =$BY$8+0*lav_w -> 0.865 | CR33: =28/28*h_abs -> 11465.417 | CS33: =IF(CR33<=11000,288.15-0.0065*CR33,216.65) -> 216.65 | CT33: =IF(CR33<=11000,rho_SL*(CS33/288.15)^4.25588,0.36392*EXP(-(CR33-11000)/6341.62)) -> 0.33816814 | CU33: =SQRT(1.4*287.053*CS33) -> 295.06956 | CV33: =TW_p*(CT33/rho_SL)^lapse_n -> 0.054914182 | CW33: =MIN(M_MO*CU33,SQRT(CV33*WS_p*(1+SQRT(1+3/(LD_max^2*CV33^2)))/(3*CT33*CD_0))) -> 211.74842 | CX33: =MAX(0,CW33*(CV33-0.5*CT33*CW33^2*CD_0/WS_p-K_ind*WS_p/(0.5*CT33*CW33^2))) -> 0 | CZ33: =MAX(0,CV33^2-4*CD_0*K_ind) -> 0 | DA33: =MAX(SQRT(2*WS_p/(CT33*CLmax_c)),SQRT(2*WS_p*(CV33-SQRT(CZ33))/(2*CD_0)/CT33)) -> 211.74842 | DB33: =MAX(DA33,MIN(M_MO*CU33,SQRT(2*WS_p*(CV33+SQRT(CZ33))/(2*CD_0)/CT33))) -> 211.74842 | DC33: =DA33/CU33 -> 0.71762206 | DD33: =DB33/CU33 -> 0.71762206 | EB33: =$AH$7+D_nac/2*1 -> 7.1353903 | EC33: =$AJ$7+D_nac/2*0 -> -2.0075068 | EG33: =d_fus/2*0.17365 -> 0.34572413 | EH33: =d_fus/2*-0.98481 -> -1.9606828 | EI33: =w_cabin/2*0.17365 -> 0.32385725 | EJ33: =w_cabin/2*-0.98481 -> -1.8366706 | EM33: =$AX$12+0.05*seat_w -> 1.3365 | EN33: =z_floor+0 -> -0.6 | HF33: =HR32 -> 72991.528 | HG33: =HF33*grav/WS_des -> 135.54274 | HH33: =SQRT(AR_*HG33) -> 35.883925 | HI33: =2*HG33/(HH33*(1+taper)) -> 6.0436083 | HJ33: =2/3*HI33*(1+taper+taper^2)/(1+taper) -> 4.2305258 | HK33: =49*MAX(0.5*HG33,HG33-d_fus*HI33*(1-(1-taper)*d_fus/(2*HH33))) -> 5511.4894 | HL33: =27*(c_HT*HJ33*HG33/L_tail+c_VT*HH33*HG33/L_tail) -> 1703.1987 | HM33: =24*S_wet_fus -> 9147.0379 | HN33: =0.043*HF33 -> 3138.6357 | HO33: =1.3*N_eng*14.7*(TW_des*HF33*grav/N_eng/1000)^1.1*EXP(-0.045*BPR) -> 4710.4343 | HP33: =0.17*HF33 -> 12408.56 | HQ33: =SUM(HK33:HP33) -> 36619.356 | HR33: =IF(fuel_frac<0.95,MIN(100*MTOW_frac,(W_crew+W_pl+HQ33)/(1-fuel_frac)),HF33) -> 72991.528 | HY33: =$HX$8+0.8*(bus_pitch*(n_rows_b>0))*($HW$8*n_SA_b+$HU$5<pax_b) -> 6.5 | HZ33: =$HV$5+seat_w_b*($HW$8*n_SA_b+$HU$5<pax_b) -> -1.84 | IA33: =HY33-L_fus/2 -> -11.31048
A34: =39/50 -> 0.78 | B34: =A34*WS_max -> 4341.7055 | C34: =B34/grav -> 442.73075 | D34: =TO_slope*B34 -> 0.22424025 | E34: =TW_2 -> 0.21941554 | F34: =TW_MA -> 0.21104328 | G34: =beta_cr/alpha_cr*(q_cr*CD_0/(beta_cr*B34)+K_ind*beta_cr*B34/q_cr+ROC_cr/V_cr) -> 0.29118922 | H34: =MAX(D34:G34) -> 0.29118922 | X34: =T13-L_fus/2 -> -13.81048 | Y34: =V13+-1*U13 -> -1.990925 | Z34: =-1*U13 -> -1.990925 | AA34: =T13 -> 4 | AY34: =MAX(0,MIN(29,n_rows-1)) -> 24 | AZ34: =x_eco0+AY34*(seat_pitch) -> 25.94 | BD34: =T13-L_fus/2 -> -13.81048 | BE34: =U13*0.86603 -> 1.7242008 | BF34: =V13+U13*0.5 -> 0.9954625 | BG34: =BD34*COS(RADIANS(view_az))+BE34*SIN(RADIANS(view_az)) -> -9.4711466 | BH34: =BF34*COS(RADIANS(view_el))+(BE34*COS(RADIANS(view_az))-BD34*SIN(RADIANS(view_az)))*SIN(RADIANS(view_el)) -> 5.2120648 | BM34: =$AZ$8+0.8*(seat_pitch)*($AY$8*n_SA+$AW$5<pax_e) -> 9.578 | BN34: =$AX$5 -> -1.84 | BO34: =BM34-L_fus/2 -> -8.23248 | CA34: =$BX$8+1*lav_len -> 29.25 | CB34: =$BY$8+1*lav_w -> 1.865 | EB34: =$AH$7+D_nac/2*0.86603 -> 6.9858402 | EC34: =$AJ$7+D_nac/2*0.5 -> -1.4493592 | EG34: =d_fus/2*0.34202 -> 0.68093617 | EH34: =d_fus/2*-0.93969 -> -1.8708523 | EI34: =w_cabin/2*0.34202 -> 0.6378673 | EJ34: =w_cabin/2*-0.93969 -> -1.7525218 | EM34: =$AX$12+0.05*seat_w -> 1.3365 | EN34: =z_floor+1.1 -> 0.5 | HF34: =HR33 -> 72991.528 | HG34: =HF34*grav/WS_des -> 135.54274 | HH34: =SQRT(AR_*HG34) -> 35.883925 | HI34: =2*HG34/(HH34*(1+taper)) -> 6.0436084 | HJ34: =2/3*HI34*(1+taper+taper^2)/(1+taper) -> 4.2305258 | HK34: =49*MAX(0.5*HG34,HG34-d_fus*HI34*(1-(1-taper)*d_fus/(2*HH34))) -> 5511.4894 | HL34: =27*(c_HT*HJ34*HG34/L_tail+c_VT*HH34*HG34/L_tail) -> 1703.1987 | HM34: =24*S_wet_fus -> 9147.0379 | HN34: =0.043*HF34 -> 3138.6357 | HO34: =1.3*N_eng*14.7*(TW_des*HF34*grav/N_eng/1000)^1.1*EXP(-0.045*BPR) -> 4710.4343 | HP34: =0.17*HF34 -> 12408.56 | HQ34: =SUM(HK34:HP34) -> 36619.356 | HR34: =IF(fuel_frac<0.95,MIN(100*MTOW_frac,(W_crew+W_pl+HQ34)/(1-fuel_frac)),HF34) -> 72991.528 | HY34: =$HX$8+0.8*(bus_pitch*(n_rows_b>0))*($HW$8*n_SA_b+$HU$5<pax_b) -> 6.5 | HZ34: =$HV$5 -> -1.84 | IA34: =HY34-L_fus/2 -> -11.31048
A35: =40/50 -> 0.8 | B35: =A35*WS_max -> 4453.0313 | C35: =B35/grav -> 454.08282 | D35: =TO_slope*B35 -> 0.22999 | E35: =TW_2 -> 0.21941554 | F35: =TW_MA -> 0.21104328 | G35: =beta_cr/alpha_cr*(q_cr*CD_0/(beta_cr*B35)+K_ind*beta_cr*B35/q_cr+ROC_cr/V_cr) -> 0.2882542 | H35: =MAX(D35:G35) -> 0.2882542 | X35: =T12-L_fus/2 -> -14.61048 | Y35: =V12+-1*U12 -> -1.9627676 | Z35: =-1*U12 -> -1.9507001 | AA35: =T12 -> 3.2 | AP35: =-1*0.48*B_box -> -18.807867 | AQ35: =-h_cg -> -3.663302 | AY35: =MAX(0,MIN(30,n_rows-1)) -> 24 | AZ35: =x_eco0+AY35*(seat_pitch) -> 25.94 | BD35: =T12-L_fus/2 -> -14.61048 | BE35: =U12*0.86603 -> 1.6893648 | BF35: =V12+U12*0.5 -> 0.96328262 | BG35: =BD35*COS(RADIANS(view_az))+BE35*SIN(RADIANS(view_az)) -> -10.106374 | BH35: =BF35*COS(RADIANS(view_el))+(BE35*COS(RADIANS(view_az))-BD35*SIN(RADIANS(view_az)))*SIN(RADIANS(view_el)) -> 5.388945 | BM35: =$AZ$8+0.2*(seat_pitch)*($AY$8*n_SA+$AW$5<pax_e) -> 9.092 | BN35: =$AX$5 -> -1.84 | BO35: =BM35-L_fus/2 -> -8.71848 | CA35: =$BX$8+0*lav_len -> 28.25 | CB35: =$BY$8+1*lav_w -> 1.865 | EB35: =$AH$7+D_nac/2*0.5 -> 6.5772426 | EC35: =$AJ$7+D_nac/2*0.86603 -> -1.0407616 | EG35: =d_fus/2*0.5 -> 0.9954625 | EH35: =d_fus/2*-0.86603 -> -1.7242008 | EI35: =w_cabin/2*0.5 -> 0.9325 | EJ35: =w_cabin/2*-0.86603 -> -1.6151459 | EM35: =$AX$12+0.95*seat_w -> 1.8135 | EN35: =z_floor+1.1 -> 0.5 | HF35: =HR34 -> 72991.528 | HG35: =HF35*grav/WS_des -> 135.54274 | HH35: =SQRT(AR_*HG35) -> 35.883925 | HI35: =2*HG35/(HH35*(1+taper)) -> 6.0436084 | HJ35: =2/3*HI35*(1+taper+taper^2)/(1+taper) -> 4.2305258 | HK35: =49*MAX(0.5*HG35,HG35-d_fus*HI35*(1-(1-taper)*d_fus/(2*HH35))) -> 5511.4894 | HL35: =27*(c_HT*HJ35*HG35/L_tail+c_VT*HH35*HG35/L_tail) -> 1703.1987 | HM35: =24*S_wet_fus -> 9147.0379 | HN35: =0.043*HF35 -> 3138.6357 | HO35: =1.3*N_eng*14.7*(TW_des*HF35*grav/N_eng/1000)^1.1*EXP(-0.045*BPR) -> 4710.4343 | HP35: =0.17*HF35 -> 12408.56 | HQ35: =SUM(HK35:HP35) -> 36619.356 | HR35: =IF(fuel_frac<0.95,MIN(100*MTOW_frac,(W_crew+W_pl+HQ35)/(1-fuel_frac)),HF35) -> 72991.528 | HY35: =$HX$8+0.2*(bus_pitch*(n_rows_b>0))*($HW$8*n_SA_b+$HU$5<pax_b) -> 6.5 | HZ35: =$HV$5 -> -1.84 | IA35: =HY35-L_fus/2 -> -11.31048
A36: =41/50 -> 0.82 | B36: =A36*WS_max -> 4564.3571 | C36: =B36/grav -> 465.43489 | D36: =TO_slope*B36 -> 0.23573975 | E36: =TW_2 -> 0.21941554 | F36: =TW_MA -> 0.21104328 | G36: =beta_cr/alpha_cr*(q_cr*CD_0/(beta_cr*B36)+K_ind*beta_cr*B36/q_cr+ROC_cr/V_cr) -> 0.28555253 | H36: =MAX(D36:G36) -> 0.28555253 | X36: =T11-L_fus/2 -> -15.41048 | Y36: =V11+-1*U11 -> -1.8745765 | Z36: =-1*U11 -> -1.8247129 | AA36: =T11 -> 2.4 | AP36: =1*0.48*B_box -> 18.807867 | AQ36: =-h_cg -> -3.663302 | AY36: =MAX(0,MIN(31,n_rows-1)) -> 24 | AZ36: =x_eco0+AY36*(seat_pitch) -> 25.94 | BD36: =T11-L_fus/2 -> -15.41048 | BE36: =U11*0.86603 -> 1.5802561 | BF36: =V11+U11*0.5 -> 0.86249282 | BG36: =BD36*COS(RADIANS(view_az))+BE36*SIN(RADIANS(view_az)) -> -10.789344 | BH36: =BF36*COS(RADIANS(view_el))+(BE36*COS(RADIANS(view_az))-BD36*SIN(RADIANS(view_az)))*SIN(RADIANS(view_el)) -> 5.4795982 | BM36: =$AZ$8+(seat_pitch) -> 9.74 | BN36: =$AX$5 -> -1.84 | BO36: =BM36-L_fus/2 -> -8.07048 | CA36: =$BX$8+0*lav_len -> 28.25 | CB36: =$BY$8+0*lav_w -> 0.865 | EB36: =$AH$7+D_nac/2*0 -> 6.0190949 | EC36: =$AJ$7+D_nac/2*1 -> -0.8912115 | EG36: =d_fus/2*0.64279 -> 1.2797467 | EH36: =d_fus/2*-0.76604 -> -1.5251282 | EI36: =w_cabin/2*0.64279 -> 1.1988033 | EJ36: =w_cabin/2*-0.76604 -> -1.4286646 | EM36: =$AX$12+0.95*seat_w -> 1.8135 | EN36: =z_floor+0 -> -0.6 | HF36: =HR35 -> 72991.528 | HG36: =HF36*grav/WS_des -> 135.54274 | HH36: =SQRT(AR_*HG36) -> 35.883925 | HI36: =2*HG36/(HH36*(1+taper)) -> 6.0436084 | HJ36: =2/3*HI36*(1+taper+taper^2)/(1+taper) -> 4.2305258 | HK36: =49*MAX(0.5*HG36,HG36-d_fus*HI36*(1-(1-taper)*d_fus/(2*HH36))) -> 5511.4894 | HL36: =27*(c_HT*HJ36*HG36/L_tail+c_VT*HH36*HG36/L_tail) -> 1703.1987 | HM36: =24*S_wet_fus -> 9147.0379 | HN36: =0.043*HF36 -> 3138.6357 | HO36: =1.3*N_eng*14.7*(TW_des*HF36*grav/N_eng/1000)^1.1*EXP(-0.045*BPR) -> 4710.4343 | HP36: =0.17*HF36 -> 12408.56 | HQ36: =SUM(HK36:HP36) -> 36619.356 | HR36: =IF(fuel_frac<0.95,MIN(100*MTOW_frac,(W_crew+W_pl+HQ36)/(1-fuel_frac)),HF36) -> 72991.528 | HY36: =$HX$8+(bus_pitch*(n_rows_b>0)) -> 6.5 | HZ36: =$HV$5 -> -1.84 | IA36: =HY36-L_fus/2 -> -11.31048
A37: =42/50 -> 0.84 | B37: =A37*WS_max -> 4675.6829 | C37: =B37/grav -> 476.78696 | D37: =TO_slope*B37 -> 0.2414895 | E37: =TW_2 -> 0.21941554 | F37: =TW_MA -> 0.21104328 | G37: =beta_cr/alpha_cr*(q_cr*CD_0/(beta_cr*B37)+K_ind*beta_cr*B37/q_cr+ROC_cr/V_cr) -> 0.28306754 | H37: =MAX(D37:G37) -> 0.28306754 | X37: =T10-L_fus/2 -> -16.01048 | Y37: =V10+-1*U10 -> -1.7612026 | Z37: =-1*U10 -> -1.6627502 | AA37: =T10 -> 1.8 | AY37: =MAX(0,MIN(32,n_rows-1)) -> 24 | AZ37: =x_eco0+AY37*(seat_pitch) -> 25.94 | BD37: =T10-L_fus/2 -> -16.01048 | BE37: =U10*0.86603 -> 1.4399915 | BF37: =V10+U10*0.5 -> 0.73292265 | BG37: =BD37*COS(RADIANS(view_az))+BE37*SIN(RADIANS(view_az)) -> -11.339131 | BH37: =BF37*COS(RADIANS(view_el))+(BE37*COS(RADIANS(view_az))-BD37*SIN(RADIANS(view_az)))*SIN(RADIANS(view_el)) -> 5.4797501 | BM37: =$AZ$9+0.2*(seat_pitch)*($AY$9*n_SA+$AW$5<pax_e) -> 9.902 | BN37: =$AX$5 -> -1.84 | BO37: =BM37-L_fus/2 -> -7.90848 | CA37: =$BX$8+1*lav_len -> 29.25 | CB37: =$BY$8+1*lav_w -> 1.865 | EB37: =$AH$7+D_nac/2*-0.5 -> 5.4609472 | EC37: =$AJ$7+D_nac/2*0.86603 -> -1.0407616 | EG37: =d_fus/2*0.76604 -> 1.5251282 | EH37: =d_fus/2*-0.64279 -> -1.2797467 | EI37: =w_cabin/2*0.76604 -> 1.4286646 | EJ37: =w_cabin/2*-0.64279 -> -1.1988033 | EM37: =$AX$13+0.05*seat_w -> 1.3365 | EN37: =z_floor+0 -> -0.6 | HF37: =HR36 -> 72991.528 | HG37: =HF37*grav/WS_des -> 135.54274 | HH37: =SQRT(AR_*HG37) -> 35.883925 | HI37: =2*HG37/(HH37*(1+taper)) -> 6.0436084 | HJ37: =2/3*HI37*(1+taper+taper^2)/(1+taper) -> 4.2305258 | HK37: =49*MAX(0.5*HG37,HG37-d_fus*HI37*(1-(1-taper)*d_fus/(2*HH37))) -> 5511.4894 | HL37: =27*(c_HT*HJ37*HG37/L_tail+c_VT*HH37*HG37/L_tail) -> 1703.1987 | HM37: =24*S_wet_fus -> 9147.0379 | HN37: =0.043*HF37 -> 3138.6357 | HO37: =1.3*N_eng*14.7*(TW_des*HF37*grav/N_eng/1000)^1.1*EXP(-0.045*BPR) -> 4710.4343 | HP37: =0.17*HF37 -> 12408.56 | HQ37: =SUM(HK37:HP37) -> 36619.356 | HR37: =IF(fuel_frac<0.95,MIN(100*MTOW_frac,(W_crew+W_pl+HQ37)/(1-fuel_frac)),HF37) -> 72991.528 | HY37: =$HX$9+0.2*(bus_pitch*(n_rows_b>0))*($HW$9*n_SA_b+$HU$5<pax_b) -> 6.5 | HZ37: =$HV$5 -> -1.84 | IA37: =HY37-L_fus/2 -> -11.31048
A38: =43/50 -> 0.86 | B38: =A38*WS_max -> 4787.0087 | C38: =B38/grav -> 488.13904 | D38: =TO_slope*B38 -> 0.24723925 | E38: =TW_2 -> 0.21941554 | F38: =TW_MA -> 0.21104328 | G38: =beta_cr/alpha_cr*(q_cr*CD_0/(beta_cr*B38)+K_ind*beta_cr*B38/q_cr+ROC_cr/V_cr) -> 0.28078412 | H38: =MAX(D38:G38) -> 0.28078412 | X38: =T9-L_fus/2 -> -16.61048 | Y38: =V9+-1*U9 -> -1.5925409 | Z38: =-1*U9 -> -1.4218048 | AA38: =T9 -> 1.2 | AY38: =MAX(0,MIN(33,n_rows-1)) -> 24 | AZ38: =x_eco0+AY38*(seat_pitch) -> 25.94 | BD38: =T9-L_fus/2 -> -16.61048 | BE38: =U9*0.86603 -> 1.2313256 | BF38: =V9+U9*0.5 -> 0.54016637 | BG38: =BD38*COS(RADIANS(view_az))+BE38*SIN(RADIANS(view_az)) -> -11.932885 | BH38: =BF38*COS(RADIANS(view_el))+(BE38*COS(RADIANS(view_az))-BD38*SIN(RADIANS(view_az)))*SIN(RADIANS(view_el)) -> 5.4004915 | BM38: =$AZ$9+0.2*(seat_pitch)*($AY$9*n_SA+$AW$5<pax_e) -> 9.902 | BN38: =$AX$5+seat_w*($AY$9*n_SA+$AW$5<pax_e) -> -1.31 | BO38: =BM38-L_fus/2 -> -7.90848 | CA38: =$BX$8+1*lav_len -> 29.25 | CB38: =$BY$8+0*lav_w -> 0.865 | EB38: =$AH$7+D_nac/2*-0.86603 -> 5.0523497 | EC38: =$AJ$7+D_nac/2*0.5 -> -1.4493592 | EG38: =d_fus/2*0.86603 -> 1.7242008 | EH38: =d_fus/2*-0.5 -> -0.9954625 | EI38: =w_cabin/2*0.86603 -> 1.6151459 | EJ38: =w_cabin/2*-0.5 -> -0.9325 | EM38: =$AX$13+0.05*seat_w -> 1.3365 | EN38: =z_floor+1.1 -> 0.5 | HF38: =HR37 -> 72991.528 | HG38: =HF38*grav/WS_des -> 135.54274 | HH38: =SQRT(AR_*HG38) -> 35.883925 | HI38: =2*HG38/(HH38*(1+taper)) -> 6.0436084 | HJ38: =2/3*HI38*(1+taper+taper^2)/(1+taper) -> 4.2305258 | HK38: =49*MAX(0.5*HG38,HG38-d_fus*HI38*(1-(1-taper)*d_fus/(2*HH38))) -> 5511.4894 | HL38: =27*(c_HT*HJ38*HG38/L_tail+c_VT*HH38*HG38/L_tail) -> 1703.1987 | HM38: =24*S_wet_fus -> 9147.0379 | HN38: =0.043*HF38 -> 3138.6357 | HO38: =1.3*N_eng*14.7*(TW_des*HF38*grav/N_eng/1000)^1.1*EXP(-0.045*BPR) -> 4710.4343 | HP38: =0.17*HF38 -> 12408.56 | HQ38: =SUM(HK38:HP38) -> 36619.356 | HR38: =IF(fuel_frac<0.95,MIN(100*MTOW_frac,(W_crew+W_pl+HQ38)/(1-fuel_frac)),HF38) -> 72991.528 | HY38: =$HX$9+0.2*(bus_pitch*(n_rows_b>0))*($HW$9*n_SA_b+$HU$5<pax_b) -> 6.5 | HZ38: =$HV$5+seat_w_b*($HW$9*n_SA_b+$HU$5<pax_b) -> -1.84 | IA38: =HY38-L_fus/2 -> -11.31048
A39: =44/50 -> 0.88 | B39: =A39*WS_max -> 4898.3345 | C39: =B39/grav -> 499.49111 | D39: =TO_slope*B39 -> 0.252989 | E39: =TW_2 -> 0.21941554 | F39: =TW_MA -> 0.21104328 | G39: =beta_cr/alpha_cr*(q_cr*CD_0/(beta_cr*B39)+K_ind*beta_cr*B39/q_cr+ROC_cr/V_cr) -> 0.27868853 | H39: =MAX(D39:G39) -> 0.27868853 | X39: =T8-L_fus/2 -> -17.21048 | Y39: =V8+-1*U8 -> -1.3314269 | Z39: =-1*U8 -> -1.0487848 | AA39: =T8 -> 0.6 | AY39: =MAX(0,MIN(34,n_rows-1)) -> 24 | AZ39: =x_eco0+AY39*(seat_pitch) -> 25.94 | BD39: =T8-L_fus/2 -> -17.21048 | BE39: =U8*0.86603 -> 0.90827912 | BF39: =V8+U8*0.5 -> 0.24175036 | BG39: =BD39*COS(RADIANS(view_az))+BE39*SIN(RADIANS(view_az)) -> -12.600162 | BH39: =BF39*COS(RADIANS(view_el))+(BE39*COS(RADIANS(view_az))-BD39*SIN(RADIANS(view_az)))*SIN(RADIANS(view_el)) -> 5.1884425 | BM39: =$AZ$9 -> 9.74 | BN39: =$AX$5+seat_w*($AY$9*n_SA+$AW$5<pax_e) -> -1.31 | BO39: =BM39-L_fus/2 -> -8.07048 | CA39: =$BX$8+0*lav_len -> 28.25 | CB39: =$BY$8+1*lav_w -> 1.865 | EB39: =$AH$7+D_nac/2*-1 -> 4.9027996 | EC39: =$AJ$7+D_nac/2*0 -> -2.0075068 | EG39: =d_fus/2*0.93969 -> 1.8708523 | EH39: =d_fus/2*-0.34202 -> -0.68093617 | EI39: =w_cabin/2*0.93969 -> 1.7525218 | EJ39: =w_cabin/2*-0.34202 -> -0.6378673 | EM39: =$AX$13+0.95*seat_w -> 1.8135 | EN39: =z_floor+1.1 -> 0.5 | HF39: =HR38 -> 72991.528 | HG39: =HF39*grav/WS_des -> 135.54274 | HH39: =SQRT(AR_*HG39) -> 35.883925 | HI39: =2*HG39/(HH39*(1+taper)) -> 6.0436084 | HJ39: =2/3*HI39*(1+taper+taper^2)/(1+taper) -> 4.2305258 | HK39: =49*MAX(0.5*HG39,HG39-d_fus*HI39*(1-(1-taper)*d_fus/(2*HH39))) -> 5511.4894 | HL39: =27*(c_HT*HJ39*HG39/L_tail+c_VT*HH39*HG39/L_tail) -> 1703.1987 | HM39: =24*S_wet_fus -> 9147.0379 | HN39: =0.043*HF39 -> 3138.6357 | HO39: =1.3*N_eng*14.7*(TW_des*HF39*grav/N_eng/1000)^1.1*EXP(-0.045*BPR) -> 4710.4343 | HP39: =0.17*HF39 -> 12408.56 | HQ39: =SUM(HK39:HP39) -> 36619.356 | HR39: =IF(fuel_frac<0.95,MIN(100*MTOW_frac,(W_crew+W_pl+HQ39)/(1-fuel_frac)),HF39) -> 72991.528 | HY39: =$HX$9 -> 6.5 | HZ39: =$HV$5+seat_w_b*($HW$9*n_SA_b+$HU$5<pax_b) -> -1.84 | IA39: =HY39-L_fus/2 -> -11.31048
A40: =45/50 -> 0.9 | B40: =A40*WS_max -> 5009.6602 | C40: =B40/grav -> 510.84318 | D40: =TO_slope*B40 -> 0.25873875 | E40: =TW_2 -> 0.21941554 | F40: =TW_MA -> 0.21104328 | G40: =beta_cr/alpha_cr*(q_cr*CD_0/(beta_cr*B40)+K_ind*beta_cr*B40/q_cr+ROC_cr/V_cr) -> 0.27676823 | H40: =MAX(D40:G40) -> 0.27676823 | X40: =T7-L_fus/2 -> -17.53048 | Y40: =V7+-1*U7 -> -1.1095259 | Z40: =-1*U7 -> -0.73178344 | AA40: =T7 -> 0.28 | AY40: =MAX(0,MIN(35,n_rows-1)) -> 24 | AZ40: =x_eco0+AY40*(seat_pitch) -> 25.94 | BD40: =T7-L_fus/2 -> -17.53048 | BE40: =U7*0.86603 -> 0.63374641 | BF40: =V7+U7*0.5 -> -0.011850752 | BG40: =BD40*COS(RADIANS(view_az))+BE40*SIN(RADIANS(view_az)) -> -13.021762 | BH40: =BF40*COS(RADIANS(view_el))+(BE40*COS(RADIANS(view_az))-BD40*SIN(RADIANS(view_az)))*SIN(RADIANS(view_el)) -> 4.9566526 | BM40: =$AZ$9+1*(seat_pitch)*($AY$9*n_SA+$AW$5<pax_e) -> 10.55 | BN40: =$AX$5+seat_w*($AY$9*n_SA+$AW$5<pax_e) -> -1.31 | BO40: =BM40-L_fus/2 -> -7.26048 | EB40: =$AH$7+D_nac/2*-0.86603 -> 5.0523497 | EC40: =$AJ$7+D_nac/2*-0.5 -> -2.5656545 | EG40: =d_fus/2*0.98481 -> 1.9606828 | EH40: =d_fus/2*-0.17365 -> -0.34572413 | EI40: =w_cabin/2*0.98481 -> 1.8366706 | EJ40: =w_cabin/2*-0.17365 -> -0.32385725 | EM40: =$AX$13+0.95*seat_w -> 1.8135 | EN40: =z_floor+0 -> -0.6 | HF40: =HR39 -> 72991.528 | HG40: =HF40*grav/WS_des -> 135.54274 | HH40: =SQRT(AR_*HG40) -> 35.883925 | HI40: =2*HG40/(HH40*(1+taper)) -> 6.0436084 | HJ40: =2/3*HI40*(1+taper+taper^2)/(1+taper) -> 4.2305259 | HK40: =49*MAX(0.5*HG40,HG40-d_fus*HI40*(1-(1-taper)*d_fus/(2*HH40))) -> 5511.4894 | HL40: =27*(c_HT*HJ40*HG40/L_tail+c_VT*HH40*HG40/L_tail) -> 1703.1987 | HM40: =24*S_wet_fus -> 9147.0379 | HN40: =0.043*HF40 -> 3138.6357 | HO40: =1.3*N_eng*14.7*(TW_des*HF40*grav/N_eng/1000)^1.1*EXP(-0.045*BPR) -> 4710.4343 | HP40: =0.17*HF40 -> 12408.56 | HQ40: =SUM(HK40:HP40) -> 36619.356 | HR40: =IF(fuel_frac<0.95,MIN(100*MTOW_frac,(W_crew+W_pl+HQ40)/(1-fuel_frac)),HF40) -> 72991.528 | HY40: =$HX$9+1*(bus_pitch*(n_rows_b>0))*($HW$9*n_SA_b+$HU$5<pax_b) -> 6.5 | HZ40: =$HV$5+seat_w_b*($HW$9*n_SA_b+$HU$5<pax_b) -> -1.84 | IA40: =HY40-L_fus/2 -> -11.31048
